Workbook
Name _Datos: 'ASISTENCIA 2 (2)'!$G1:$AK1
Name _Datos: 'ASISTENCIA OCTUBRE'!$I1:$AM1
Name _Datos: 'TAREO HORAS EXTRAS'!$G1:$AK1
Name _Fechafinal: 'SET - OCT'!$AX$9
Name _Fechainicial: 'ASISTENCIA 2 (2)'!A$8
Name _Fechainicial: 'ASISTENCIA OCTUBRE'!A$8
Name _Fechainicial: 'TAREO HORAS EXTRAS'!A$8
Name _Fechainicial1: 'SET - OCT'!A$9
Name _Fechainicial1: 'SET - OCT'!A$9
Name _FECHAINICIAL2: 'OCT - NOV'!A$9
Name _FECHAINICIAL2: 'OCT - NOV'!A$9
Name _FECHAINICIAL3: 'NOV - DIC'!A$9
Name _FechaSiguiente: 'ASISTENCIA 2 (2)'!B$8
Name _FechaSiguiente: 'ASISTENCIA OCTUBRE'!B$8
Name _Fechasiguiente: 'SET - OCT'!B$9
Name _Fechasiguiente: 'SET - OCT'!B$9
Name _FechaSiguiente: 'TAREO HORAS EXTRAS'!B$8
Name _FECHASIGUIENTE2: 'OCT - NOV'!B$9
Name _FECHASIGUIENTE2: 'OCT - NOV'!B$9
Name _FECHASIGUIENTE3: 'NOV - DIC'!B$9
Name _HorasExtras: 'ASISTENCIA 2 (2)'!$AO$4
Name _HorasExtras: 'ASISTENCIA OCTUBRE'!$AQ$4
Name _HorasExtras: 'TAREO HORAS EXTRAS'!$AO$4
Name _NOMBRES: DATOS[NOMBRES]
Name _PorEncimade: 'ASISTENCIA 2 (2)'!$AO$6
Name _PorEncimade: 'ASISTENCIA OCTUBRE'!$AQ$6
Name _PorEncimade: 'TAREO HORAS EXTRAS'!$AO$6
Name LMeses: TMESES[[MES ]]
Name LMeses: TMESES[[MES ]]
Name LMeses: TMESES[[MES ]]
Name nFestivos: tFestivos4[[#All],[Festivos]]
Name nFestivos: tFestivos46[[#All],[Festivos]]
Name nFestivos: tFestivos[[#All],[Festivos]]

Sheet DATOS GRALES
B1: NOMBRES | C1: DNI
A2: 1 | B2: NAVARRO LOZANO, ANGEL JAROL | C2: 75396402
A3: 2 | B3: JEREMIAS PALOMINO, NORBERTO LEONCIO | C3: 44184914
A4: 3 | B4: LOZANO MALDONADO, HERNAN | C4: 40839932
A5: 4 | B5: PIÑA CHUJANDAMA, KEVIN | C5: 70833343
A6: 5 | B6: MAYTAHUARI ACOSTA, SAMMER AXEL | C6: 48492558
A7: 6 | B7: CORDOVA ANGULO, JUAN | C7: 40889884
A8: 7 | B8: ROJAS SANDOVAL, JAVIER ELOY | C8: 40861767
A9: 8 | B9: CHINO PILCO SIMON | C9: 00487377
A10: 9
A11: 10
A12: 11
A13: 12
A14: 13
A15: 14
A16: 15
A17: 16
A18: 17
A19: 18
A20: 19
A21: 20
... A36: 35

Sheet DATOS GRALES 1
A1: N° | B1: NOMBRES | C1: DNI | D1: CLASE | E1: CARGO | F1: Columna1 | G1: NRO CUENTA BBVA | H1: CCI BBVA | I1: NRO CUENTA BCP | J1: CCI BCP | K1: NRO CUENTA INTERBANK | L1: CCI INTERBANK
A2: 1 | B2: NAVARRO LOZANO, ANGEL JAROL | C2: 75396402 | D2: OBRERO | E2: PEON | I2: 48099576706093 | J2: 002480199576706093-22
A3: 2 | B3: JEREMIAS PALOMINO, NORBERTO LEONCIO | C3: 44184914 | D3: OBRERO | E3: PEON | I3: 40594770093053 | J3: 00240519477009305391
A4: 3 | B4: LOZANO MALDONADO, HERNAN | C4: 40839932 | D4: OBRERO | E4: PEON | I4: 48008842398077 | J4: 00248010884239807724
A5: 4 | B5: PIÑA CHUJANDAMA, KEVIN | C5: 70833343 | D5: OBRERO | E5: PEON | I5: 54095302262034 | J5: 00254019530226203437
A6: 5 | B6: MAYTAHUARI ACOSTA, SAMMER AXEL | C6: 48492558 | D6: OBRERO | E6: OPERARIO | F6: CARPINTERO | I6: 54096578590053
A7: 6 | B7: CORDOVA ANGULO, JUAN | C7: 40889884 | D7: OBRERO | E7: PEON | I7: 54009616015070
A8: 7 | B8: ROJAS SANDOVAL, JAVIER ELOY | C8: 40861767 | D8: OBRERO | E8: OPERARIO/VOLQUETERO | F8: VOLQUETERO | G8: 0011-0814-0282771654 | H8: 011-814-000282771654-15
A9: 8 | B9: CHINO PILCO SIMON | C9: 00487377 | D9: OBRERO | E9: PEON/CHOFER
A10: 9 | B10: ACUACHI LANCHIPA, ERNESTO ALONSO | C10: 41056694 | D10: PERSONAL NO CLAVE | E10: LOGISTICO | K10: 342-3123820927 | L10: 003-342-013123820927-37
A11: 10 | B11: ALEJO CHARCA, DENNYS MIRIAM | C11: 76470794 | D11: PERSONAL CLAVE | E11: ING. CALIDAD | I11: 54074340317053 | J11: 00254017434031705337
A12: 11 | B12: SILVA BORDA, ARLETTE NINOSKA | C12: 71234038 | D12: PERSONAL NO CLAVE | E12: ASIS. ING. | G12: 0011-0814-0277651071 | H12: 011-814-000277651071-17
A13: 12 | B13: ADUVIRE ARGUATA, MARIO ARTURO | C13: 00662471 | D13: OBRERO | E13: MAESTRO OBRA | G13: 0011-0232-0201494909 | H13: 011-232-000201494909-69
A14: 13 | B14: SALAZAR BAZAN, ROCÍO DALILA | C14: 26683098 | D14: PERSONAL CLAVE | E14: RESIDENTE | I14: 54039320324023 | J14: 00254013932032402337
A15: 14 | B15: CHACON ORTIZ, JOSE ANTONIO | C15: 00515241 | D15: OBRERO | E15: OPERARIO | F15: CARPINTERO | G15: 0011-0814-0282789561 | H15: 011-814-000282789561-12
A16: 15 | B16: ORDOÑEZ CONDORI, GILBERTO | C16: 44723682 | D16: OBRERO | E16: PEON | G16: 0011-0814-0282772960 | H16: 011-814-000282772960-15
A17: 16 | B17: GUTARATE SABINO, ADRIEL ANTONY | C17: 78202475 | D17: OBRERO | E17: OPERARIO | F17: fierro | G17: 0011-0814-0282782036 | H17: 011-814-000282782036-12
A18: 17 | B18: QUISPE LIMACHE, ROGELIO | C18: 44758063 | D18: OBRERO | E18: OPERARIO | F18: albañil | G18: 0011-0232-0201496596 | H18: 011-232-000201496596-62
A19: 18 | B19: APASTEGUI GRANDEZ, LUIS ALFREDO | C19: 46906026 | D19: OBRERO | E19: PEON | G19: 0011-0814-0282770674 | H19: 011-814-000282770674-14
A20: 19 | B20: LOZA YAPUCHURA, KENNY GUILLERMO | C20: 72188706 | D20: PERSONA CLAVE | E20: TOPOGRAFO | I20: 54003775270027 | J20: 00254010377527002739
A21: 20 | B21: VILLEGAS, ROGER | D21: OBRERO | E21: OPERARIO MAQU.
A22: 21 | B22: TUANAMA PILCO, CHRIS | C22: 74367601 | D22: OBRERO | E22: PEON | G22: 0011-0814-0281980403 | H22: 011-814-000281980403-16
A23: 22 | B23: CACERES CALACHUA, YEYSON JORGE | C23: 47109805 | D23: OBRERO | E23: OPERARIO | F23: fierro | I23: 42510879044040 | J23: 00242511087904404078
A24: 23 | B24: ACOSTA ROJAS, JOSEPH ALFONSO | C24: 70522697 | D24: PERSONAL CLAVE | E24: REPRESENTANTE
A25: 24 | B25: YEANCARLO | D25: PERSONAL CLAVE | E25: ASIS. ING.
A26: 25 | B26: ESCOBAR PALACIOS, LUIS IVAN | D26: PERSONAL CLAVE | E26: ESP. SEGURIDAD
A27: 26 | B27: MAQUERA QUISPE, LEONIDAS EDWIN | C27: 41018582 | D27: OBRERO | E27: OPERARIO | F27: CARPINTERO | G27: 0011-0814-0267066219 | H27: 011-814-000267066219-12
A28: 27 | B28: MOGROVEJO FALCON, OSMAR ADOLFO | C28: 61415253 | D28: PERSONAL CLAVE | E28: ESP. SEGURIDAD | I28: 21570446064035 | J28: 00221517044606403528
A29: 28 | B29: TACANAHUI CALISAYA NESTOR | D29: OBRERO | E29: PEÓN | I29: 54099248033061 | J29: 00254019924803306139
A30: 29 | B30: GUTARATE SABINO, RONEL ARTURO | C30: 76338169 | D30: OBRERO | E30: PEÓN | G30: 0011-0814-0283137347 | H30: 011-814-000283137347-13
A31: 30 | B31: ROSAS CHACHAJE, WILSON JHONY | C31: 44365799 | D31: OBRERO | E31: OPERARIO | F31: MAQUINISTA | I31: 54092485355073
A32: 31 | B32: GAMARRA CONDORI, ANGEL | C32: 47099079 | D32: OBRERO | E32: OPERARIO | F32: ALBAÑIL | G32: 0011-0814-0232544827 | H32: 011-814-000232544827-18
A33: 32 | B33: QUISPE MAQUERA, MARCO ANTONIO | C33: 74808890 | D33: OBRERO | E33: PEON
A34: 33 | B34: PUMAYALLI LICONA, ENOCH | C34: 45366294 | D34: OBRERO | E34: PEON
A35: 34 | B35: CURMAYARI MANUYAMA, VICTOR RAUL | C35: 00082335 | D35: OBRERO | E35: OPERARIO
A36: 35 | B36: CURMAYARI GUZMAN, JOFFRE | C36: 47846597 | D36: OBRERO | E36: OPERARIO
A37: 36 | B37: OLIVA TARAPA, TOMAS | C37: 01764813 | D37: OBRERO | E37: PEON
A38: 37 | B38: MACHUCA NAVARRO, OMAR JIAN FRANCO | C38: 74208220 | D38: OBRERO | E38: PEON
A39: 38 | B39: ESCOBAR ARBILDO, GOLBER | C39: 45415827 | D39: OBRERO | E39: PEON
A40: 39 | B40: ESCOBAR ARBILDO, RUSBER | C40: 48841643 | D40: OBRERO | E40: PEON
A41: 40 | B41: CHAVEZ MONTALICO, ISAAC | C41: 00663998 | D41: OBRERO | E41: OPERARIO
A42: 41 | B42: NAVARRO LOZANO, MARCO MANUEL | C42: 47308810 | D42: OBRERO | E42: OPERARIO
A43: 42 | B43: ARAPA PARQUE, ENOC | C43: 40748695 | D43: OBRERO | E43: OPERARIO
A44: 42 | B44: LAQUIHUANACO PACA, BARTOLOME | C44: 01328043 | D44: OBRERO | E44: OPERARIO | F44: CARPINTERO
A45: 43 | B45: MOLLO JILAJA, YOEL JHONATHAN | C45: 76949507 | D45: OBRERO | E45: OPERARIO | F45: CARPINTERO
A46: 44 | B46: CARMELO MONTEJO, OSCAR CESAR | C46: 73009722 | D46: OBRERO | E46: PEON
A47: 45 | B47: CONDORI LAQUI, RAUL | C47: 7398 | D47: OBRERO | E47: OPERARIO | F47: MAQUINISTA
A48: 46 | B48: LAQUIHUANACO PACA, BARTOLOME | C48: 01328043 | D48: OBRERO | E48: OPERARIO | F48: CARPINTERO
A49: 47 | B49: MOLLO JILAJA, YOEL JHONATHAN | C49: 76949507 | D49: OBRERO | E49: OPERARIO | F49: CARPINTERO
A50: 48 | B50: CARMELO MONTEJO, OSCAR CESAR | C50: 73009722 | D50: OBRERO | E50: PEON
A51: 49

Sheet Hoja1
A4: N° | B4: APELLIDOS Y NOMBRES | C4: DNI | D4: CARGO
A5: 1 | B5: SALAZAR BAZAN, ROCÍO DALILA | C5: =IF(_xlfn.XLOOKUP(Hoja1!B5,DATOS[NOMBRES],DATOS[DNI])="","",_xlfn.XLOOKUP(Hoja1!B5,DATOS[NOMBRES],DATOS[DNI])) -> 26683098 | D5: =IF(_xlfn.XLOOKUP(Tabla6[[#This Row],[APELLIDOS Y NOMBRES]],DATOS[NOMBRES],DATOS[CARGO])="","",_xlfn.XLOOKUP(Tabla6[[#This Row],[APELLIDOS Y NOMBRES]],DATOS[NOMBRES],DATOS[CARGO])) -> RESIDENTE
A6: 2 | B6: ALEJO CHARCA, DENNYS MIRIAM | C6: =IF(_xlfn.XLOOKUP(Hoja1!B6,DATOS[NOMBRES],DATOS[DNI])="","",_xlfn.XLOOKUP(Hoja1!B6,DATOS[NOMBRES],DATOS[DNI])) -> 76470794 | D6: =IF(_xlfn.XLOOKUP(Tabla6[[#This Row],[APELLIDOS Y NOMBRES]],DATOS[NOMBRES],DATOS[CARGO])="","",_xlfn.XLOOKUP(Tabla6[[#This Row],[APELLIDOS Y NOMBRES]],DATOS[NOMBRES],DATOS[CARGO])) -> ING. CALIDAD
A7: 3 | B7: SILVA BORDA, ARLETTE NINOSKA | C7: =IF(_xlfn.XLOOKUP(Hoja1!B7,DATOS[NOMBRES],DATOS[DNI])="","",_xlfn.XLOOKUP(Hoja1!B7,DATOS[NOMBRES],DATOS[DNI])) -> 71234038 | D7: =IF(_xlfn.XLOOKUP(Tabla6[[#This Row],[APELLIDOS Y NOMBRES]],DATOS[NOMBRES],DATOS[CARGO])="","",_xlfn.XLOOKUP(Tabla6[[#This Row],[APELLIDOS Y NOMBRES]],DATOS[NOMBRES],DATOS[CARGO])) -> ASIS. ING.
A8: 4 | B8: ACUACHI LANCHIPA, ERNESTO ALONSO | C8: =IF(_xlfn.XLOOKUP(Hoja1!B8,DATOS[NOMBRES],DATOS[DNI])="","",_xlfn.XLOOKUP(Hoja1!B8,DATOS[NOMBRES],DATOS[DNI])) -> 41056694 | D8: =IF(_xlfn.XLOOKUP(Tabla6[[#This Row],[APELLIDOS Y NOMBRES]],DATOS[NOMBRES],DATOS[CARGO])="","",_xlfn.XLOOKUP(Tabla6[[#This Row],[APELLIDOS Y NOMBRES]],DATOS[NOMBRES],DATOS[CARGO])) -> LOGISTICO
A9: 5 | B9: LOZA YAPUCHURA, KENNY GUILLERMO | C9: =IF(_xlfn.XLOOKUP(Hoja1!B9,DATOS[NOMBRES],DATOS[DNI])="","",_xlfn.XLOOKUP(Hoja1!B9,DATOS[NOMBRES],DATOS[DNI])) -> 72188706 | D9: =IF(_xlfn.XLOOKUP(Tabla6[[#This Row],[APELLIDOS Y NOMBRES]],DATOS[NOMBRES],DATOS[CARGO])="","",_xlfn.XLOOKUP(Tabla6[[#This Row],[APELLIDOS Y NOMBRES]],DATOS[NOMBRES],DATOS[CARGO])) -> TOPOGRAFO
A10: 6 | B10: ADUVIRE ARGUATA, MARIO ARTURO | C10: =IF(_xlfn.XLOOKUP(Hoja1!B10,DATOS[NOMBRES],DATOS[DNI])="","",_xlfn.XLOOKUP(Hoja1!B10,DATOS[NOMBRES],DATOS[DNI])) -> 00662471 | D10: =IF(_xlfn.XLOOKUP(Tabla6[[#This Row],[APELLIDOS Y NOMBRES]],DATOS[NOMBRES],DATOS[CARGO])="","",_xlfn.XLOOKUP(Tabla6[[#This Row],[APELLIDOS Y NOMBRES]],DATOS[NOMBRES],DATOS[CARGO])) -> MAESTRO OBRA
A11: 7 | B11: ACOSTA ROJAS, JOSEPH ALFONSO | C11: =IF(_xlfn.XLOOKUP(Hoja1!B11,DATOS[NOMBRES],DATOS[DNI])="","",_xlfn.XLOOKUP(Hoja1!B11,DATOS[NOMBRES],DATOS[DNI])) -> 70522697 | D11: =IF(_xlfn.XLOOKUP(Tabla6[[#This Row],[APELLIDOS Y NOMBRES]],DATOS[NOMBRES],DATOS[CARGO])="","",_xlfn.XLOOKUP(Tabla6[[#This Row],[APELLIDOS Y NOMBRES]],DATOS[NOMBRES],DATOS[CARGO])) -> REPRESENTANTE
A12: 8 | B12: YEANCARLO | C12: =IF(_xlfn.XLOOKUP(Hoja1!B12,DATOS[NOMBRES],DATOS[DNI])="","",_xlfn.XLOOKUP(Hoja1!B12,DATOS[NOMBRES],DATOS[DNI])) | D12: =IF(_xlfn.XLOOKUP(Tabla6[[#This Row],[APELLIDOS Y NOMBRES]],DATOS[NOMBRES],DATOS[CARGO])="","",_xlfn.XLOOKUP(Tabla6[[#This Row],[APELLIDOS Y NOMBRES]],DATOS[NOMBRES],DATOS[CARGO])) -> ASIS. ING.
A13: 9 | B13: ESCOBAR PALACIOS, LUIS IVAN | C13: =IF(_xlfn.XLOOKUP(Hoja1!B13,DATOS[NOMBRES],DATOS[DNI])="","",_xlfn.XLOOKUP(Hoja1!B13,DATOS[NOMBRES],DATOS[DNI])) | D13: =IF(_xlfn.XLOOKUP(Tabla6[[#This Row],[APELLIDOS Y NOMBRES]],DATOS[NOMBRES],DATOS[CARGO])="","",_xlfn.XLOOKUP(Tabla6[[#This Row],[APELLIDOS Y NOMBRES]],DATOS[NOMBRES],DATOS[CARGO])) -> ESP. SEGURIDAD
A14: 10 | C14: =IF(_xlfn.XLOOKUP(Hoja1!B14,DATOS[NOMBRES],DATOS[DNI])="","",_xlfn.XLOOKUP(Hoja1!B14,DATOS[NOMBRES],DATOS[DNI])) | D14: =IF(_xlfn.XLOOKUP(Tabla6[[#This Row],[APELLIDOS Y NOMBRES]],DATOS[NOMBRES],DATOS[CARGO])="","",_xlfn.XLOOKUP(Tabla6[[#This Row],[APELLIDOS Y NOMBRES]],DATOS[NOMBRES],DATOS[CARGO]))
B16: PERSONAL OBRERO
A17: 1 | B17: MAYTAHUARI ACOSTA, SAMMER AXEL | C17: =IF(_xlfn.XLOOKUP(Hoja1!B17,DATOS[NOMBRES],DATOS[DNI])="","",_xlfn.XLOOKUP(Hoja1!B17,DATOS[NOMBRES],DATOS[DNI])) -> 48492558 | D17: =IF(_xlfn.XLOOKUP(Tabla6[[#This Row],[APELLIDOS Y NOMBRES]],DATOS[NOMBRES],DATOS[CARGO])="","",_xlfn.XLOOKUP(Tabla6[[#This Row],[APELLIDOS Y NOMBRES]],DATOS[NOMBRES],DATOS[CARGO])) -> OPERARIO
A18: 2 | B18: CHACON ORTIZ, JOSE ANTONIO | C18: =IF(_xlfn.XLOOKUP(Hoja1!B18,DATOS[NOMBRES],DATOS[DNI])="","",_xlfn.XLOOKUP(Hoja1!B18,DATOS[NOMBRES],DATOS[DNI])) -> 00515241 | D18: =IF(_xlfn.XLOOKUP(Tabla6[[#This Row],[APELLIDOS Y NOMBRES]],DATOS[NOMBRES],DATOS[CARGO])="","",_xlfn.XLOOKUP(Tabla6[[#This Row],[APELLIDOS Y NOMBRES]],DATOS[NOMBRES],DATOS[CARGO])) -> OPERARIO
A19: 3 | B19: GUTARATE SABINO, ADRIEL ANTONY | C19: =IF(_xlfn.XLOOKUP(Hoja1!B19,DATOS[NOMBRES],DATOS[DNI])="","",_xlfn.XLOOKUP(Hoja1!B19,DATOS[NOMBRES],DATOS[DNI])) -> 78202475 | D19: =IF(_xlfn.XLOOKUP(Tabla6[[#This Row],[APELLIDOS Y NOMBRES]],DATOS[NOMBRES],DATOS[CARGO])="","",_xlfn.XLOOKUP(Tabla6[[#This Row],[APELLIDOS Y NOMBRES]],DATOS[NOMBRES],DATOS[CARGO])) -> OPERARIO
A20: 4 | B20: QUISPE LIMACHE, ROGELIO | C20: =IF(_xlfn.XLOOKUP(Hoja1!B20,DATOS[NOMBRES],DATOS[DNI])="","",_xlfn.XLOOKUP(Hoja1!B20,DATOS[NOMBRES],DATOS[DNI])) -> 44758063 | D20: =IF(_xlfn.XLOOKUP(Tabla6[[#This Row],[APELLIDOS Y NOMBRES]],DATOS[NOMBRES],DATOS[CARGO])="","",_xlfn.XLOOKUP(Tabla6[[#This Row],[APELLIDOS Y NOMBRES]],DATOS[NOMBRES],DATOS[CARGO])) -> OPERARIO
A21: 5 | B21: CACERES CALACHUA, YEYSON JORGE | C21: =IF(_xlfn.XLOOKUP(Hoja1!B21,DATOS[NOMBRES],DATOS[DNI])="","",_xlfn.XLOOKUP(Hoja1!B21,DATOS[NOMBRES],DATOS[DNI])) -> 47109805 | D21: =IF(_xlfn.XLOOKUP(Tabla6[[#This Row],[APELLIDOS Y NOMBRES]],DATOS[NOMBRES],DATOS[CARGO])="","",_xlfn.XLOOKUP(Tabla6[[#This Row],[APELLIDOS Y NOMBRES]],DATOS[NOMBRES],DATOS[CARGO])) -> OPERARIO
A22: 6 | B22: ROJAS SANDOVAL, JAVIER ELOY | C22: =IF(_xlfn.XLOOKUP(Hoja1!B22,DATOS[NOMBRES],DATOS[DNI])="","",_xlfn.XLOOKUP(Hoja1!B22,DATOS[NOMBRES],DATOS[DNI])) -> 40861767 | D22: =IF(_xlfn.XLOOKUP(Tabla6[[#This Row],[APELLIDOS Y NOMBRES]],DATOS[NOMBRES],DATOS[CARGO])="","",_xlfn.XLOOKUP(Tabla6[[#This Row],[APELLIDOS Y NOMBRES]],DATOS[NOMBRES],DATOS[CARGO])) -> OPERARIO/VOLQUETERO
A23: 7 | B23: NAVARRO LOZANO, ANGEL JAROL | C23: =IF(_xlfn.XLOOKUP(Hoja1!B23,DATOS[NOMBRES],DATOS[DNI])="","",_xlfn.XLOOKUP(Hoja1!B23,DATOS[NOMBRES],DATOS[DNI])) -> 75396402 | D23: =IF(_xlfn.XLOOKUP(Tabla6[[#This Row],[APELLIDOS Y NOMBRES]],DATOS[NOMBRES],DATOS[CARGO])="","",_xlfn.XLOOKUP(Tabla6[[#This Row],[APELLIDOS Y NOMBRES]],DATOS[NOMBRES],DATOS[CARGO])) -> PEON
A24: 8 | B24: JEREMIAS PALOMINO, NORBERTO LEONCIO | C24: =IF(_xlfn.XLOOKUP(Hoja1!B24,DATOS[NOMBRES],DATOS[DNI])="","",_xlfn.XLOOKUP(Hoja1!B24,DATOS[NOMBRES],DATOS[DNI])) -> 44184914 | D24: =IF(_xlfn.XLOOKUP(Tabla6[[#This Row],[APELLIDOS Y NOMBRES]],DATOS[NOMBRES],DATOS[CARGO])="","",_xlfn.XLOOKUP(Tabla6[[#This Row],[APELLIDOS Y NOMBRES]],DATOS[NOMBRES],DATOS[CARGO])) -> PEON
A25: 9 | B25: LOZANO MALDONADO, HERNAN | C25: =IF(_xlfn.XLOOKUP(Hoja1!B25,DATOS[NOMBRES],DATOS[DNI])="","",_xlfn.XLOOKUP(Hoja1!B25,DATOS[NOMBRES],DATOS[DNI])) -> 40839932 | D25: =IF(_xlfn.XLOOKUP(Tabla6[[#This Row],[APELLIDOS Y NOMBRES]],DATOS[NOMBRES],DATOS[CARGO])="","",_xlfn.XLOOKUP(Tabla6[[#This Row],[APELLIDOS Y NOMBRES]],DATOS[NOMBRES],DATOS[CARGO])) -> PEON
A26: 10 | B26: PIÑA CHUJANDAMA, KEVIN | C26: =IF(_xlfn.XLOOKUP(Hoja1!B26,DATOS[NOMBRES],DATOS[DNI])="","",_xlfn.XLOOKUP(Hoja1!B26,DATOS[NOMBRES],DATOS[DNI])) -> 70833343 | D26: =IF(_xlfn.XLOOKUP(Tabla6[[#This Row],[APELLIDOS Y NOMBRES]],DATOS[NOMBRES],DATOS[CARGO])="","",_xlfn.XLOOKUP(Tabla6[[#This Row],[APELLIDOS Y NOMBRES]],DATOS[NOMBRES],DATOS[CARGO])) -> PEON
A27: 11 | B27: CORDOVA ANGULO, JUAN | C27: =IF(_xlfn.XLOOKUP(Hoja1!B27,DATOS[NOMBRES],DATOS[DNI])="","",_xlfn.XLOOKUP(Hoja1!B27,DATOS[NOMBRES],DATOS[DNI])) -> 40889884 | D27: =IF(_xlfn.XLOOKUP(Tabla6[[#This Row],[APELLIDOS Y NOMBRES]],DATOS[NOMBRES],DATOS[CARGO])="","",_xlfn.XLOOKUP(Tabla6[[#This Row],[APELLIDOS Y NOMBRES]],DATOS[NOMBRES],DATOS[CARGO])) -> PEON
A28: 12 | B28: ORDOÑEZ CONDORI, GILBERTO | C28: =IF(_xlfn.XLOOKUP(Hoja1!B28,DATOS[NOMBRES],DATOS[DNI])="","",_xlfn.XLOOKUP(Hoja1!B28,DATOS[NOMBRES],DATOS[DNI])) -> 44723682 | D28: =IF(_xlfn.XLOOKUP(Tabla6[[#This Row],[APELLIDOS Y NOMBRES]],DATOS[NOMBRES],DATOS[CARGO])="","",_xlfn.XLOOKUP(Tabla6[[#This Row],[APELLIDOS Y NOMBRES]],DATOS[NOMBRES],DATOS[CARGO])) -> PEON
... A31: 15 | B31: VILLEGAS, ROGER | C31: =IF(_xlfn.XLOOKUP(Hoja1!B31,DATOS[NOMBRES],DATOS[DNI])="","",_xlfn.XLOOKUP(Hoja1!B31,DATOS[NOMBRES],DATOS[DNI])) | D31: =IF(_xlfn.XLOOKUP(Tabla6[[#This Row],[APELLIDOS Y NOMBRES]],DATOS[NOMBRES],DATOS[CARGO])="","",_xlfn.XLOOKUP(Tabla6[[#This Row],[APELLIDOS Y NOMBRES]],DATOS[NOMBRES],DATOS[CARGO])) -> OPERARIO MAQU.
A32: 16 | C32: =IF(_xlfn.XLOOKUP(Hoja1!B32,DATOS[NOMBRES],DATOS[DNI])="","",_xlfn.XLOOKUP(Hoja1!B32,DATOS[NOMBRES],DATOS[DNI])) | D32: =IF(_xlfn.XLOOKUP(Tabla6[[#This Row],[APELLIDOS Y NOMBRES]],DATOS[NOMBRES],DATOS[CARGO])="","",_xlfn.XLOOKUP(Tabla6[[#This Row],[APELLIDOS Y NOMBRES]],DATOS[NOMBRES],DATOS[CARGO]))
A33: 17 | C33: =IF(_xlfn.XLOOKUP(Hoja1!B33,DATOS[NOMBRES],DATOS[DNI])="","",_xlfn.XLOOKUP(Hoja1!B33,DATOS[NOMBRES],DATOS[DNI])) | D33: =IF(_xlfn.XLOOKUP(Tabla6[[#This Row],[APELLIDOS Y NOMBRES]],DATOS[NOMBRES],DATOS[CARGO])="","",_xlfn.XLOOKUP(Tabla6[[#This Row],[APELLIDOS Y NOMBRES]],DATOS[NOMBRES],DATOS[CARGO]))
A34: 18 | C34: =IF(_xlfn.XLOOKUP(Hoja1!B34,DATOS[NOMBRES],DATOS[DNI])="","",_xlfn.XLOOKUP(Hoja1!B34,DATOS[NOMBRES],DATOS[DNI])) | D34: =IF(_xlfn.XLOOKUP(Tabla6[[#This Row],[APELLIDOS Y NOMBRES]],DATOS[NOMBRES],DATOS[CARGO])="","",_xlfn.XLOOKUP(Tabla6[[#This Row],[APELLIDOS Y NOMBRES]],DATOS[NOMBRES],DATOS[CARGO]))
A35: 19 | C35: =IF(_xlfn.XLOOKUP(Hoja1!B35,DATOS[NOMBRES],DATOS[DNI])="","",_xlfn.XLOOKUP(Hoja1!B35,DATOS[NOMBRES],DATOS[DNI])) | D35: =IF(_xlfn.XLOOKUP(Tabla6[[#This Row],[APELLIDOS Y NOMBRES]],DATOS[NOMBRES],DATOS[CARGO])="","",_xlfn.XLOOKUP(Tabla6[[#This Row],[APELLIDOS Y NOMBRES]],DATOS[NOMBRES],DATOS[CARGO]))
A36: 20 | C36: =IF(_xlfn.XLOOKUP(Hoja1!B36,DATOS[NOMBRES],DATOS[DNI])="","",_xlfn.XLOOKUP(Hoja1!B36,DATOS[NOMBRES],DATOS[DNI])) | D36: =IF(_xlfn.XLOOKUP(Tabla6[[#This Row],[APELLIDOS Y NOMBRES]],DATOS[NOMBRES],DATOS[CARGO])="","",_xlfn.XLOOKUP(Tabla6[[#This Row],[APELLIDOS Y NOMBRES]],DATOS[NOMBRES],DATOS[CARGO]))
A37: 21 | C37: =IF(_xlfn.XLOOKUP(Hoja1!B37,DATOS[NOMBRES],DATOS[DNI])="","",_xlfn.XLOOKUP(Hoja1!B37,DATOS[NOMBRES],DATOS[DNI])) | D37: =IF(_xlfn.XLOOKUP(Tabla6[[#This Row],[APELLIDOS Y NOMBRES]],DATOS[NOMBRES],DATOS[CARGO])="","",_xlfn.XLOOKUP(Tabla6[[#This Row],[APELLIDOS Y NOMBRES]],DATOS[NOMBRES],DATOS[CARGO]))
A38: 22 | C38: =IF(_xlfn.XLOOKUP(Hoja1!B38,DATOS[NOMBRES],DATOS[DNI])="","",_xlfn.XLOOKUP(Hoja1!B38,DATOS[NOMBRES],DATOS[DNI])) | D38: =IF(_xlfn.XLOOKUP(Tabla6[[#This Row],[APELLIDOS Y NOMBRES]],DATOS[NOMBRES],DATOS[CARGO])="","",_xlfn.XLOOKUP(Tabla6[[#This Row],[APELLIDOS Y NOMBRES]],DATOS[NOMBRES],DATOS[CARGO]))
A39: 23 | C39: =IF(_xlfn.XLOOKUP(Hoja1!B39,DATOS[NOMBRES],DATOS[DNI])="","",_xlfn.XLOOKUP(Hoja1!B39,DATOS[NOMBRES],DATOS[DNI])) | D39: =IF(_xlfn.XLOOKUP(Tabla6[[#This Row],[APELLIDOS Y NOMBRES]],DATOS[NOMBRES],DATOS[CARGO])="","",_xlfn.XLOOKUP(Tabla6[[#This Row],[APELLIDOS Y NOMBRES]],DATOS[NOMBRES],DATOS[CARGO]))
A40: 24 | C40: =IF(_xlfn.XLOOKUP(Hoja1!B40,DATOS[NOMBRES],DATOS[DNI])="","",_xlfn.XLOOKUP(Hoja1!B40,DATOS[NOMBRES],DATOS[DNI])) | D40: =IF(_xlfn.XLOOKUP(Tabla6[[#This Row],[APELLIDOS Y NOMBRES]],DATOS[NOMBRES],DATOS[CARGO])="","",_xlfn.XLOOKUP(Tabla6[[#This Row],[APELLIDOS Y NOMBRES]],DATOS[NOMBRES],DATOS[CARGO]))
A41: 25 | C41: =IF(_xlfn.XLOOKUP(Hoja1!B41,DATOS[NOMBRES],DATOS[DNI])="","",_xlfn.XLOOKUP(Hoja1!B41,DATOS[NOMBRES],DATOS[DNI])) | D41: =IF(_xlfn.XLOOKUP(Tabla6[[#This Row],[APELLIDOS Y NOMBRES]],DATOS[NOMBRES],DATOS[CARGO])="","",_xlfn.XLOOKUP(Tabla6[[#This Row],[APELLIDOS Y NOMBRES]],DATOS[NOMBRES],DATOS[CARGO]))
A42: 26 | C42: =IF(_xlfn.XLOOKUP(Hoja1!B42,DATOS[NOMBRES],DATOS[DNI])="","",_xlfn.XLOOKUP(Hoja1!B42,DATOS[NOMBRES],DATOS[DNI])) | D42: =IF(_xlfn.XLOOKUP(Tabla6[[#This Row],[APELLIDOS Y NOMBRES]],DATOS[NOMBRES],DATOS[CARGO])="","",_xlfn.XLOOKUP(Tabla6[[#This Row],[APELLIDOS Y NOMBRES]],DATOS[NOMBRES],DATOS[CARGO]))
A43: 27 | C43: =IF(_xlfn.XLOOKUP(Hoja1!B43,DATOS[NOMBRES],DATOS[DNI])="","",_xlfn.XLOOKUP(Hoja1!B43,DATOS[NOMBRES],DATOS[DNI])) | D43: =IF(_xlfn.XLOOKUP(Tabla6[[#This Row],[APELLIDOS Y NOMBRES]],DATOS[NOMBRES],DATOS[CARGO])="","",_xlfn.XLOOKUP(Tabla6[[#This Row],[APELLIDOS Y NOMBRES]],DATOS[NOMBRES],DATOS[CARGO]))
... A46: 30 | C46: =IF(_xlfn.XLOOKUP(Hoja1!B46,DATOS[NOMBRES],DATOS[DNI])="","",_xlfn.XLOOKUP(Hoja1!B46,DATOS[NOMBRES],DATOS[DNI])) | D46: =IF(_xlfn.XLOOKUP(Tabla6[[#This Row],[APELLIDOS Y NOMBRES]],DATOS[NOMBRES],DATOS[CARGO])="","",_xlfn.XLOOKUP(Tabla6[[#This Row],[APELLIDOS Y NOMBRES]],DATOS[NOMBRES],DATOS[CARGO]))

Sheet CONTROL ASISTENCIA
C1: REGISTRO DE CONTROL DE ASISTENCIA
C2: CONSORCIO FORTALEZA E.I.R.L
C3: RUC 20612747271
A4: N° | B4: TRABAJADORES | C4: DNI N° | D4: INGRESO | F4: SALIDA | H4: SOBRE TIEMPO | J4: TOTAL | K4: FIRMA | L4: OBSERVACIONES
B5: APELLIDOS Y NOMBRES | D5: Dia | E5: Hora y Min. | F5: Dia | G5: Hora y Min. | H5: De | I5: A | J5: GENERAL
H6: Hora y Min. | I6: Hora y Min.
A7: 1 | B7: NAVARRO LOZANO, ANGEL JAROL | C7: =IFERROR(VLOOKUP(B7,'DATOS GRALES 1'!$B$2:$C$50,2,0)," ") -> 75396402 | D7: 45909 | F7: 45909
A8: 2 | B8: JEREMIAS PALOMINO, NORBERTO LEONCIO | C8: =IFERROR(VLOOKUP(B8,'DATOS GRALES 1'!$B$2:$C$50,2,0)," ") -> 44184914 | D8: 45909 | F8: 45909
A9: =+A8+1 -> 3 | B9: LOZANO MALDONADO, HERNAN | C9: =IFERROR(VLOOKUP(B9,'DATOS GRALES 1'!$B$2:$C$50,2,0)," ") -> 40839932 | D9: 45909 | F9: 45909
A10: =+A9+1 -> 4 | B10: PIÑA CHUJANDAMA, KEVIN | C10: =IFERROR(VLOOKUP(B10,'DATOS GRALES 1'!$B$2:$C$50,2,0)," ") -> 70833343 | D10: 45909 | F10: 45909
A11: =+A10+1 -> 5 | B11: MAYTAHUARI ACOSTA, SAMMER AXEL | C11: =IFERROR(VLOOKUP(B11,'DATOS GRALES 1'!$B$2:$C$50,2,0)," ") -> 48492558 | D11: 45909 | F11: 45909
A12: =+A11+1 -> 6 | B12: CORDOVA ANGULO, JUAN | C12: =IFERROR(VLOOKUP(B12,'DATOS GRALES 1'!$B$2:$C$50,2,0)," ") -> 40889884 | D12: 45909 | F12: 45909
A13: =+A12+1 -> 7 | B13: ROJAS SANDOVAL, JAVIER ELOY | C13: =IFERROR(VLOOKUP(B13,'DATOS GRALES 1'!$B$2:$C$50,2,0)," ") -> 40861767 | D13: 45909 | F13: 45909
A14: =+A13+1 -> 8 | B14: CHINO PILCO SIMON | C14: =IFERROR(VLOOKUP(B14,'DATOS GRALES 1'!$B$2:$C$50,2,0)," ") -> 00487377 | D14: 45909 | F14: 45909
A15: =+A14+1 -> 9 | B15: NAVARRO LOZANO, ANGEL JAROL | C15: =IFERROR(VLOOKUP(B15,'DATOS GRALES 1'!$B$2:$C$50,2,0)," ") -> 75396402 | D15: 45910 | F15: 45910
A16: =+A15+1 -> 10 | B16: JEREMIAS PALOMINO, NORBERTO LEONCIO | C16: =IFERROR(VLOOKUP(B16,'DATOS GRALES 1'!$B$2:$C$50,2,0)," ") -> 44184914 | D16: 45910 | F16: 45910
A17: =+A16+1 -> 11 | B17: LOZANO MALDONADO, HERNAN | C17: =IFERROR(VLOOKUP(B17,'DATOS GRALES 1'!$B$2:$C$50,2,0)," ") -> 40839932 | D17: 45910 | F17: 45910
A18: =+A17+1 -> 12 | B18: PIÑA CHUJANDAMA, KEVIN | C18: =IFERROR(VLOOKUP(B18,'DATOS GRALES 1'!$B$2:$C$50,2,0)," ") -> 70833343 | D18: 45910 | F18: 45910
A19: =+A18+1 -> 13 | B19: MAYTAHUARI ACOSTA, SAMMER AXEL | C19: =IFERROR(VLOOKUP(B19,'DATOS GRALES 1'!$B$2:$C$50,2,0)," ") -> 48492558 | D19: 45910 | F19: 45910
A20: =+A19+1 -> 14 | B20: CORDOVA ANGULO, JUAN | C20: =IFERROR(VLOOKUP(B20,'DATOS GRALES 1'!$B$2:$C$50,2,0)," ") -> 40889884 | D20: 45910 | F20: 45910
A21: 15 | B21: ROJAS SANDOVAL, JAVIER ELOY | C21: =IFERROR(VLOOKUP(B21,'DATOS GRALES 1'!$B$2:$C$50,2,0)," ") -> 40861767 | D21: 45910 | F21: 45910
A22: =+A21+1 -> 16 | B22: CHINO PILCO SIMON | C22: =IFERROR(VLOOKUP(B22,'DATOS GRALES 1'!$B$2:$C$50,2,0)," ") -> 00487377 | D22: 45910 | F22: 45910
A23: 17 | B23: NAVARRO LOZANO, ANGEL JAROL | C23: =IFERROR(VLOOKUP(B23,'DATOS GRALES 1'!$B$2:$C$50,2,0)," ") -> 75396402 | D23: 45911 | F23: 45911
A24: 18 | B24: JEREMIAS PALOMINO, NORBERTO LEONCIO | C24: =IFERROR(VLOOKUP(B24,'DATOS GRALES 1'!$B$2:$C$50,2,0)," ") -> 44184914 | D24: 45911 | F24: 45911
A25: 19 | B25: LOZANO MALDONADO, HERNAN | C25: =IFERROR(VLOOKUP(B25,'DATOS GRALES 1'!$B$2:$C$50,2,0)," ") -> 40839932 | D25: 45911 | F25: 45911
A26: 20 | B26: PIÑA CHUJANDAMA, KEVIN | C26: =IFERROR(VLOOKUP(B26,'DATOS GRALES 1'!$B$2:$C$50,2,0)," ") -> 70833343 | D26: 45911 | F26: 45911
A27: 21 | B27: MAYTAHUARI ACOSTA, SAMMER AXEL | C27: =IFERROR(VLOOKUP(B27,'DATOS GRALES 1'!$B$2:$C$50,2,0)," ") -> 48492558 | D27: 45911 | F27: 45911
A28: 22 | B28: CORDOVA ANGULO, JUAN | C28: =IFERROR(VLOOKUP(B28,'DATOS GRALES 1'!$B$2:$C$50,2,0)," ") -> 40889884 | D28: 45911 | F28: 45911
A29: 23 | B29: ROJAS SANDOVAL, JAVIER ELOY | C29: =IFERROR(VLOOKUP(B29,'DATOS GRALES 1'!$B$2:$C$50,2,0)," ") -> 40861767 | D29: 45911 | F29: 45911
A30: =+A29+1 -> 24 | B30: NAVARRO LOZANO, ANGEL JAROL | C30: =IFERROR(VLOOKUP(B30,'DATOS GRALES 1'!$B$2:$C$50,2,0)," ") -> 75396402 | D30: 45912 | F30: 45912
A31: =+A30+1 -> 25 | B31: JEREMIAS PALOMINO, NORBERTO LEONCIO | C31: =IFERROR(VLOOKUP(B31,'DATOS GRALES 1'!$B$2:$C$50,2,0)," ") -> 44184914 | D31: 45912 | F31: 45912
A32: =+A31+1 -> 26 | B32: LOZANO MALDONADO, HERNAN | C32: =IFERROR(VLOOKUP(B32,'DATOS GRALES 1'!$B$2:$C$50,2,0)," ") -> 40839932 | D32: 45912 | F32: 45912
A33: 27 | B33: PIÑA CHUJANDAMA, KEVIN | C33: =IFERROR(VLOOKUP(B33,'DATOS GRALES 1'!$B$2:$C$50,2,0)," ") -> 70833343 | D33: 45912 | F33: 45912
A34: 28 | B34: MAYTAHUARI ACOSTA, SAMMER AXEL | C34: =IFERROR(VLOOKUP(B34,'DATOS GRALES 1'!$B$2:$C$50,2,0)," ") -> 48492558 | D34: 45912 | F34: 45912
A35: 29 | B35: CORDOVA ANGULO, JUAN | C35: =IFERROR(VLOOKUP(B35,'DATOS GRALES 1'!$B$2:$C$50,2,0)," ") -> 40889884 | D35: 45912 | F35: 45912
A36: 30 | B36: ROJAS SANDOVAL, JAVIER ELOY | C36: =IFERROR(VLOOKUP(B36,'DATOS GRALES 1'!$B$2:$C$50,2,0)," ") -> 40861767 | D36: 45912 | F36: 45912
A37: =+A36+1 -> 31 | B37: NAVARRO LOZANO, ANGEL JAROL | C37: =IFERROR(VLOOKUP(B37,'DATOS GRALES 1'!$B$2:$C$50,2,0)," ") -> 75396402 | D37: 45913 | F37: 45913
A38: =+A37+1 -> 32 | B38: JEREMIAS PALOMINO, NORBERTO LEONCIO | C38: =IFERROR(VLOOKUP(B38,'DATOS GRALES 1'!$B$2:$C$50,2,0)," ") -> 44184914 | D38: 45913 | F38: 45913
A39: =+A38+1 -> 33 | B39: LOZANO MALDONADO, HERNAN | C39: =IFERROR(VLOOKUP(B39,'DATOS GRALES 1'!$B$2:$C$50,2,0)," ") -> 40839932 | D39: 45913 | F39: 45913
A40: 34 | B40: PIÑA CHUJANDAMA, KEVIN | C40: =IFERROR(VLOOKUP(B40,'DATOS GRALES 1'!$B$2:$C$50,2,0)," ") -> 70833343 | D40: 45913 | F40: 45913
A41: 35 | B41: MAYTAHUARI ACOSTA, SAMMER AXEL | C41: =IFERROR(VLOOKUP(B41,'DATOS GRALES 1'!$B$2:$C$50,2,0)," ") -> 48492558 | D41: 45913 | F41: 45913
A42: 36 | B42: CORDOVA ANGULO, JUAN | C42: =IFERROR(VLOOKUP(B42,'DATOS GRALES 1'!$B$2:$C$50,2,0)," ") -> 40889884 | D42: 45913 | F42: 45913
A43: 37 | B43: ROJAS SANDOVAL, JAVIER ELOY | C43: =IFERROR(VLOOKUP(B43,'DATOS GRALES 1'!$B$2:$C$50,2,0)," ") -> 40861767 | D43: 45913 | F43: 45913
A44: 38 | B44: NAVARRO LOZANO, ANGEL JAROL | C44: =IFERROR(VLOOKUP(B44,'DATOS GRALES 1'!$B$2:$C$50,2,0)," ") -> 75396402 | D44: 45915 | F44: 45915
A45: 39 | B45: JEREMIAS PALOMINO, NORBERTO LEONCIO | C45: =IFERROR(VLOOKUP(B45,'DATOS GRALES 1'!$B$2:$C$50,2,0)," ") -> 44184914 | D45: 45915 | F45: 45915
A46: 40 | B46: LOZANO MALDONADO, HERNAN | C46: =IFERROR(VLOOKUP(B46,'DATOS GRALES 1'!$B$2:$C$50,2,0)," ") -> 40839932 | D46: 45915 | F46: 45915
A47: 41 | B47: PIÑA CHUJANDAMA, KEVIN | C47: =IFERROR(VLOOKUP(B47,'DATOS GRALES 1'!$B$2:$C$50,2,0)," ") -> 70833343 | D47: 45915 | F47: 45915
A48: 42 | B48: MAYTAHUARI ACOSTA, SAMMER AXEL | C48: =IFERROR(VLOOKUP(B48,'DATOS GRALES 1'!$B$2:$C$50,2,0)," ") -> 48492558 | D48: 45915 | F48: 45915
A49: 43 | B49: CORDOVA ANGULO, JUAN | C49: =IFERROR(VLOOKUP(B49,'DATOS GRALES 1'!$B$2:$C$50,2,0)," ") -> 40889884 | D49: 45915 | F49: 45915
A50: 44 | B50: ROJAS SANDOVAL, JAVIER ELOY | C50: =IFERROR(VLOOKUP(B50,'DATOS GRALES 1'!$B$2:$C$50,2,0)," ") -> 40861767 | D50: 45915 | F50: 45915
A51: 45 | B51: CHACON ORTIZ, JOSE ANTONIO | C51: =IFERROR(VLOOKUP(B51,'DATOS GRALES 1'!$B$2:$C$50,2,0)," ") -> 00515241 | D51: 45915 | F51: 45915
... A70: 64 | B70: ORDOÑEZ CONDORI, GILBERTO | C70: =IFERROR(VLOOKUP(B70,'DATOS GRALES 1'!$B$2:$C$50,2,0)," ") -> 44723682 | D70: 45917 | F70: 45917
A71: 65 | C71: =IFERROR(VLOOKUP(B71,'DATOS GRALES 1'!$B$2:$C$50,2,0)," ")
A72: 66 | C72: =IFERROR(VLOOKUP(B72,'DATOS GRALES 1'!$B$2:$C$50,2,0)," ")
A73: 67 | C73: =IFERROR(VLOOKUP(B73,'DATOS GRALES 1'!$B$2:$C$50,2,0)," ")
A74: 68 | C74: =IFERROR(VLOOKUP(B74,'DATOS GRALES 1'!$B$2:$C$50,2,0)," ")
A75: 69 | C75: =IFERROR(VLOOKUP(B75,'DATOS GRALES 1'!$B$2:$C$50,2,0)," ")
A76: 70 | C76: =IFERROR(VLOOKUP(B76,'DATOS GRALES 1'!$B$2:$C$50,2,0)," ")
A77: 71 | C77: =IFERROR(VLOOKUP(B77,'DATOS GRALES 1'!$B$2:$C$50,2,0)," ")
A78: 72 | C78: =IFERROR(VLOOKUP(B78,'DATOS GRALES 1'!$B$2:$C$50,2,0)," ")
A79: 73 | C79: =IFERROR(VLOOKUP(B79,'DATOS GRALES 1'!$B$2:$C$50,2,0)," ")
A80: 74 | C80: =IFERROR(VLOOKUP(B80,'DATOS GRALES 1'!$B$2:$C$50,2,0)," ")
A81: 75 | C81: =IFERROR(VLOOKUP(B81,'DATOS GRALES 1'!$B$2:$C$50,2,0)," ")
A82: 76 | C82: =IFERROR(VLOOKUP(B82,'DATOS GRALES 1'!$B$2:$C$50,2,0)," ")
A83: 77 | C83: =IFERROR(VLOOKUP(B83,'DATOS GRALES 1'!$B$2:$C$50,2,0)," ")

Sheet FORMATO
C1: REGISTRO DE CONTROL DE ASISTENCIA
C2: CONSORCIO FORTALEZA E.I.R.L
C3: RUC 20612747271
A4: N° | B4: TRABAJADORES | C4: DNI N° | D4: INGRESO | F4: SALIDA | H4: SOBRE TIEMPO | J4: TOTAL | K4: FIRMA | L4: OBSERVACIONES
B5: APELLIDOS Y NOMBRES | D5: Dia | E5: Hora y Min. | F5: Dia | G5: Hora y Min. | H5: De | I5: A | J5: GENERAL
H6: Hora y Min. | I6: Hora y Min.
A7: 1 | B7: NAVARRO LOZANO, ANGEL JAROL | C7: =IF(_xlfn.XLOOKUP(B7,DATOS[NOMBRES],DATOS[DNI])=0,"",_xlfn.XLOOKUP(B7,DATOS[NOMBRES],DATOS[DNI])) -> 75396402 | D7: 45920 | F7: 45920
A8: 2 | B8: JEREMIAS PALOMINO, NORBERTO LEONCIO | C8: =IF(_xlfn.XLOOKUP(B8,DATOS[NOMBRES],DATOS[DNI])=0,"",_xlfn.XLOOKUP(B8,DATOS[NOMBRES],DATOS[DNI])) -> 44184914 | D8: 45920 | F8: 45920
A9: 3 | B9: LOZANO MALDONADO, HERNAN | C9: =IF(_xlfn.XLOOKUP(B9,DATOS[NOMBRES],DATOS[DNI])=0,"",_xlfn.XLOOKUP(B9,DATOS[NOMBRES],DATOS[DNI])) -> 40839932 | D9: 45920 | F9: 45920
A10: 4 | B10: PIÑA CHUJANDAMA, KEVIN | C10: =IF(_xlfn.XLOOKUP(B10,DATOS[NOMBRES],DATOS[DNI])=0,"",_xlfn.XLOOKUP(B10,DATOS[NOMBRES],DATOS[DNI])) -> 70833343 | D10: 45920 | F10: 45920
A11: 5 | B11: MAYTAHUARI ACOSTA, SAMMER AXEL | C11: =IF(_xlfn.XLOOKUP(B11,DATOS[NOMBRES],DATOS[DNI])=0,"",_xlfn.XLOOKUP(B11,DATOS[NOMBRES],DATOS[DNI])) -> 48492558 | D11: 45920 | F11: 45920
A12: 6 | B12: CORDOVA ANGULO, JUAN | C12: =IF(_xlfn.XLOOKUP(B12,DATOS[NOMBRES],DATOS[DNI])=0,"",_xlfn.XLOOKUP(B12,DATOS[NOMBRES],DATOS[DNI])) -> 40889884 | D12: 45920 | F12: 45920
A13: 7 | B13: ROJAS SANDOVAL, JAVIER ELOY | C13: =IF(_xlfn.XLOOKUP(B13,DATOS[NOMBRES],DATOS[DNI])=0,"",_xlfn.XLOOKUP(B13,DATOS[NOMBRES],DATOS[DNI])) -> 40861767 | D13: 45920 | F13: 45920
A14: 8 | B14: CHACON ORTIZ, JOSE ANTONIO | C14: =IF(_xlfn.XLOOKUP(B14,DATOS[NOMBRES],DATOS[DNI])=0,"",_xlfn.XLOOKUP(B14,DATOS[NOMBRES],DATOS[DNI])) -> 00515241 | D14: 45920 | F14: 45920
A15: 9 | B15: ORDOÑEZ CONDORI, GILBERTO | C15: =IF(_xlfn.XLOOKUP(B15,DATOS[NOMBRES],DATOS[DNI])=0,"",_xlfn.XLOOKUP(B15,DATOS[NOMBRES],DATOS[DNI])) -> 44723682 | D15: 45920 | F15: 45920
A16: 10 | C16: =IF(_xlfn.XLOOKUP(B16,DATOS[NOMBRES],DATOS[DNI])=0,"",_xlfn.XLOOKUP(B16,DATOS[NOMBRES],DATOS[DNI]))
A17: 11 | C17: =IF(_xlfn.XLOOKUP(B17,DATOS[NOMBRES],DATOS[DNI])=0,"",_xlfn.XLOOKUP(B17,DATOS[NOMBRES],DATOS[DNI]))
A18: 12 | C18: =IF(_xlfn.XLOOKUP(B18,DATOS[NOMBRES],DATOS[DNI])=0,"",_xlfn.XLOOKUP(B18,DATOS[NOMBRES],DATOS[DNI]))
A19: 13 | C19: =IF(_xlfn.XLOOKUP(B19,DATOS[NOMBRES],DATOS[DNI])=0,"",_xlfn.XLOOKUP(B19,DATOS[NOMBRES],DATOS[DNI]))
A20: 14 | C20: =IF(_xlfn.XLOOKUP(B20,DATOS[NOMBRES],DATOS[DNI])=0,"",_xlfn.XLOOKUP(B20,DATOS[NOMBRES],DATOS[DNI]))
A21: 15 | C21: =IF(_xlfn.XLOOKUP(B21,DATOS[NOMBRES],DATOS[DNI])=0,"",_xlfn.XLOOKUP(B21,DATOS[NOMBRES],DATOS[DNI]))
A22: 16 | C22: =IF(_xlfn.XLOOKUP(B22,DATOS[NOMBRES],DATOS[DNI])=0,"",_xlfn.XLOOKUP(B22,DATOS[NOMBRES],DATOS[DNI]))
A23: 17 | C23: =IF(_xlfn.XLOOKUP(B23,DATOS[NOMBRES],DATOS[DNI])=0,"",_xlfn.XLOOKUP(B23,DATOS[NOMBRES],DATOS[DNI]))
A24: 18 | C24: =IF(_xlfn.XLOOKUP(B24,DATOS[NOMBRES],DATOS[DNI])=0,"",_xlfn.XLOOKUP(B24,DATOS[NOMBRES],DATOS[DNI]))
A25: 19 | C25: =IF(_xlfn.XLOOKUP(B25,DATOS[NOMBRES],DATOS[DNI])=0,"",_xlfn.XLOOKUP(B25,DATOS[NOMBRES],DATOS[DNI]))
A26: 20 | C26: =IF(_xlfn.XLOOKUP(B26,DATOS[NOMBRES],DATOS[DNI])=0,"",_xlfn.XLOOKUP(B26,DATOS[NOMBRES],DATOS[DNI]))
A27: 21 | C27: =IF(_xlfn.XLOOKUP(B27,DATOS[NOMBRES],DATOS[DNI])=0,"",_xlfn.XLOOKUP(B27,DATOS[NOMBRES],DATOS[DNI]))
... A41: 35 | C41: =IF(_xlfn.XLOOKUP(B41,DATOS[NOMBRES],DATOS[DNI])=0,"",_xlfn.XLOOKUP(B41,DATOS[NOMBRES],DATOS[DNI]))

Sheet TAREO HORAS EXTRAS
C1: Registro y Control de Horas Trabajadas
C4: Escoja Mes: | E4: Octubre | H4: ← Item Lista Desplegable | N4: Empresa: | Q4: FSA Constructora | V4: El Periodo Comprende | AD4: Mes: | AG4: Año: | AM4: Horas Extras: | AO4: SI
N5: Obra: | Q5: Ticapampa | V5: ="Desde: "&TEXT(DATE(E6,MONTH(E4&1),1),"mmm-dd-yy")&" Hasta "&TEXT(EOMONTH(DATE(E6,MONTH(E4&1),1),0),"mmm-dd-yy") -> Desde: Oct-01-25 Hasta Oct-31-25 | AD5: =E4 -> Octubre | AG5: =E6 -> 2025
C6: Escoja Año: | E6: 2025 | H6: ← Introduzca manualmente | N6: Encargado: | Q6: Ernesto Acuachi | AM6: Por Encima de: | AO6: 8
G8: =DATE(E6,MONTH(E4&1),21) -> 45951 | H8: =G8+1 -> 45952 | I8: =H8+1 -> 45953 | J8: =I8+1 -> 45954 | K8: =J8+1 -> 45955 | L8: =K8+1 -> 45956 | M8: =L8+1 -> 45957 | N8: =M8+1 -> 45958 | O8: =N8+1 -> 45959 | ... AK8: =AJ8+1 -> 45981
AQ9: Festivos
AQ10: 45658
AQ11: 45866
AQ12: 45867
C13: Apellido y Nombres | E13: Cargo | G13: =PROPER(LEFT(TEXT(G8,"dddd"),3)) -> Mar | H13: =PROPER(LEFT(TEXT(H8,"dddd"),3)) -> Mié | I13: =PROPER(LEFT(TEXT(I8,"dddd"),3)) -> Jue | J13: =PROPER(LEFT(TEXT(J8,"dddd"),3)) -> Vie | K13: =PROPER(LEFT(TEXT(K8,"dddd"),3)) -> Sáb | L13: =PROPER(LEFT(TEXT(L8,"dddd"),3)) -> Dom | M13: =PROPER(LEFT(TEXT(M8,"dddd"),3)) -> Lun | N13: =PROPER(LEFT(TEXT(N8,"dddd"),3)) -> Mar | ... AK13: =PROPER(LEFT(TEXT(AK8,"dddd"),3)) -> Jue | AM13: Horas Normales | AO13: Horas Extras | AQ13: 45962
AQ14: 46016
C15: NAVARRO LOZANO, ANGEL JAROL | AM15: {=_xlfn.SWITCH(_HorasExtras, "Si",SUMPRODUCT(IF(_Datos<=_PorEncimade,_Datos,_PorEncimade),(WEEKDAY($G$8:$AK$8,2)<=6)*1,NOT(ISNUMBER(MATCH($G$8:$AK$8,nFestivos,0)))*1), "No",SUMPRODUCT(_Datos,(WEEKDAY($G$8:$AK$8,2)<=5)*1,NOT(ISNUMBER(MATCH($G$8:$AK$8,nFestivos,0)))*1))} -> 0 | AO15: {=_xlfn.SWITCH(_HorasExtras, "Si",SUMPRODUCT(IF(_Datos>_PorEncimade,_Datos-_PorEncimade,0),(WEEKDAY($G$8:$AK$8,2)<=6)*1,NOT(ISNUMBER(MATCH($G$8:$AK$8,nFestivos,0)))*1), "No",0)} -> 0 | AQ15: 46022
C16: JEREMIAS PALOMINO, NORBERTO LEONCIO | AM16: {=_xlfn.SWITCH(_HorasExtras, "Si",SUMPRODUCT(IF(_Datos<=_PorEncimade,_Datos,_PorEncimade),(WEEKDAY($G$8:$AK$8,2)<=5)*1,NOT(ISNUMBER(MATCH($G$8:$AK$8,nFestivos,0)))*1), "No",SUMPRODUCT(_Datos,(WEEKDAY($G$8:$AK$8,2)<=5)*1,NOT(ISNUMBER(MATCH($G$8:$AK$8,nFestivos,0)))*1))} -> 0 | AO16: {=_xlfn.SWITCH(_HorasExtras, "Si",SUMPRODUCT(IF(_Datos>_PorEncimade,_Datos-_PorEncimade,0),(WEEKDAY($G$8:$AK$8,2)<=6)*1,NOT(ISNUMBER(MATCH($G$8:$AK$8,nFestivos,0)))*1), "No",0)} -> 0
C17: LOZANO MALDONADO, HERNAN | I17: 12 | U17: 10 | V17: 9 | AM17: {=_xlfn.SWITCH(_HorasExtras, "Si",SUMPRODUCT(IF(_Datos<=_PorEncimade,_Datos,_PorEncimade),(WEEKDAY($G$8:$AK$8,2)<=5)*1,NOT(ISNUMBER(MATCH($G$8:$AK$8,nFestivos,0)))*1), "No",SUMPRODUCT(_Datos,(WEEKDAY($G$8:$AK$8,2)<=5)*1,NOT(ISNUMBER(MATCH($G$8:$AK$8,nFestivos,0)))*1))} -> 24 | AO17: {=_xlfn.SWITCH(_HorasExtras, "Si",SUMPRODUCT(IF(_Datos>_PorEncimade,_Datos-_PorEncimade,0),(WEEKDAY($G$8:$AK$8,2)<=6)*1,NOT(ISNUMBER(MATCH($G$8:$AK$8,nFestivos,0)))*1), "No",0)} -> 7
C18: PIÑA CHUJANDAMA, KEVIN | I18: 12 | AM18: {=_xlfn.SWITCH(_HorasExtras, "Si",SUMPRODUCT(IF(_Datos<=_PorEncimade,_Datos,_PorEncimade),(WEEKDAY($G$8:$AK$8,2)<=5)*1,NOT(ISNUMBER(MATCH($G$8:$AK$8,nFestivos,0)))*1), "No",SUMPRODUCT(_Datos,(WEEKDAY($G$8:$AK$8,2)<=5)*1,NOT(ISNUMBER(MATCH($G$8:$AK$8,nFestivos,0)))*1))} -> 8 | AO18: {=_xlfn.SWITCH(_HorasExtras, "Si",SUMPRODUCT(IF(_Datos>_PorEncimade,_Datos-_PorEncimade,0),(WEEKDAY($G$8:$AK$8,2)<=6)*1,NOT(ISNUMBER(MATCH($G$8:$AK$8,nFestivos,0)))*1), "No",0)} -> 4
C19: MAYTAHUARI ACOSTA, SAMMER AXEL | AM19: {=_xlfn.SWITCH(_HorasExtras, "Si",SUMPRODUCT(IF(_Datos<=_PorEncimade,_Datos,_PorEncimade),(WEEKDAY($G$8:$AK$8,2)<=5)*1,NOT(ISNUMBER(MATCH($G$8:$AK$8,nFestivos,0)))*1), "No",SUMPRODUCT(_Datos,(WEEKDAY($G$8:$AK$8,2)<=5)*1,NOT(ISNUMBER(MATCH($G$8:$AK$8,nFestivos,0)))*1))} -> 0 | AO19: {=_xlfn.SWITCH(_HorasExtras, "Si",SUMPRODUCT(IF(_Datos>_PorEncimade,_Datos-_PorEncimade,0),(WEEKDAY($G$8:$AK$8,2)<=6)*1,NOT(ISNUMBER(MATCH($G$8:$AK$8,nFestivos,0)))*1), "No",0)} -> 0
C20: CORDOVA ANGULO, JUAN | AM20: {=_xlfn.SWITCH(_HorasExtras, "Si",SUMPRODUCT(IF(_Datos<=_PorEncimade,_Datos,_PorEncimade),(WEEKDAY($G$8:$AK$8,2)<=5)*1,NOT(ISNUMBER(MATCH($G$8:$AK$8,nFestivos,0)))*1), "No",SUMPRODUCT(_Datos,(WEEKDAY($G$8:$AK$8,2)<=5)*1,NOT(ISNUMBER(MATCH($G$8:$AK$8,nFestivos,0)))*1))} -> 0 | AO20: {=_xlfn.SWITCH(_HorasExtras, "Si",SUMPRODUCT(IF(_Datos>_PorEncimade,_Datos-_PorEncimade,0),(WEEKDAY($G$8:$AK$8,2)<=6)*1,NOT(ISNUMBER(MATCH($G$8:$AK$8,nFestivos,0)))*1), "No",0)} -> 0
C21: CHACON ORTIZ, JOSE ANTONIO | AM21: {=_xlfn.SWITCH(_HorasExtras, "Si",SUMPRODUCT(IF(_Datos<=_PorEncimade,_Datos,_PorEncimade),(WEEKDAY($G$8:$AK$8,2)<=5)*1,NOT(ISNUMBER(MATCH($G$8:$AK$8,nFestivos,0)))*1), "No",SUMPRODUCT(_Datos,(WEEKDAY($G$8:$AK$8,2)<=5)*1,NOT(ISNUMBER(MATCH($G$8:$AK$8,nFestivos,0)))*1))} -> 0 | AO21: {=_xlfn.SWITCH(_HorasExtras, "Si",SUMPRODUCT(IF(_Datos>_PorEncimade,_Datos-_PorEncimade,0),(WEEKDAY($G$8:$AK$8,2)<=6)*1,NOT(ISNUMBER(MATCH($G$8:$AK$8,nFestivos,0)))*1), "No",0)} -> 0
C22: ORDOÑEZ CONDORI, GILBERTO | AM22: {=_xlfn.SWITCH(_HorasExtras, "Si",SUMPRODUCT(IF(_Datos<=_PorEncimade,_Datos,_PorEncimade),(WEEKDAY($G$8:$AK$8,2)<=5)*1,NOT(ISNUMBER(MATCH($G$8:$AK$8,nFestivos,0)))*1), "No",SUMPRODUCT(_Datos,(WEEKDAY($G$8:$AK$8,2)<=5)*1,NOT(ISNUMBER(MATCH($G$8:$AK$8,nFestivos,0)))*1))} -> 0 | AO22: {=_xlfn.SWITCH(_HorasExtras, "Si",SUMPRODUCT(IF(_Datos>_PorEncimade,_Datos-_PorEncimade,0),(WEEKDAY($G$8:$AK$8,2)<=6)*1,NOT(ISNUMBER(MATCH($G$8:$AK$8,nFestivos,0)))*1), "No",0)} -> 0
C23: GUTARATE SABINO, ADRIEL ANTONY | AM23: {=_xlfn.SWITCH(_HorasExtras, "Si",SUMPRODUCT(IF(_Datos<=_PorEncimade,_Datos,_PorEncimade),(WEEKDAY($G$8:$AK$8,2)<=5)*1,NOT(ISNUMBER(MATCH($G$8:$AK$8,nFestivos,0)))*1), "No",SUMPRODUCT(_Datos,(WEEKDAY($G$8:$AK$8,2)<=5)*1,NOT(ISNUMBER(MATCH($G$8:$AK$8,nFestivos,0)))*1))} -> 0 | AO23: {=_xlfn.SWITCH(_HorasExtras, "Si",SUMPRODUCT(IF(_Datos>_PorEncimade,_Datos-_PorEncimade,0),(WEEKDAY($G$8:$AK$8,2)<=6)*1,NOT(ISNUMBER(MATCH($G$8:$AK$8,nFestivos,0)))*1), "No",0)} -> 0
C24: QUISPE LIMACHE, ROGELIO | I24: 12 | AM24: {=_xlfn.SWITCH(_HorasExtras, "Si",SUMPRODUCT(IF(_Datos<=_PorEncimade,_Datos,_PorEncimade),(WEEKDAY($G$8:$AK$8,2)<=5)*1,NOT(ISNUMBER(MATCH($G$8:$AK$8,nFestivos,0)))*1), "No",SUMPRODUCT(_Datos,(WEEKDAY($G$8:$AK$8,2)<=5)*1,NOT(ISNUMBER(MATCH($G$8:$AK$8,nFestivos,0)))*1))} -> 8 | AO24: {=_xlfn.SWITCH(_HorasExtras, "Si",SUMPRODUCT(IF(_Datos>_PorEncimade,_Datos-_PorEncimade,0),(WEEKDAY($G$8:$AK$8,2)<=6)*1,NOT(ISNUMBER(MATCH($G$8:$AK$8,nFestivos,0)))*1), "No",0)} -> 4
C25: CACERES CALACHUA, YEYSON JORGE | AM25: {=_xlfn.SWITCH(_HorasExtras, "Si",SUMPRODUCT(IF(_Datos<=_PorEncimade,_Datos,_PorEncimade),(WEEKDAY($G$8:$AK$8,2)<=5)*1,NOT(ISNUMBER(MATCH($G$8:$AK$8,nFestivos,0)))*1), "No",SUMPRODUCT(_Datos,(WEEKDAY($G$8:$AK$8,2)<=5)*1,NOT(ISNUMBER(MATCH($G$8:$AK$8,nFestivos,0)))*1))} -> 0 | AO25: {=_xlfn.SWITCH(_HorasExtras, "Si",SUMPRODUCT(IF(_Datos>_PorEncimade,_Datos-_PorEncimade,0),(WEEKDAY($G$8:$AK$8,2)<=6)*1,NOT(ISNUMBER(MATCH($G$8:$AK$8,nFestivos,0)))*1), "No",0)} -> 0
C26: MAQUERA QUISPE, LEONIDAS EDWIN | AM26: {=_xlfn.SWITCH(_HorasExtras, "Si",SUMPRODUCT(IF(_Datos<=_PorEncimade,_Datos,_PorEncimade),(WEEKDAY($G$8:$AK$8,2)<=5)*1,NOT(ISNUMBER(MATCH($G$8:$AK$8,nFestivos,0)))*1), "No",SUMPRODUCT(_Datos,(WEEKDAY($G$8:$AK$8,2)<=5)*1,NOT(ISNUMBER(MATCH($G$8:$AK$8,nFestivos,0)))*1))} -> 0 | AO26: {=_xlfn.SWITCH(_HorasExtras, "Si",SUMPRODUCT(IF(_Datos>_PorEncimade,_Datos-_PorEncimade,0),(WEEKDAY($G$8:$AK$8,2)<=6)*1,NOT(ISNUMBER(MATCH($G$8:$AK$8,nFestivos,0)))*1), "No",0)} -> 0
C27: TACANAHUI CALISAYA NESTOR | I27: 12 | U27: 10 | V27: 9 | AM27: {=_xlfn.SWITCH(_HorasExtras, "Si",SUMPRODUCT(IF(_Datos<=_PorEncimade,_Datos,_PorEncimade),(WEEKDAY($G$8:$AK$8,2)<=5)*1,NOT(ISNUMBER(MATCH($G$8:$AK$8,nFestivos,0)))*1), "No",SUMPRODUCT(_Datos,(WEEKDAY($G$8:$AK$8,2)<=5)*1,NOT(ISNUMBER(MATCH($G$8:$AK$8,nFestivos,0)))*1))} -> 24 | AO27: {=_xlfn.SWITCH(_HorasExtras, "Si",SUMPRODUCT(IF(_Datos>_PorEncimade,_Datos-_PorEncimade,0),(WEEKDAY($G$8:$AK$8,2)<=6)*1,NOT(ISNUMBER(MATCH($G$8:$AK$8,nFestivos,0)))*1), "No",0)} -> 7
C28: ROSAS CHACHAJE, WILSON JHONY | I28: 11 | U28: 10 | V28: 9 | AM28: {=_xlfn.SWITCH(_HorasExtras, "Si",SUMPRODUCT(IF(_Datos<=_PorEncimade,_Datos,_PorEncimade),(WEEKDAY($G$8:$AK$8,2)<=5)*1,NOT(ISNUMBER(MATCH($G$8:$AK$8,nFestivos,0)))*1), "No",SUMPRODUCT(_Datos,(WEEKDAY($G$8:$AK$8,2)<=5)*1,NOT(ISNUMBER(MATCH($G$8:$AK$8,nFestivos,0)))*1))} -> 24 | AO28: {=_xlfn.SWITCH(_HorasExtras, "Si",SUMPRODUCT(IF(_Datos>_PorEncimade,_Datos-_PorEncimade,0),(WEEKDAY($G$8:$AK$8,2)<=6)*1,NOT(ISNUMBER(MATCH($G$8:$AK$8,nFestivos,0)))*1), "No",0)} -> 6
C29: GAMARRA CONDORI, ANGEL | U29: 10 | AM29: {=_xlfn.SWITCH(_HorasExtras, "Si",SUMPRODUCT(IF(_Datos<=_PorEncimade,_Datos,_PorEncimade),(WEEKDAY($G$8:$AK$8,2)<=5)*1,NOT(ISNUMBER(MATCH($G$8:$AK$8,nFestivos,0)))*1), "No",SUMPRODUCT(_Datos,(WEEKDAY($G$8:$AK$8,2)<=5)*1,NOT(ISNUMBER(MATCH($G$8:$AK$8,nFestivos,0)))*1))} -> 8 | AO29: {=_xlfn.SWITCH(_HorasExtras, "Si",SUMPRODUCT(IF(_Datos>_PorEncimade,_Datos-_PorEncimade,0),(WEEKDAY($G$8:$AK$8,2)<=6)*1,NOT(ISNUMBER(MATCH($G$8:$AK$8,nFestivos,0)))*1), "No",0)} -> 2
C30: QUISPE MAQUERA, MARCO ANTONIO | AM30: {=_xlfn.SWITCH(_HorasExtras, "Si",SUMPRODUCT(IF(_Datos<=_PorEncimade,_Datos,_PorEncimade),(WEEKDAY($G$8:$AK$8,2)<=5)*1,NOT(ISNUMBER(MATCH($G$8:$AK$8,nFestivos,0)))*1), "No",SUMPRODUCT(_Datos,(WEEKDAY($G$8:$AK$8,2)<=5)*1,NOT(ISNUMBER(MATCH($G$8:$AK$8,nFestivos,0)))*1))} -> 0 | AO30: {=_xlfn.SWITCH(_HorasExtras, "Si",SUMPRODUCT(IF(_Datos>_PorEncimade,_Datos-_PorEncimade,0),(WEEKDAY($G$8:$AK$8,2)<=6)*1,NOT(ISNUMBER(MATCH($G$8:$AK$8,nFestivos,0)))*1), "No",0)} -> 0
C31: PUMAYALLI LICONA, ENOCH | I31: 11 | AM31: {=_xlfn.SWITCH(_HorasExtras, "Si",SUMPRODUCT(IF(_Datos<=_PorEncimade,_Datos,_PorEncimade),(WEEKDAY($G$8:$AK$8,2)<=5)*1,NOT(ISNUMBER(MATCH($G$8:$AK$8,nFestivos,0)))*1), "No",SUMPRODUCT(_Datos,(WEEKDAY($G$8:$AK$8,2)<=5)*1,NOT(ISNUMBER(MATCH($G$8:$AK$8,nFestivos,0)))*1))} -> 8 | AO31: {=_xlfn.SWITCH(_HorasExtras, "Si",SUMPRODUCT(IF(_Datos>_PorEncimade,_Datos-_PorEncimade,0),(WEEKDAY($G$8:$AK$8,2)<=6)*1,NOT(ISNUMBER(MATCH($G$8:$AK$8,nFestivos,0)))*1), "No",0)} -> 3
C32: CURMAYARI MANUYAMA, VICTOR RAUL | U32: 10 | AM32: {=_xlfn.SWITCH(_HorasExtras, "Si",SUMPRODUCT(IF(_Datos<=_PorEncimade,_Datos,_PorEncimade),(WEEKDAY($G$8:$AK$8,2)<=5)*1,NOT(ISNUMBER(MATCH($G$8:$AK$8,nFestivos,0)))*1), "No",SUMPRODUCT(_Datos,(WEEKDAY($G$8:$AK$8,2)<=5)*1,NOT(ISNUMBER(MATCH($G$8:$AK$8,nFestivos,0)))*1))} -> 8 | AO32: {=_xlfn.SWITCH(_HorasExtras, "Si",SUMPRODUCT(IF(_Datos>_PorEncimade,_Datos-_PorEncimade,0),(WEEKDAY($G$8:$AK$8,2)<=6)*1,NOT(ISNUMBER(MATCH($G$8:$AK$8,nFestivos,0)))*1), "No",0)} -> 2
C33: CURMAYARI GUZMAN, JOFFRE | I33: 12 | AM33: {=_xlfn.SWITCH(_HorasExtras, "Si",SUMPRODUCT(IF(_Datos<=_PorEncimade,_Datos,_PorEncimade),(WEEKDAY($G$8:$AK$8,2)<=5)*1,NOT(ISNUMBER(MATCH($G$8:$AK$8,nFestivos,0)))*1), "No",SUMPRODUCT(_Datos,(WEEKDAY($G$8:$AK$8,2)<=5)*1,NOT(ISNUMBER(MATCH($G$8:$AK$8,nFestivos,0)))*1))} -> 8 | AO33: {=_xlfn.SWITCH(_HorasExtras, "Si",SUMPRODUCT(IF(_Datos>_PorEncimade,_Datos-_PorEncimade,0),(WEEKDAY($G$8:$AK$8,2)<=6)*1,NOT(ISNUMBER(MATCH($G$8:$AK$8,nFestivos,0)))*1), "No",0)} -> 4
C34: OLIVA TARAPA, TOMAS | U34: 10 | V34: 9 | AM34: {=_xlfn.SWITCH(_HorasExtras, "Si",SUMPRODUCT(IF(_Datos<=_PorEncimade,_Datos,_PorEncimade),(WEEKDAY($G$8:$AK$8,2)<=5)*1,NOT(ISNUMBER(MATCH($G$8:$AK$8,nFestivos,0)))*1), "No",SUMPRODUCT(_Datos,(WEEKDAY($G$8:$AK$8,2)<=5)*1,NOT(ISNUMBER(MATCH($G$8:$AK$8,nFestivos,0)))*1))} -> 16 | AO34: {=_xlfn.SWITCH(_HorasExtras, "Si",SUMPRODUCT(IF(_Datos>_PorEncimade,_Datos-_PorEncimade,0),(WEEKDAY($G$8:$AK$8,2)<=6)*1,NOT(ISNUMBER(MATCH($G$8:$AK$8,nFestivos,0)))*1), "No",0)} -> 3
C35: MACHUCA NAVARRO, OMAR JIAN FRANCO | I35: 11 | AM35: {=_xlfn.SWITCH(_HorasExtras, "Si",SUMPRODUCT(IF(_Datos<=_PorEncimade,_Datos,_PorEncimade),(WEEKDAY($G$8:$AK$8,2)<=5)*1,NOT(ISNUMBER(MATCH($G$8:$AK$8,nFestivos,0)))*1), "No",SUMPRODUCT(_Datos,(WEEKDAY($G$8:$AK$8,2)<=5)*1,NOT(ISNUMBER(MATCH($G$8:$AK$8,nFestivos,0)))*1))} -> 8 | AO35: {=_xlfn.SWITCH(_HorasExtras, "Si",SUMPRODUCT(IF(_Datos>_PorEncimade,_Datos-_PorEncimade,0),(WEEKDAY($G$8:$AK$8,2)<=6)*1,NOT(ISNUMBER(MATCH($G$8:$AK$8,nFestivos,0)))*1), "No",0)} -> 3
C36: ESCOBAR ARBILDO, GOLBER | I36: 11 | AM36: {=_xlfn.SWITCH(_HorasExtras, "Si",SUMPRODUCT(IF(_Datos<=_PorEncimade,_Datos,_PorEncimade),(WEEKDAY($G$8:$AK$8,2)<=5)*1,NOT(ISNUMBER(MATCH($G$8:$AK$8,nFestivos,0)))*1), "No",SUMPRODUCT(_Datos,(WEEKDAY($G$8:$AK$8,2)<=5)*1,NOT(ISNUMBER(MATCH($G$8:$AK$8,nFestivos,0)))*1))} -> 8 | AO36: {=_xlfn.SWITCH(_HorasExtras, "Si",SUMPRODUCT(IF(_Datos>_PorEncimade,_Datos-_PorEncimade,0),(WEEKDAY($G$8:$AK$8,2)<=6)*1,NOT(ISNUMBER(MATCH($G$8:$AK$8,nFestivos,0)))*1), "No",0)} -> 3
C37: ESCOBAR ARBILDO, RUSBER | I37: 11 | AM37: {=_xlfn.SWITCH(_HorasExtras, "Si",SUMPRODUCT(IF(_Datos<=_PorEncimade,_Datos,_PorEncimade),(WEEKDAY($G$8:$AK$8,2)<=5)*1,NOT(ISNUMBER(MATCH($G$8:$AK$8,nFestivos,0)))*1), "No",SUMPRODUCT(_Datos,(WEEKDAY($G$8:$AK$8,2)<=5)*1,NOT(ISNUMBER(MATCH($G$8:$AK$8,nFestivos,0)))*1))} -> 8 | AO37: {=_xlfn.SWITCH(_HorasExtras, "Si",SUMPRODUCT(IF(_Datos>_PorEncimade,_Datos-_PorEncimade,0),(WEEKDAY($G$8:$AK$8,2)<=6)*1,NOT(ISNUMBER(MATCH($G$8:$AK$8,nFestivos,0)))*1), "No",0)} -> 3
C38: CHAVEZ MONTALICO, ISAAC | U38: 10 | V38: 9 | AM38: {=_xlfn.SWITCH(_HorasExtras, "Si",SUMPRODUCT(IF(_Datos<=_PorEncimade,_Datos,_PorEncimade),(WEEKDAY($G$8:$AK$8,2)<=5)*1,NOT(ISNUMBER(MATCH($G$8:$AK$8,nFestivos,0)))*1), "No",SUMPRODUCT(_Datos,(WEEKDAY($G$8:$AK$8,2)<=5)*1,NOT(ISNUMBER(MATCH($G$8:$AK$8,nFestivos,0)))*1))} -> 16 | AO38: {=_xlfn.SWITCH(_HorasExtras, "Si",SUMPRODUCT(IF(_Datos>_PorEncimade,_Datos-_PorEncimade,0),(WEEKDAY($G$8:$AK$8,2)<=6)*1,NOT(ISNUMBER(MATCH($G$8:$AK$8,nFestivos,0)))*1), "No",0)} -> 3
C39: NAVARRO LOZANO, MARCO MANUEL | AM39: {=_xlfn.SWITCH(_HorasExtras, "Si",SUMPRODUCT(IF(_Datos<=_PorEncimade,_Datos,_PorEncimade),(WEEKDAY($G$8:$AK$8,2)<=5)*1,NOT(ISNUMBER(MATCH($G$8:$AK$8,nFestivos,0)))*1), "No",SUMPRODUCT(_Datos,(WEEKDAY($G$8:$AK$8,2)<=5)*1,NOT(ISNUMBER(MATCH($G$8:$AK$8,nFestivos,0)))*1))} -> 0 | AO39: {=_xlfn.SWITCH(_HorasExtras, "Si",SUMPRODUCT(IF(_Datos>_PorEncimade,_Datos-_PorEncimade,0),(WEEKDAY($G$8:$AK$8,2)<=6)*1,NOT(ISNUMBER(MATCH($G$8:$AK$8,nFestivos,0)))*1), "No",0)} -> 0
C40: ARAPA PARQUE, ENOC | U40: 10 | AM40: {=_xlfn.SWITCH(_HorasExtras, "Si",SUMPRODUCT(IF(_Datos<=_PorEncimade,_Datos,_PorEncimade),(WEEKDAY($G$8:$AK$8,2)<=5)*1,NOT(ISNUMBER(MATCH($G$8:$AK$8,nFestivos,0)))*1), "No",SUMPRODUCT(_Datos,(WEEKDAY($G$8:$AK$8,2)<=5)*1,NOT(ISNUMBER(MATCH($G$8:$AK$8,nFestivos,0)))*1))} -> 8 | AO40: {=_xlfn.SWITCH(_HorasExtras, "Si",SUMPRODUCT(IF(_Datos>_PorEncimade,_Datos-_PorEncimade,0),(WEEKDAY($G$8:$AK$8,2)<=6)*1,NOT(ISNUMBER(MATCH($G$8:$AK$8,nFestivos,0)))*1), "No",0)} -> 2
AM41: {=_xlfn.SWITCH(_HorasExtras, "Si",SUMPRODUCT(IF(_Datos<=_PorEncimade,_Datos,_PorEncimade),(WEEKDAY($G$8:$AK$8,2)<=5)*1,NOT(ISNUMBER(MATCH($G$8:$AK$8,nFestivos,0)))*1), "No",SUMPRODUCT(_Datos,(WEEKDAY($G$8:$AK$8,2)<=5)*1,NOT(ISNUMBER(MATCH($G$8:$AK$8,nFestivos,0)))*1))} -> 0 | AO41: {=_xlfn.SWITCH(_HorasExtras, "Si",SUMPRODUCT(IF(_Datos>_PorEncimade,_Datos-_PorEncimade,0),(WEEKDAY($G$8:$AK$8,2)<=6)*1,NOT(ISNUMBER(MATCH($G$8:$AK$8,nFestivos,0)))*1), "No",0)} -> 0
AM42: {=_xlfn.SWITCH(_HorasExtras, "Si",SUMPRODUCT(IF(_Datos<=_PorEncimade,_Datos,_PorEncimade),(WEEKDAY($G$8:$AK$8,2)<=5)*1,NOT(ISNUMBER(MATCH($G$8:$AK$8,nFestivos,0)))*1), "No",SUMPRODUCT(_Datos,(WEEKDAY($G$8:$AK$8,2)<=5)*1,NOT(ISNUMBER(MATCH($G$8:$AK$8,nFestivos,0)))*1))} -> 0 | AO42: {=_xlfn.SWITCH(_HorasExtras, "Si",SUMPRODUCT(IF(_Datos>_PorEncimade,_Datos-_PorEncimade,0),(WEEKDAY($G$8:$AK$8,2)<=6)*1,NOT(ISNUMBER(MATCH($G$8:$AK$8,nFestivos,0)))*1), "No",0)} -> 0
AM43: {=_xlfn.SWITCH(_HorasExtras, "Si",SUMPRODUCT(IF(_Datos<=_PorEncimade,_Datos,_PorEncimade),(WEEKDAY($G$8:$AK$8,2)<=5)*1,NOT(ISNUMBER(MATCH($G$8:$AK$8,nFestivos,0)))*1), "No",SUMPRODUCT(_Datos,(WEEKDAY($G$8:$AK$8,2)<=5)*1,NOT(ISNUMBER(MATCH($G$8:$AK$8,nFestivos,0)))*1))} -> 0 | AO43: {=_xlfn.SWITCH(_HorasExtras, "Si",SUMPRODUCT(IF(_Datos>_PorEncimade,_Datos-_PorEncimade,0),(WEEKDAY($G$8:$AK$8,2)<=6)*1,NOT(ISNUMBER(MATCH($G$8:$AK$8,nFestivos,0)))*1), "No",0)} -> 0
AM44: {=_xlfn.SWITCH(_HorasExtras, "Si",SUMPRODUCT(IF(_Datos<=_PorEncimade,_Datos,_PorEncimade),(WEEKDAY($G$8:$AK$8,2)<=5)*1,NOT(ISNUMBER(MATCH($G$8:$AK$8,nFestivos,0)))*1), "No",SUMPRODUCT(_Datos,(WEEKDAY($G$8:$AK$8,2)<=5)*1,NOT(ISNUMBER(MATCH($G$8:$AK$8,nFestivos,0)))*1))} -> 0 | AO44: {=_xlfn.SWITCH(_HorasExtras, "Si",SUMPRODUCT(IF(_Datos>_PorEncimade,_Datos-_PorEncimade,0),(WEEKDAY($G$8:$AK$8,2)<=6)*1,NOT(ISNUMBER(MATCH($G$8:$AK$8,nFestivos,0)))*1), "No",0)} -> 0
AM45: {=_xlfn.SWITCH(_HorasExtras, "Si",SUMPRODUCT(IF(_Datos<=_PorEncimade,_Datos,_PorEncimade),(WEEKDAY($G$8:$AK$8,2)<=5)*1,NOT(ISNUMBER(MATCH($G$8:$AK$8,nFestivos,0)))*1), "No",SUMPRODUCT(_Datos,(WEEKDAY($G$8:$AK$8,2)<=5)*1,NOT(ISNUMBER(MATCH($G$8:$AK$8,nFestivos,0)))*1))} -> 0 | AO45: {=_xlfn.SWITCH(_HorasExtras, "Si",SUMPRODUCT(IF(_Datos>_PorEncimade,_Datos-_PorEncimade,0),(WEEKDAY($G$8:$AK$8,2)<=6)*1,NOT(ISNUMBER(MATCH($G$8:$AK$8,nFestivos,0)))*1), "No",0)} -> 0
AM46: {=_xlfn.SWITCH(_HorasExtras, "Si",SUMPRODUCT(IF(_Datos<=_PorEncimade,_Datos,_PorEncimade),(WEEKDAY($G$8:$AK$8,2)<=5)*1,NOT(ISNUMBER(MATCH($G$8:$AK$8,nFestivos,0)))*1), "No",SUMPRODUCT(_Datos,(WEEKDAY($G$8:$AK$8,2)<=5)*1,NOT(ISNUMBER(MATCH($G$8:$AK$8,nFestivos,0)))*1))} -> 0 | AO46: {=_xlfn.SWITCH(_HorasExtras, "Si",SUMPRODUCT(IF(_Datos>_PorEncimade,_Datos-_PorEncimade,0),(WEEKDAY($G$8:$AK$8,2)<=6)*1,NOT(ISNUMBER(MATCH($G$8:$AK$8,nFestivos,0)))*1), "No",0)} -> 0
AM47: {=_xlfn.SWITCH(_HorasExtras, "Si",SUMPRODUCT(IF(_Datos<=_PorEncimade,_Datos,_PorEncimade),(WEEKDAY($G$8:$AK$8,2)<=5)*1,NOT(ISNUMBER(MATCH($G$8:$AK$8,nFestivos,0)))*1), "No",SUMPRODUCT(_Datos,(WEEKDAY($G$8:$AK$8,2)<=5)*1,NOT(ISNUMBER(MATCH($G$8:$AK$8,nFestivos,0)))*1))} -> 0 | AO47: {=_xlfn.SWITCH(_HorasExtras, "Si",SUMPRODUCT(IF(_Datos>_PorEncimade,_Datos-_PorEncimade,0),(WEEKDAY($G$8:$AK$8,2)<=6)*1,NOT(ISNUMBER(MATCH($G$8:$AK$8,nFestivos,0)))*1), "No",0)} -> 0
AM48: {=_xlfn.SWITCH(_HorasExtras, "Si",SUMPRODUCT(IF(_Datos<=_PorEncimade,_Datos,_PorEncimade),(WEEKDAY($G$8:$AK$8,2)<=5)*1,NOT(ISNUMBER(MATCH($G$8:$AK$8,nFestivos,0)))*1), "No",SUMPRODUCT(_Datos,(WEEKDAY($G$8:$AK$8,2)<=5)*1,NOT(ISNUMBER(MATCH($G$8:$AK$8,nFestivos,0)))*1))} -> 0 | AO48: {=_xlfn.SWITCH(_HorasExtras, "Si",SUMPRODUCT(IF(_Datos>_PorEncimade,_Datos-_PorEncimade,0),(WEEKDAY($G$8:$AK$8,2)<=6)*1,NOT(ISNUMBER(MATCH($G$8:$AK$8,nFestivos,0)))*1), "No",0)} -> 0
AM49: {=_xlfn.SWITCH(_HorasExtras, "Si",SUMPRODUCT(IF(_Datos<=_PorEncimade,_Datos,_PorEncimade),(WEEKDAY($G$8:$AK$8,2)<=5)*1,NOT(ISNUMBER(MATCH($G$8:$AK$8,nFestivos,0)))*1), "No",SUMPRODUCT(_Datos,(WEEKDAY($G$8:$AK$8,2)<=5)*1,NOT(ISNUMBER(MATCH($G$8:$AK$8,nFestivos,0)))*1))} -> 0 | AO49: {=_xlfn.SWITCH(_HorasExtras, "Si",SUMPRODUCT(IF(_Datos>_PorEncimade,_Datos-_PorEncimade,0),(WEEKDAY($G$8:$AK$8,2)<=6)*1,NOT(ISNUMBER(MATCH($G$8:$AK$8,nFestivos,0)))*1), "No",0)} -> 0
AM50: {=_xlfn.SWITCH(_HorasExtras, "Si",SUMPRODUCT(IF(_Datos<=_PorEncimade,_Datos,_PorEncimade),(WEEKDAY($G$8:$AK$8,2)<=5)*1,NOT(ISNUMBER(MATCH($G$8:$AK$8,nFestivos,0)))*1), "No",SUMPRODUCT(_Datos,(WEEKDAY($G$8:$AK$8,2)<=5)*1,NOT(ISNUMBER(MATCH($G$8:$AK$8,nFestivos,0)))*1))} -> 0 | AO50: {=_xlfn.SWITCH(_HorasExtras, "Si",SUMPRODUCT(IF(_Datos>_PorEncimade,_Datos-_PorEncimade,0),(WEEKDAY($G$8:$AK$8,2)<=6)*1,NOT(ISNUMBER(MATCH($G$8:$AK$8,nFestivos,0)))*1), "No",0)} -> 0
AM51: {=_xlfn.SWITCH(_HorasExtras, "Si",SUMPRODUCT(IF(_Datos<=_PorEncimade,_Datos,_PorEncimade),(WEEKDAY($G$8:$AK$8,2)<=5)*1,NOT(ISNUMBER(MATCH($G$8:$AK$8,nFestivos,0)))*1), "No",SUMPRODUCT(_Datos,(WEEKDAY($G$8:$AK$8,2)<=5)*1,NOT(ISNUMBER(MATCH($G$8:$AK$8,nFestivos,0)))*1))} -> 0 | AO51: {=_xlfn.SWITCH(_HorasExtras, "Si",SUMPRODUCT(IF(_Datos>_PorEncimade,_Datos-_PorEncimade,0),(WEEKDAY($G$8:$AK$8,2)<=6)*1,NOT(ISNUMBER(MATCH($G$8:$AK$8,nFestivos,0)))*1), "No",0)} -> 0

Sheet formulas
A3: 1 | B3: {=WEEKDAY(_Fechainicial,2)>WEEKDAY(_FechaSiguiente,2)} -> #NAME? | C3: colocar una linea de lunes a domingo en formato condicional
A4: 2 | B4: {=MONTH(_Fechainicial)<>MONTH($E$4&1)} -> #NAME? | C4: apaga los dias que no se utlizan de acuerdo al mes
A5: 3 | B5: {=MONTH(_Fechainicial)=MONTH($E$4&1)} -> #NAME? | C5: para colocar un color de relleno hasta donde este los dias activos
B6: {=OR(WEEKDAY(_Fechainicial,2)>=7,ISNUMBER(MATCH(_Fechainicial,nFestivo,0)),MONTH(_Fechainicial)<>MONTH($E$4&1))} -> #NAME? | C6: colocar una trama en los dias festivos y domingos
B7: =CAMBIAR(_HorasExtras; | N7: para hallar horas normales = 8horas
B8: Si;SUMAPRODUCTO(SI(_Datos<=_PorEncimade;_Datos;_PorEncimade);(DIASEM($G$8:$AK$8;2)<=5)*1;NO(ESNUMERO(COINCIDIR($G$8:$AK$8;nFestivos;0)))*1);
B9: No;SUMAPRODUCTO(_Datos;(DIASEM($G$8:$AK$8;2)<=5)*1;NO(ESNUMERO(COINCIDIR($G$8:$AK$8;nFestivos;0)))*1))
B10: {=_HorasExtras="NO"} -> #NAME? | C10: para que las horas extras en formato condiciona tenga otro color
B12: {=AND(_HorasExtras="SI",OR(_Datos>_PorEncimade))} -> #NAME? | C12: para el color al costado de los empleados

Sheet ASISTENCIA KRAMER1
A5: Año | B5: 2025
A6: Mes | B6: ABRIL
C8: =IF($B$6="","",1) -> 1 | D8: =IF(IF(C8="","",SUM(C8+1))>VLOOKUP('ASISTENCIA KRAMER1'!$B$6,TMESES[],2,FALSE),"",SUM('ASISTENCIA KRAMER1'!C8+1)) -> 2 | E8: =IF(IF(D8="","",SUM(D8+1))>VLOOKUP('ASISTENCIA KRAMER1'!$B$6,TMESES[],2,FALSE),"",SUM('ASISTENCIA KRAMER1'!D8+1)) -> 3 | F8: =IF(IF(E8="","",SUM(E8+1))>VLOOKUP('ASISTENCIA KRAMER1'!$B$6,TMESES[],2,FALSE),"",SUM('ASISTENCIA KRAMER1'!E8+1)) -> 4 | G8: =IF(IF(F8="","",SUM(F8+1))>VLOOKUP('ASISTENCIA KRAMER1'!$B$6,TMESES[],2,FALSE),"",SUM('ASISTENCIA KRAMER1'!F8+1)) -> 5 | H8: =IF(IF(G8="","",SUM(G8+1))>VLOOKUP('ASISTENCIA KRAMER1'!$B$6,TMESES[],2,FALSE),"",SUM('ASISTENCIA KRAMER1'!G8+1)) -> 6 | I8: =IF(IF(H8="","",SUM(H8+1))>VLOOKUP('ASISTENCIA KRAMER1'!$B$6,TMESES[],2,FALSE),"",SUM('ASISTENCIA KRAMER1'!H8+1)) -> 7 | J8: =IF(IF(I8="","",SUM(I8+1))>VLOOKUP('ASISTENCIA KRAMER1'!$B$6,TMESES[],2,FALSE),"",SUM('ASISTENCIA KRAMER1'!I8+1)) -> 8 | K8: =IF(IF(J8="","",SUM(J8+1))>VLOOKUP('ASISTENCIA KRAMER1'!$B$6,TMESES[],2,FALSE),"",SUM('ASISTENCIA KRAMER1'!J8+1)) -> 9 | ... AG8: =IF(IF(AF8="","",SUM(AF8+1))>VLOOKUP('ASISTENCIA KRAMER1'!$B$6,TMESES[],2,FALSE),"",SUM('ASISTENCIA KRAMER1'!AF8+1))
C9: =TEXT(DATE($B$5,MONTH($B$6&1),C8),"ddd") -> mar | D9: =TEXT(DATE($B$5,MONTH($B$6&1),D8),"ddd") -> mié | E9: =TEXT(DATE($B$5,MONTH($B$6&1),E8),"ddd") -> jue | F9: =TEXT(DATE($B$5,MONTH($B$6&1),F8),"ddd") -> vie | G9: =TEXT(DATE($B$5,MONTH($B$6&1),G8),"ddd") -> sáb | H9: =TEXT(DATE($B$5,MONTH($B$6&1),H8),"ddd") -> dom | I9: =TEXT(DATE($B$5,MONTH($B$6&1),I8),"ddd") -> lun | J9: =TEXT(DATE($B$5,MONTH($B$6&1),J8),"ddd") -> mar | ... AF9: =TEXT(DATE($B$5,MONTH($B$6&1),AF8),"ddd") -> mié
A10: N° | B10: APELLIDOS Y NOMBRES

Sheet MESES
A1: MES | B1: HASTA
A2: ENERO | B2: 31
A3: FEBRERO | B3: 28
A4: MARZO | B4: 31
A5: ABRIL | B5: 30
A6: MAYO | B6: 31
A7: JUNIO | B7: 30
A8: JULIO | B8: 31
A9: AGOSTO | B9: 31
A10: SETIEMBRE | B10: 30
A11: OCTUBRE | B11: 31
A12: NOVIEMBRE | B12: 30
A13: DICIEMBRE | B13: 31

Sheet ASISTENCIA 2 (2)
C1: Registro y Control de Asistencia
C4: Escoja Mes: | E4: Setiembre | H4: ← Item Lista Desplegable | N4: Empresa: | Q4: FSA Constructora | V4: El Periodo Comprende | AD4: Mes: | AG4: Año: | AM4: Horas Extras: | AO4: NO
N5: Obra: | Q5: Ticapampa | V5: ="Desde: "&TEXT(DATE(E6,MONTH(E4&1),1),"mmm-dd-yy")&" Hasta "&TEXT(EOMONTH(DATE(E6,MONTH(E4&1),1),0),"mmm-dd-yy") -> Desde: Set-01-25 Hasta Set-30-25 | AD5: =E4 -> Setiembre | AG5: =E6 -> 2025
C6: Escoja Año: | E6: 2025 | H6: ← Introduzca manualmente | N6: Encargado: | Q6: Ernesto Acuachi | AM6: Por Encima de: | AO6: 8
G8: =DATE(E6,MONTH(E4&1),1) -> 45901 | H8: =G8+1 -> 45902 | I8: =H8+1 -> 45903 | J8: =I8+1 -> 45904 | K8: =J8+1 -> 45905 | L8: =K8+1 -> 45906 | M8: =L8+1 -> 45907 | N8: =M8+1 -> 45908 | O8: =N8+1 -> 45909 | ... AK8: =AJ8+1 -> 45931
AT9: Festivos
AT10: 45658
AT11: 45866
AT12: 45867
C13: Apellido y Nombres | E13: Cargo | G13: =PROPER(LEFT(TEXT(G8,"dddd"),3)) -> Lun | H13: =PROPER(LEFT(TEXT(H8,"dddd"),3)) -> Mar | I13: =PROPER(LEFT(TEXT(I8,"dddd"),3)) -> Mié | J13: =PROPER(LEFT(TEXT(J8,"dddd"),3)) -> Jue | K13: =PROPER(LEFT(TEXT(K8,"dddd"),3)) -> Vie | L13: =PROPER(LEFT(TEXT(L8,"dddd"),3)) -> Sáb | M13: =PROPER(LEFT(TEXT(M8,"dddd"),3)) -> Dom | N13: =PROPER(LEFT(TEXT(N8,"dddd"),3)) -> Lun | ... AK13: =PROPER(LEFT(TEXT(AK8,"dddd"),3)) -> Mié | AM13: ASISTIO(SI) | AO13: FALTA(NO) | AQ13: MEDIO DIA(MED) | AS13: TOTAL | AT13: 45962
AT14: 46016
C15: SALAZAR BAZAN, ROCÍO DALILA | E15: =IFERROR(VLOOKUP(C15,'DATOS GRALES 1'!$B$2:$E$50,4,0),"") -> RESIDENTE | N15: SI | O15: SI | P15: SI | Q15: SI | R15: SI | S15: SI | U15: SI | V15: SI | W15: SI | X15: SI | Y15: SI | Z15: SI | AB15: NO | AC15: SI | AD15: si | AE15: SI | AF15: SI | AG15: SI | AI15: SI | AJ15: SI | AM15: =IF(COUNTIF(G15:AK15,"SI")=0,"",COUNTIF(G15:AK15,"SI")) -> 19 | AO15: =IF(COUNTIF(G15:AK15,"NO")=0,"",COUNTIF(G15:AK15,"NO")) -> 1 | AQ15: =IF(COUNTIF(G15:AK15,"MED")=0,"",COUNTIF(G15:AK15,"MED")) | AS15: =IF(SUM(AM15:AQ15)=0,"",SUM(AM15:AQ15)) -> 20 | AT15: 46022
C16: ALEJO CHARCA, DENNYS MIRIAM | E16: =IFERROR(VLOOKUP(C16,'DATOS GRALES 1'!$B$2:$E$50,4,0),"") -> ING. CALIDAD | O16: SI | P16: SI | Q16: SI | R16: SI | S16: SI | U16: SI | V16: SI | W16: SI | X16: SI | Y16: SI | Z16: SI | AB16: SI | AC16: SI | AD16: si | AE16: SI | AF16: SI | AG16: SI | AI16: SI | AJ16: SI | AM16: =IF(COUNTIF(G16:AK16,"SI")=0,"",COUNTIF(G16:AK16,"SI")) -> 19 | AO16: =IF(COUNTIF(G16:AK16,"NO")=0,"",COUNTIF(G16:AK16,"NO")) | AQ16: =IF(COUNTIF(G16:AK16,"MED")=0,"",COUNTIF(G16:AK16,"MED")) | AS16: =IF(SUM(AM16:AQ16)=0,"",SUM(AM16:AQ16)) -> 19
C17: SILVA BORDA, ARLETTE NINOSKA | E17: =IFERROR(VLOOKUP(C17,'DATOS GRALES 1'!$B$2:$E$50,4,0),"") -> ASIS. ING. | P17: SI | Q17: SI | R17: SI | S17: SI | U17: SI | V17: SI | W17: SI | X17: SI | Y17: SI | Z17: SI | AB17: SI | AC17: SI | AD17: si | AE17: SI | AF17: SI | AG17: SI | AI17: SI | AJ17: SI | AM17: =IF(COUNTIF(G17:AK17,"SI")=0,"",COUNTIF(G17:AK17,"SI")) -> 18 | AO17: =IF(COUNTIF(G17:AK17,"NO")=0,"",COUNTIF(G17:AK17,"NO")) | AQ17: =IF(COUNTIF(G17:AK17,"MED")=0,"",COUNTIF(G17:AK17,"MED")) | AS17: =IF(SUM(AM17:AQ17)=0,"",SUM(AM17:AQ17)) -> 18
C18: ACUACHI LANCHIPA, ERNESTO ALONSO | E18: =IFERROR(VLOOKUP(C18,'DATOS GRALES 1'!$B$2:$E$50,4,0),"") -> LOGISTICO | N18: SI | O18: SI | P18: SI | Q18: SI | R18: SI | S18: SI | U18: SI | V18: SI | W18: SI | X18: SI | Y18: SI | Z18: SI | AB18: SI | AC18: SI | AD18: SI | AE18: MED | AF18: SI | AG18: SI | AI18: SI | AJ18: SI | AM18: =IF(COUNTIF(G18:AK18,"SI")=0,"",COUNTIF(G18:AK18,"SI")) -> 19 | AO18: =IF(COUNTIF(G18:AK18,"NO")=0,"",COUNTIF(G18:AK18,"NO")) | AQ18: =IF(COUNTIF(G18:AK18,"MED")=0,"",COUNTIF(G18:AK18,"MED")) -> 1 | AS18: =IF(SUM(AM18:AQ18)=0,"",SUM(AM18:AQ18)) -> 20
C19: ADUVIRE ARGUATA, MARIO ARTURO | E19: =IFERROR(VLOOKUP(C19,'DATOS GRALES 1'!$B$2:$E$50,4,0),"") -> MAESTRO OBRA | N19: SI | O19: SI | P19: SI | Q19: SI | R19: SI | S19: SI | U19: SI | V19: SI | W19: SI | X19: SI | Y19: SI | Z19: SI | AB19: SI | AC19: SI | AD19: si | AE19: SI | AF19: SI | AG19: SI | AI19: SI | AJ19: SI | AM19: =IF(COUNTIF(G19:AK19,"SI")=0,"",COUNTIF(G19:AK19,"SI")) -> 20 | AO19: =IF(COUNTIF(G19:AK19,"NO")=0,"",COUNTIF(G19:AK19,"NO")) | AQ19: =IF(COUNTIF(G19:AK19,"MED")=0,"",COUNTIF(G19:AK19,"MED")) | AS19: =IF(SUM(AM19:AQ19)=0,"",SUM(AM19:AQ19)) -> 20
C20: LOZA YAPUCHURA, KENNY GUILLERMO | E20: =IFERROR(VLOOKUP(C20,'DATOS GRALES 1'!$B$2:$E$50,4,0),"") -> TOPOGRAFO | AB20: SI | AC20: SI | AD20: si | AE20: SI | AF20: SI | AG20: SI | AI20: SI | AJ20: SI | AM20: =IF(COUNTIF(G20:AK20,"SI")=0,"",COUNTIF(G20:AK20,"SI")) -> 8 | AO20: =IF(COUNTIF(G20:AK20,"NO")=0,"",COUNTIF(G20:AK20,"NO")) | AQ20: =IF(COUNTIF(G20:AK20,"MED")=0,"",COUNTIF(G20:AK20,"MED")) | AS20: =IF(SUM(AM20:AQ20)=0,"",SUM(AM20:AQ20)) -> 8
C21: MOGROVEJO FALCON, OSMAR ADOLFO | E21: =IFERROR(VLOOKUP(C21,'DATOS GRALES 1'!$B$2:$E$50,4,0),"") -> ESP. SEGURIDAD | AI21: SI | AJ21: SI | AM21: =IF(COUNTIF(G21:AK21,"SI")=0,"",COUNTIF(G21:AK21,"SI")) -> 2 | AO21: =IF(COUNTIF(G21:AK21,"NO")=0,"",COUNTIF(G21:AK21,"NO")) | AQ21: =IF(COUNTIF(G21:AK21,"MED")=0,"",COUNTIF(G21:AK21,"MED")) | AS21: =IF(SUM(AM21:AQ21)=0,"",SUM(AM21:AQ21)) -> 2
E22: =IFERROR(VLOOKUP(C22,'DATOS GRALES 1'!$B$2:$E$50,4,0),"") | AM22: =IF(COUNTIF(G22:AK22,"SI")=0,"",COUNTIF(G22:AK22,"SI")) | AO22: =IF(COUNTIF(G22:AK22,"NO")=0,"",COUNTIF(G22:AK22,"NO")) | AQ22: =IF(COUNTIF(G22:AK22,"MED")=0,"",COUNTIF(G22:AK22,"MED")) | AS22: =IF(SUM(AM22:AQ22)=0,"",SUM(AM22:AQ22))
C23: OBREROS | G23: OBREROS
C24: NAVARRO LOZANO, ANGEL JAROL | E24: =IFERROR(VLOOKUP(C24,'DATOS GRALES 1'!B2:E50,4,0),"") -> PEON | O24: SI | P24: SI | Q24: SI | R24: SI | S24: SI | U24: SI | V24: SI | W24: SI | X24: SI | Y24: SI | Z24: SI | AB24: SI | AC24: SI | AD24: SI | AE24: SI | AF24: SI | AG24: SI | AI24: SI | AJ24: SI | AM24: =IF(COUNTIF(G24:AK24,"SI")=0,"",COUNTIF(G24:AK24,"SI")) -> 19 | AO24: =IF(COUNTIF(G24:AK24,"NO")=0,"",COUNTIF(G24:AK24,"NO")) | AQ24: =IF(COUNTIF(G24:AK24,"MED")=0,"",COUNTIF(G24:AK24,"MED")) | AS24: =IF(SUM(AM24:AQ24)=0,"",SUM(AM24:AQ24)) -> 19
C25: JEREMIAS PALOMINO, NORBERTO LEONCIO | E25: =IFERROR(VLOOKUP(C25,'DATOS GRALES 1'!B3:E47,4,0),"") -> PEON | O25: SI | P25: SI | Q25: SI | R25: SI | S25: SI | U25: SI | V25: SI | W25: SI | X25: SI | Y25: NO | Z25: NO | AB25: SI | AC25: SI | AD25: SI | AE25: SI | AF25: SI | AG25: SI | AI25: SI | AJ25: SI | AM25: =IF(COUNTIF(G25:AK25,"SI")=0,"",COUNTIF(G25:AK25,"SI")) -> 17 | AO25: =IF(COUNTIF(G25:AK25,"NO")=0,"",COUNTIF(G25:AK25,"NO")) -> 2 | AQ25: =IF(COUNTIF(G25:AK25,"MED")=0,"",COUNTIF(G25:AK25,"MED")) | AS25: =IF(SUM(AM25:AQ25)=0,"",SUM(AM25:AQ25)) -> 19 | AU25: 29/09/2025 llego 8:00 am
C26: LOZANO MALDONADO, HERNAN | E26: =IFERROR(VLOOKUP(C26,'DATOS GRALES 1'!B4:E47,4,0),"") -> PEON | O26: SI | P26: SI | Q26: SI | R26: SI | S26: SI | U26: SI | V26: SI | W26: SI | X26: SI | Y26: SI | Z26: SI | AB26: SI | AC26: SI | AD26: SI | AE26: SI | AF26: SI | AG26: SI | AI26: SI | AJ26: SI | AM26: =IF(COUNTIF(G26:AK26,"SI")=0,"",COUNTIF(G26:AK26,"SI")) -> 19 | AO26: =IF(COUNTIF(G26:AK26,"NO")=0,"",COUNTIF(G26:AK26,"NO")) | AQ26: =IF(COUNTIF(G26:AK26,"MED")=0,"",COUNTIF(G26:AK26,"MED")) | AS26: =IF(SUM(AM26:AQ26)=0,"",SUM(AM26:AQ26)) -> 19
C27: PIÑA CHUJANDAMA, KEVIN | E27: =IFERROR(VLOOKUP(C27,'DATOS GRALES 1'!B5:E48,4,0),"") -> PEON | O27: SI | P27: SI. | Q27: SI | R27: SI | S27: SI | U27: SI | V27: SI | W27: SI | X27: SI | Y27: SI | Z27: SI | AB27: SI | AC27: SI | AD27: SI | AE27: SI | AF27: SI | AG27: SI | AI27: SI | AJ27: SI | AM27: =IF(COUNTIF(G27:AK27,"SI")=0,"",COUNTIF(G27:AK27,"SI")) -> 18 | AO27: =IF(COUNTIF(G27:AK27,"NO")=0,"",COUNTIF(G27:AK27,"NO")) | AQ27: =IF(COUNTIF(G27:AK27,"MED")=0,"",COUNTIF(G27:AK27,"MED")) | AS27: =IF(SUM(AM27:AQ27)=0,"",SUM(AM27:AQ27)) -> 18
C28: MAYTAHUARI ACOSTA, SAMMER AXEL | E28: =IFERROR(VLOOKUP(C28,'DATOS GRALES 1'!B6:E52,4,0),"") -> OPERARIO | O28: SI | P28: SI | Q28: SI | R28: SI | S28: SI | U28: SI | V28: SI | W28: SI | X28: SI | Y28: SI | Z28: SI | AB28: SI | AC28: SI | AD28: SI | AE28: SI | AF28: SI | AG28: SI | AI28: NO | AJ28: SI | AM28: =IF(COUNTIF(G28:AK28,"SI")=0,"",COUNTIF(G28:AK28,"SI")) -> 18 | AO28: =IF(COUNTIF(G28:AK28,"NO")=0,"",COUNTIF(G28:AK28,"NO")) -> 1 | AQ28: =IF(COUNTIF(G28:AK28,"MED")=0,"",COUNTIF(G28:AK28,"MED")) | AS28: =IF(SUM(AM28:AQ28)=0,"",SUM(AM28:AQ28)) -> 19
C29: CORDOVA ANGULO, JUAN | E29: =IFERROR(VLOOKUP(C29,'DATOS GRALES 1'!B7:E53,4,0),"") -> PEON | O29: SI | P29: SI | Q29: SI | R29: SI | S29: SI | U29: NO | V29: SI | W29: SI | X29: SI | Y29: SI | Z29: SI | AB29: SI | AC29: SI | AD29: SI | AE29: SI | AF29: SI | AG29: SI | AI29: SI | AJ29: SI | AM29: =IF(COUNTIF(G29:AK29,"SI")=0,"",COUNTIF(G29:AK29,"SI")) -> 18 | AO29: =IF(COUNTIF(G29:AK29,"NO")=0,"",COUNTIF(G29:AK29,"NO")) -> 1 | AQ29: =IF(COUNTIF(G29:AK29,"MED")=0,"",COUNTIF(G29:AK29,"MED")) | AS29: =IF(SUM(AM29:AQ29)=0,"",SUM(AM29:AQ29)) -> 19
C30: ROJAS SANDOVAL, JAVIER ELOY | E30: =IFERROR(VLOOKUP(C30,'DATOS GRALES 1'!B8:E54,4,0),"") -> OPERARIO/VOLQUETERO | O30: SI | P30: SI | Q30: SI | R30: SI | S30: SI | U30: SI | V30: SI | W30: SI | X30: SI | Y30: SI | Z30: SI | AB30: SI | AC30: SI | AD30: SI | AE30: SI | AF30: SI | AG30: SI | AI30: SI | AJ30: SI | AM30: =IF(COUNTIF(G30:AK30,"SI")=0,"",COUNTIF(G30:AK30,"SI")) -> 19 | AO30: =IF(COUNTIF(G30:AK30,"NO")=0,"",COUNTIF(G30:AK30,"NO")) | AQ30: =IF(COUNTIF(G30:AK30,"MED")=0,"",COUNTIF(G30:AK30,"MED")) | AS30: =IF(SUM(AM30:AQ30)=0,"",SUM(AM30:AQ30)) -> 19 | AU30: 29/09/2025 llego 9:00 am
C31: CHINO PILCO SIMON | E31: =IFERROR(VLOOKUP(C31,'DATOS GRALES 1'!B9:E55,4,0),"") -> PEON/CHOFER | O31: SI | AM31: =IF(COUNTIF(G31:AK31,"SI")=0,"",COUNTIF(G31:AK31,"SI")) -> 1 | AO31: =IF(COUNTIF(G31:AK31,"NO")=0,"",COUNTIF(G31:AK31,"NO")) | AQ31: =IF(COUNTIF(G31:AK31,"MED")=0,"",COUNTIF(G31:AK31,"MED")) | AS31: =IF(SUM(AM31:AQ31)=0,"",SUM(AM31:AQ31)) -> 1
C32: CHACON ORTIZ, JOSE ANTONIO | E32: =IFERROR(VLOOKUP(C32,'DATOS GRALES 1'!B10:E56,4,0),"") -> OPERARIO | U32: SI | V32: SI | W32: SI | X32: SI | Y32: SI | Z32: SI | AB32: SI | AC32: SI | AD32: SI | AE32: SI | AF32: SI | AG32: SI | AI32: SI | AJ32: SI | AM32: =IF(COUNTIF(G32:AK32,"SI")=0,"",COUNTIF(G32:AK32,"SI")) -> 14 | AO32: =IF(COUNTIF(G32:AK32,"NO")=0,"",COUNTIF(G32:AK32,"NO")) | AQ32: =IF(COUNTIF(G32:AK32,"MED")=0,"",COUNTIF(G32:AK32,"MED")) | AS32: =IF(SUM(AM32:AQ32)=0,"",SUM(AM32:AQ32)) -> 14
C33: ORDOÑEZ CONDORI, GILBERTO | E33: =IFERROR(VLOOKUP(C33,'DATOS GRALES 1'!B11:E57,4,0),"") -> PEON | U33: SI | V33: SI | W33: SI | X33: SI | Y33: SI | Z33: SI | AB33: SI | AC33: SI | AD33: SI | AE33: SI | AF33: SI | AG33: SI | AI33: SI | AJ33: SI | AM33: =IF(COUNTIF(G33:AK33,"SI")=0,"",COUNTIF(G33:AK33,"SI")) -> 14 | AO33: =IF(COUNTIF(G33:AK33,"NO")=0,"",COUNTIF(G33:AK33,"NO")) | AQ33: =IF(COUNTIF(G33:AK33,"MED")=0,"",COUNTIF(G33:AK33,"MED")) | AS33: =IF(SUM(AM33:AQ33)=0,"",SUM(AM33:AQ33)) -> 14
C34: GUTARATE SABINO, ADRIEL ANTONY | E34: =IFERROR(VLOOKUP(C34,'DATOS GRALES 1'!B12:E58,4,0),"") -> OPERARIO | AB34: SI | AC34: SI | AD34: SI | AE34: SI | AF34: SI | AG34: SI | AI34: NO | AJ34: SI | AM34: =IF(COUNTIF(G34:AK34,"SI")=0,"",COUNTIF(G34:AK34,"SI")) -> 7 | AO34: =IF(COUNTIF(G34:AK34,"NO")=0,"",COUNTIF(G34:AK34,"NO")) -> 1 | AQ34: =IF(COUNTIF(G34:AK34,"MED")=0,"",COUNTIF(G34:AK34,"MED")) | AS34: =IF(SUM(AM34:AQ34)=0,"",SUM(AM34:AQ34)) -> 8
C35: QUISPE LIMACHE, ROGELIO | E35: =IFERROR(VLOOKUP(C35,'DATOS GRALES 1'!B13:E59,4,0),"") -> OPERARIO | AB35: SI | AC35: SI | AD35: SI | AE35: SI | AF35: SI | AG35: SI | AI35: SI | AJ35: SI | AM35: =IF(COUNTIF(G35:AK35,"SI")=0,"",COUNTIF(G35:AK35,"SI")) -> 8 | AO35: =IF(COUNTIF(G35:AK35,"NO")=0,"",COUNTIF(G35:AK35,"NO")) | AQ35: =IF(COUNTIF(G35:AK35,"MED")=0,"",COUNTIF(G35:AK35,"MED")) | AS35: =IF(SUM(AM35:AQ35)=0,"",SUM(AM35:AQ35)) -> 8
C36: APASTEGUI GRANDEZ, LUIS ALFREDO | E36: =IFERROR(VLOOKUP(C36,'DATOS GRALES 1'!B14:E60,4,0),"") -> PEON | AB36: SI | AC36: SI | AD36: SI | AE36: SI | AF36: SI | AG36: SI | AI36: SI | AJ36: SI | AM36: =IF(COUNTIF(G36:AK36,"SI")=0,"",COUNTIF(G36:AK36,"SI")) -> 8 | AO36: =IF(COUNTIF(G36:AK36,"NO")=0,"",COUNTIF(G36:AK36,"NO")) | AQ36: =IF(COUNTIF(G36:AK36,"MED")=0,"",COUNTIF(G36:AK36,"MED")) | AS36: =IF(SUM(AM36:AQ36)=0,"",SUM(AM36:AQ36)) -> 8
C37: VILLEGAS, ROGER | E37: =IFERROR(VLOOKUP(C37,'DATOS GRALES 1'!B15:E61,4,0),"") -> OPERARIO MAQU. | Z37: SI | AB37: SI | AC37: SI | AD37: SI | AE37: SI | AF37: SI | AG37: SI | AI37: SI | AJ37: SI | AM37: =IF(COUNTIF(G37:AK37,"SI")=0,"",COUNTIF(G37:AK37,"SI")) -> 9 | AO37: =IF(COUNTIF(G37:AK37,"NO")=0,"",COUNTIF(G37:AK37,"NO")) | AQ37: =IF(COUNTIF(G37:AK37,"MED")=0,"",COUNTIF(G37:AK37,"MED")) | AS37: =IF(SUM(AM37:AQ37)=0,"",SUM(AM37:AQ37)) -> 9 | AU37: 22/09/2025 llego tarde | AV37: 29/09/2025 llego 9:00 am
C38: TUANAMA PILCO, CHRIS | E38: =IFERROR(VLOOKUP(C38,'DATOS GRALES 1'!B16:E62,4,0),"") -> PEON | AB38: NO | AC38: SI | AD38: SI | AE38: SI | AF38: SI | AG38: SI | AI38: SI | AJ38: SI | AM38: =IF(COUNTIF(G38:AK38,"SI")=0,"",COUNTIF(G38:AK38,"SI")) -> 7 | AO38: =IF(COUNTIF(G38:AK38,"NO")=0,"",COUNTIF(G38:AK38,"NO")) -> 1 | AQ38: =IF(COUNTIF(G38:AK38,"MED")=0,"",COUNTIF(G38:AK38,"MED")) | AS38: =IF(SUM(AM38:AQ38)=0,"",SUM(AM38:AQ38)) -> 8 | AU38: 22 09 2025 llego media dia
C39: CACERES CALACHUA, YEYSON JORGE | E39: =IFERROR(VLOOKUP(C39,'DATOS GRALES 1'!B17:E63,4,0),"") -> OPERARIO | AB39: si | AC39: SI | AD39: SI | AE39: SI | AF39: SI | AG39: SI | AI39: SI | AJ39: SI | AM39: =IF(COUNTIF(G39:AK39,"SI")=0,"",COUNTIF(G39:AK39,"SI")) -> 8 | AO39: =IF(COUNTIF(G39:AK39,"NO")=0,"",COUNTIF(G39:AK39,"NO")) | AQ39: =IF(COUNTIF(G39:AK39,"MED")=0,"",COUNTIF(G39:AK39,"MED")) | AS39: =IF(SUM(AM39:AQ39)=0,"",SUM(AM39:AQ39)) -> 8 | AU39: 29/09/25 LLEGO 7:12
C40: MAQUERA QUISPE, LEONIDAS EDWIN | E40: =IFERROR(VLOOKUP(C40,'DATOS GRALES 1'!B18:E64,4,0),"") -> OPERARIO | AI40: SI | AJ40: SI | AM40: =IF(COUNTIF(G40:AK40,"SI")=0,"",COUNTIF(G40:AK40,"SI")) -> 2 | AO40: =IF(COUNTIF(G40:AK40,"NO")=0,"",COUNTIF(G40:AK40,"NO")) | AQ40: =IF(COUNTIF(G40:AK40,"MED")=0,"",COUNTIF(G40:AK40,"MED")) | AS40: =IF(SUM(AM40:AQ40)=0,"",SUM(AM40:AQ40)) -> 2
E41: =IFERROR(VLOOKUP(C41,'DATOS GRALES 1'!B19:E65,4,0),"") | AM41: =IF(COUNTIF(G41:AK41,"SI")=0,"",COUNTIF(G41:AK41,"SI")) | AO41: =IF(COUNTIF(G41:AK41,"NO")=0,"",COUNTIF(G41:AK41,"NO")) | AQ41: =IF(COUNTIF(G41:AK41,"MED")=0,"",COUNTIF(G41:AK41,"MED")) | AS41: =IF(SUM(AM41:AQ41)=0,"",SUM(AM41:AQ41))
E42: =IFERROR(VLOOKUP(C42,'DATOS GRALES 1'!B20:E66,4,0),"") | AM42: =IF(COUNTIF(G42:AK42,"SI")=0,"",COUNTIF(G42:AK42,"SI")) | AO42: =IF(COUNTIF(G42:AK42,"NO")=0,"",COUNTIF(G42:AK42,"NO")) | AQ42: =IF(COUNTIF(G42:AK42,"MED")=0,"",COUNTIF(G42:AK42,"MED")) | AS42: =IF(SUM(AM42:AQ42)=0,"",SUM(AM42:AQ42))
E43: =IFERROR(VLOOKUP(C43,'DATOS GRALES 1'!B21:E67,4,0),"") | AM43: =IF(COUNTIF(G43:AK43,"SI")=0,"",COUNTIF(G43:AK43,"SI")) | AO43: =IF(COUNTIF(G43:AK43,"NO")=0,"",COUNTIF(G43:AK43,"NO")) | AQ43: =IF(COUNTIF(G43:AK43,"MED")=0,"",COUNTIF(G43:AK43,"MED")) | AS43: =IF(SUM(AM43:AQ43)=0,"",SUM(AM43:AQ43))
E44: =IFERROR(VLOOKUP(C44,'DATOS GRALES 1'!B22:E68,4,0),"") | AM44: =IF(COUNTIF(G44:AK44,"SI")=0,"",COUNTIF(G44:AK44,"SI")) | AO44: =IF(COUNTIF(G44:AK44,"NO")=0,"",COUNTIF(G44:AK44,"NO")) | AQ44: =IF(COUNTIF(G44:AK44,"MED")=0,"",COUNTIF(G44:AK44,"MED")) | AS44: =IF(SUM(AM44:AQ44)=0,"",SUM(AM44:AQ44))
E45: =IFERROR(VLOOKUP(C45,'DATOS GRALES 1'!B23:E69,4,0),"") | AM45: =IF(COUNTIF(G45:AK45,"SI")=0,"",COUNTIF(G45:AK45,"SI")) | AO45: =IF(COUNTIF(G45:AK45,"NO")=0,"",COUNTIF(G45:AK45,"NO")) | AQ45: =IF(COUNTIF(G45:AK45,"MED")=0,"",COUNTIF(G45:AK45,"MED")) | AS45: =IF(SUM(AM45:AQ45)=0,"",SUM(AM45:AQ45))
E46: =IFERROR(VLOOKUP(C46,'DATOS GRALES 1'!B24:E70,4,0),"") | AM46: =IF(COUNTIF(G46:AK46,"SI")=0,"",COUNTIF(G46:AK46,"SI")) | AO46: =IF(COUNTIF(G46:AK46,"NO")=0,"",COUNTIF(G46:AK46,"NO")) | AQ46: =IF(COUNTIF(G46:AK46,"MED")=0,"",COUNTIF(G46:AK46,"MED")) | AS46: =IF(SUM(AM46:AQ46)=0,"",SUM(AM46:AQ46))
E47: =IFERROR(VLOOKUP(C47,'DATOS GRALES 1'!B25:E71,4,0),"") | AM47: =IF(COUNTIF(G47:AK47,"SI")=0,"",COUNTIF(G47:AK47,"SI")) | AO47: =IF(COUNTIF(G47:AK47,"NO")=0,"",COUNTIF(G47:AK47,"NO")) | AQ47: =IF(COUNTIF(G47:AK47,"MED")=0,"",COUNTIF(G47:AK47,"MED")) | AS47: =IF(SUM(AM47:AQ47)=0,"",SUM(AM47:AQ47))
E48: =IFERROR(VLOOKUP(C48,'DATOS GRALES 1'!B26:E72,4,0),"") | AM48: =IF(COUNTIF(G48:AK48,"SI")=0,"",COUNTIF(G48:AK48,"SI")) | AO48: =IF(COUNTIF(G48:AK48,"NO")=0,"",COUNTIF(G48:AK48,"NO")) | AQ48: =IF(COUNTIF(G48:AK48,"MED")=0,"",COUNTIF(G48:AK48,"MED")) | AS48: =IF(SUM(AM48:AQ48)=0,"",SUM(AM48:AQ48))
E49: =IFERROR(VLOOKUP(C49,'DATOS GRALES 1'!B27:E73,4,0),"") | AM49: =IF(COUNTIF(G49:AK49,"SI")=0,"",COUNTIF(G49:AK49,"SI")) | AO49: =IF(COUNTIF(G49:AK49,"NO")=0,"",COUNTIF(G49:AK49,"NO")) | AQ49: =IF(COUNTIF(G49:AK49,"MED")=0,"",COUNTIF(G49:AK49,"MED")) | AS49: =IF(SUM(AM49:AQ49)=0,"",SUM(AM49:AQ49))
E50: =IFERROR(VLOOKUP(C50,'DATOS GRALES 1'!B28:E74,4,0),"") | AM50: =IF(COUNTIF(G50:AK50,"SI")=0,"",COUNTIF(G50:AK50,"SI")) | AO50: =IF(COUNTIF(G50:AK50,"NO")=0,"",COUNTIF(G50:AK50,"NO")) | AQ50: =IF(COUNTIF(G50:AK50,"MED")=0,"",COUNTIF(G50:AK50,"MED")) | AS50: =IF(SUM(AM50:AQ50)=0,"",SUM(AM50:AQ50))
E51: =IFERROR(VLOOKUP(C51,'DATOS GRALES 1'!B29:E75,4,0),"") | AM51: =IF(COUNTIF(G51:AK51,"SI")=0,"",COUNTIF(G51:AK51,"SI")) | AO51: =IF(COUNTIF(G51:AK51,"NO")=0,"",COUNTIF(G51:AK51,"NO")) | AQ51: =IF(COUNTIF(G51:AK51,"MED")=0,"",COUNTIF(G51:AK51,"MED")) | AS51: =IF(SUM(AM51:AQ51)=0,"",SUM(AM51:AQ51))

Sheet ASISTENCIA OCTUBRE
C1: Registro y Control de Asistencia
C4: Escoja Mes: | G4: Setiembre | J4: ← Item Lista Desplegable | P4: Empresa: | S4: FSA Constructora | X4: El Periodo Comprende | AF4: Mes: | AI4: Año: | AO4: Horas Extras: | AQ4: NO
P5: Obra: | S5: Ticapampa | X5: ="Desde: "&TEXT(DATE(G6,MONTH(G4&1),1),"mmm-dd-yy")&" Hasta "&TEXT(EOMONTH(DATE(G6,MONTH(G4&1),1),0),"mmm-dd-yy") -> Desde: Set-01-25 Hasta Set-30-25 | AF5: =G4 -> Setiembre | AI5: =G6 -> 2025
C6: Escoja Año: | G6: 2025 | J6: ← Introduzca manualmente | P6: Encargado: | S6: Ernesto Acuachi | AO6: Por Encima de: | AQ6: 8
I8: 45915 | J8: =I8+1 -> 45916 | K8: =J8+1 -> 45917 | L8: =K8+1 -> 45918 | M8: =L8+1 -> 45919 | N8: =M8+1 -> 45920 | O8: =N8+1 -> 45921 | P8: =O8+1 -> 45922 | Q8: =P8+1 -> 45923 | ... AM8: =AL8+1 -> 45945
AV9: Festivos | AW9: Columna1 | AX9: Columna2 | AY9: Columna3 | AZ9: Columna4 | BA9: Columna5 | BB9: Columna6 | BC9: Columna7 | BD9: Columna8 | BE9: Columna9 | BF9: Columna10 | BG9: Columna11 | BH9: Columna12 | BI9: Columna13 | BJ9: Columna14 | BK9: Columna15 | BL9: Columna16 | BM9: Columna17 | BN9: Columna18 | BO9: Columna19
AV10: 45658
AV11: 45866
AV12: 45867
C13: Apellido y Nombres | E13: Sueldo | F13: sueldo x dia | G13: Cargo | I13: =PROPER(LEFT(TEXT(I8,"dddd"),3)) -> Lun | J13: =PROPER(LEFT(TEXT(J8,"dddd"),3)) -> Mar | K13: =PROPER(LEFT(TEXT(K8,"dddd"),3)) -> Mié | L13: =PROPER(LEFT(TEXT(L8,"dddd"),3)) -> Jue | M13: =PROPER(LEFT(TEXT(M8,"dddd"),3)) -> Vie | N13: =PROPER(LEFT(TEXT(N8,"dddd"),3)) -> Sáb | O13: =PROPER(LEFT(TEXT(O8,"dddd"),3)) -> Dom | P13: =PROPER(LEFT(TEXT(P8,"dddd"),3)) -> Lun | ... AM13: =PROPER(LEFT(TEXT(AM8,"dddd"),3)) -> Mié | AO13: ASISTIO(SI) | AQ13: FALTA(NO) | AS13: MEDIO DIA(MED) | AU13: TOTAL | AV13: 45962 | AW13: SUELDO | AX13: HORAS EXTRAS | AY13: HORAS EXTRAS A PAGAR | AZ13: FECHA | BA13: ADELANTO 1 | BB13: FECHA | BC13: ADELANTO2 | BD13: FECHA | BE13: ADELANTO3 | BF13: FECHA | BG13: ADELANTO4 | BH13: TOTAL ADELANTOS | BI13: AFP SETIEMBRE MITAD FINAL | BJ13: CONAFOVICER AGOSTO MITAD | BK13: AFP OCTUBRE 1ERA MITAD | BL13: CONAFOVICER SETIEMBRE MITAD | BM13: TOTAL DESCUENTOS | BN13: SUMA TOTAL ADELANTOS Y DSCTOS | BO13: SUELDO NETO A DEPOSITAR
AV14: 46016
C15: NAVARRO LOZANO, ANGEL JAROL | E15: 3300 | F15: =E15/30 -> 110 | G15: =IFERROR(VLOOKUP(C15,'DATOS GRALES 1'!$B$2:$E$50,4,0),"") -> PEON | P15: SI | Q15: SI | R15: SI | S15: SI | T15: SI | U15: SI | V15: SI | W15: SI | X15: SI | Y15: SI | Z15: SI | AA15: SI | AB15: SI | AC15: SI | AD15: SI | AE15: SI | AF15: SI | AG15: SI | AH15: SI | AI15: SI | AJ15: SI | AK15: NO | AO15: =COUNTIF(I15:AM15,"SI") -> 21 | AQ15: =IF(COUNTIF(I15:AM15,"NO")=0,"",COUNTIF(I15:AM15,"NO")) -> 1 | AS15: =COUNTIF(I15:AM15,"MED") -> 0 | AU15: =IF(SUM(AO15:AS15)=0,"",SUM(AO15:AS15)) -> 22 | AV15: 46022 | AW15: =(F15/2*AS15)+(AO15*F15) -> 2310 | AX15: 8 | AY15: =F15/8*tFestivos46[[#This Row],[Columna2]] -> 110 | AZ15: 45910 | BA15: 520 | BB15: 45911 | BC15: 350 | BE15: 250 | BG15: 150 | BH15: =tFestivos46[[#This Row],[Columna5]]+tFestivos46[[#This Row],[Columna7]]+tFestivos46[[#This Row],[Columna9]]+tFestivos46[[#This Row],[Columna11]] -> 1270 | BI15: =(E15*13%)/2 -> 214.5 | BJ15: =(E15*2%)/2 -> 33 | BK15: =(E15*13%)/2 -> 214.5 | BL15: =(E15*2%)/2 -> 33 | BM15: =tFestivos46[[#This Row],[Columna13]]+tFestivos46[[#This Row],[Columna14]]+tFestivos46[[#This Row],[Columna15]]+tFestivos46[[#This Row],[Columna16]] -> 495 | BN15: =tFestivos46[[#This Row],[Columna12]]+tFestivos46[[#This Row],[Columna17]] -> 1765 | BO15: =tFestivos46[[#This Row],[Columna1]]-tFestivos46[[#This Row],[Columna18]] -> 545
C16: JEREMIAS PALOMINO, NORBERTO LEONCIO | E16: 3300 | F16: =E16/30 -> 110 | G16: =IFERROR(VLOOKUP(C16,'DATOS GRALES 1'!$B$2:$E$50,4,0),"") -> PEON | P16: SI | Q16: SI | R16: SI | S16: SI | T16: SI | U16: SI | V16: SI | W16: SI | X16: SI | Y16: SI | Z16: SI | AA16: SI | AB16: SI | AC16: SI | AD16: SI | AE16: SI | AF16: SI | AG16: SI | AH16: SI | AI16: SI | AJ16: SI | AK16: NO | AO16: =COUNTIF(I16:AM16,"SI") -> 21 | AQ16: =IF(COUNTIF(I16:AM16,"NO")=0,"",COUNTIF(I16:AM16,"NO")) -> 1 | AS16: =COUNTIF(I16:AM16,"MED") -> 0 | AU16: =IF(SUM(AO16:AS16)=0,"",SUM(AO16:AS16)) -> 22 | AW16: =(F16/2*AS16)+(AO16*F16) -> 2310 | AX16: 7 | AY16: =F16/8*tFestivos46[[#This Row],[Columna2]] -> 96.25 | BH16: =tFestivos46[[#This Row],[Columna5]]+tFestivos46[[#This Row],[Columna7]]+tFestivos46[[#This Row],[Columna9]]+tFestivos46[[#This Row],[Columna11]] -> 0 | BI16: =(E16*13%)/2 -> 214.5 | BJ16: =(E16*2%)/2 -> 33 | BK16: =(E16*13%)/2 -> 214.5 | BL16: =(E16*2%)/2 -> 33 | BM16: =tFestivos46[[#This Row],[Columna13]]+tFestivos46[[#This Row],[Columna14]]+tFestivos46[[#This Row],[Columna15]]+tFestivos46[[#This Row],[Columna16]] -> 495 | BN16: =tFestivos46[[#This Row],[Columna12]]+tFestivos46[[#This Row],[Columna17]] -> 495 | BO16: =tFestivos46[[#This Row],[Columna1]]-tFestivos46[[#This Row],[Columna18]] -> 1815
C17: LOZANO MALDONADO, HERNAN | E17: 3300 | F17: =E17/30 -> 110 | G17: =IFERROR(VLOOKUP(C17,'DATOS GRALES 1'!$B$2:$E$50,4,0),"") -> PEON | P17: SI | Q17: SI | R17: SI | S17: SI | T17: SI | U17: SI | V17: SI | W17: SI | X17: SI | Y17: SI | Z17: SI | AA17: SI | AB17: SI | AC17: SI | AD17: SI | AE17: SI | AF17: SI | AG17: SI | AH17: SI | AI17: SI | AJ17: SI | AK17: NO | AO17: =COUNTIF(I17:AM17,"SI") -> 21 | AQ17: =IF(COUNTIF(I17:AM17,"NO")=0,"",COUNTIF(I17:AM17,"NO")) -> 1 | AS17: =COUNTIF(I17:AM17,"MED") -> 0 | AU17: =IF(SUM(AO17:AS17)=0,"",SUM(AO17:AS17)) -> 22 | AW17: =(F17/2*AS17)+(AO17*F17) -> 2310 | AY17: =F17/8*tFestivos46[[#This Row],[Columna2]] -> 0 | BH17: =tFestivos46[[#This Row],[Columna5]]+tFestivos46[[#This Row],[Columna7]]+tFestivos46[[#This Row],[Columna9]]+tFestivos46[[#This Row],[Columna11]] -> 0 | BI17: =(E17*13%)/2 -> 214.5 | BJ17: =(E17*2%)/2 -> 33 | BK17: =(E17*13%)/2 -> 214.5 | BL17: =(E17*2%)/2 -> 33 | BM17: =tFestivos46[[#This Row],[Columna13]]+tFestivos46[[#This Row],[Columna14]]+tFestivos46[[#This Row],[Columna15]]+tFestivos46[[#This Row],[Columna16]] -> 495 | BN17: =tFestivos46[[#This Row],[Columna12]]+tFestivos46[[#This Row],[Columna17]] -> 495 | BO17: =tFestivos46[[#This Row],[Columna1]]-tFestivos46[[#This Row],[Columna18]] -> 1815
C18: PIÑA CHUJANDAMA, KEVIN | E18: 3300 | F18: =E18/30 -> 110 | G18: =IFERROR(VLOOKUP(C18,'DATOS GRALES 1'!$B$2:$E$50,4,0),"") -> PEON | P18: SI | Q18: SI | R18: SI | S18: SI | T18: SI | U18: SI | V18: SI | W18: SI | X18: SI | Y18: SI | Z18: SI | AA18: SI | AB18: SI | AC18: SI | AD18: SI | AE18: SI | AF18: SI | AG18: SI | AH18: SI | AI18: SI | AJ18: SI | AK18: NO | AO18: =COUNTIF(I18:AM18,"SI") -> 21 | AQ18: =IF(COUNTIF(I18:AM18,"NO")=0,"",COUNTIF(I18:AM18,"NO")) -> 1 | AS18: =COUNTIF(I18:AM18,"MED") -> 0 | AU18: =IF(SUM(AO18:AS18)=0,"",SUM(AO18:AS18)) -> 22 | AW18: =(F18/2*AS18)+(AO18*F18) -> 2310 | AY18: =F18/8*tFestivos46[[#This Row],[Columna2]] -> 0 | BH18: =tFestivos46[[#This Row],[Columna5]]+tFestivos46[[#This Row],[Columna7]]+tFestivos46[[#This Row],[Columna9]]+tFestivos46[[#This Row],[Columna11]] -> 0 | BI18: =(E18*13%)/2 -> 214.5 | BJ18: =(E18*2%)/2 -> 33 | BK18: =(E18*13%)/2 -> 214.5 | BL18: =(E18*2%)/2 -> 33 | BM18: =tFestivos46[[#This Row],[Columna13]]+tFestivos46[[#This Row],[Columna14]]+tFestivos46[[#This Row],[Columna15]]+tFestivos46[[#This Row],[Columna16]] -> 495 | BN18: =tFestivos46[[#This Row],[Columna12]]+tFestivos46[[#This Row],[Columna17]] -> 495 | BO18: =tFestivos46[[#This Row],[Columna1]]-tFestivos46[[#This Row],[Columna18]] -> 1815
C19: MAYTAHUARI ACOSTA, SAMMER AXEL | E19: 4200 | F19: =E19/30 -> 140 | G19: =IFERROR(VLOOKUP(C19,'DATOS GRALES 1'!$B$2:$E$50,4,0),"") -> OPERARIO | P19: SI | Q19: SI | R19: SI | S19: SI | T19: SI | U19: SI | V19: SI | W19: NO | X19: SI | Y19: SI | Z19: SI | AA19: SI | AB19: SI | AC19: NO | AD19: SI | AE19: SI | AF19: SI | AG19: SI | AH19: SI | AI19: SI | AJ19: SI | AK19: NO | AO19: =COUNTIF(I19:AM19,"SI") -> 19 | AQ19: =IF(COUNTIF(I19:AM19,"NO")=0,"",COUNTIF(I19:AM19,"NO")) -> 3 | AS19: =COUNTIF(I19:AM19,"MED") -> 0 | AU19: =IF(SUM(AO19:AS19)=0,"",SUM(AO19:AS19)) -> 22 | AW19: =(F19/2*AS19)+(AO19*F19) -> 2660 | AY19: =F19/8*tFestivos46[[#This Row],[Columna2]] -> 0 | BH19: =tFestivos46[[#This Row],[Columna5]]+tFestivos46[[#This Row],[Columna7]]+tFestivos46[[#This Row],[Columna9]]+tFestivos46[[#This Row],[Columna11]] -> 0 | BI19: =(E19*13%)/2 -> 273 | BJ19: =(E19*2%)/2 -> 42 | BK19: =(E19*13%)/2 -> 273 | BL19: =(E19*2%)/2 -> 42 | BM19: =tFestivos46[[#This Row],[Columna13]]+tFestivos46[[#This Row],[Columna14]]+tFestivos46[[#This Row],[Columna15]]+tFestivos46[[#This Row],[Columna16]] -> 630 | BN19: =tFestivos46[[#This Row],[Columna12]]+tFestivos46[[#This Row],[Columna17]] -> 630 | BO19: =tFestivos46[[#This Row],[Columna1]]-tFestivos46[[#This Row],[Columna18]] -> 2030
C20: CORDOVA ANGULO, JUAN | E20: 3300 | F20: =E20/30 -> 110 | G20: =IFERROR(VLOOKUP(C20,'DATOS GRALES 1'!$B$2:$E$50,4,0),"") -> PEON | P20: SI | Q20: SI | R20: SI | S20: SI | T20: SI | U20: SI | V20: SI | W20: SI | X20: SI | Y20: SI | Z20: SI | AA20: SI | AB20: SI | AC20: SI | AD20: SI | AE20: SI | AF20: SI | AG20: SI | AH20: SI | AI20: SI | AJ20: SI | AK20: NO | AO20: =COUNTIF(I20:AM20,"SI") -> 21 | AQ20: =IF(COUNTIF(I20:AM20,"NO")=0,"",COUNTIF(I20:AM20,"NO")) -> 1 | AS20: =COUNTIF(I20:AM20,"MED") -> 0 | AU20: =IF(SUM(AO20:AS20)=0,"",SUM(AO20:AS20)) -> 22 | AW20: =(F20/2*AS20)+(AO20*F20) -> 2310 | AY20: =F20/8*tFestivos46[[#This Row],[Columna2]] -> 0 | BH20: =tFestivos46[[#This Row],[Columna5]]+tFestivos46[[#This Row],[Columna7]]+tFestivos46[[#This Row],[Columna9]]+tFestivos46[[#This Row],[Columna11]] -> 0 | BI20: =(E20*13%)/2 -> 214.5 | BJ20: =(E20*2%)/2 -> 33 | BK20: =(E20*13%)/2 -> 214.5 | BL20: =(E20*2%)/2 -> 33 | BM20: =tFestivos46[[#This Row],[Columna13]]+tFestivos46[[#This Row],[Columna14]]+tFestivos46[[#This Row],[Columna15]]+tFestivos46[[#This Row],[Columna16]] -> 495 | BN20: =tFestivos46[[#This Row],[Columna12]]+tFestivos46[[#This Row],[Columna17]] -> 495 | BO20: =tFestivos46[[#This Row],[Columna1]]-tFestivos46[[#This Row],[Columna18]] -> 1815
C21: ROJAS SANDOVAL, JAVIER ELOY | E21: 4200 | F21: =E21/30 -> 140 | G21: =IFERROR(VLOOKUP(C21,'DATOS GRALES 1'!$B$2:$E$50,4,0),"") -> OPERARIO/VOLQUETERO | P21: SI | Q21: SI | R21: SI | S21: SI | T21: SI | U21: SI | V21: SI | W21: SI | X21: SI | Y21: SI | Z21: SI | AA21: MED | AB21: SI | AC21: SI | AD21: SI | AE21: SI | AF21: SI | AG21: SI | AH21: MED | AI21: SI | AJ21: SI | AK21: NO | AO21: =COUNTIF(I21:AM21,"SI") -> 19 | AQ21: =IF(COUNTIF(I21:AM21,"NO")=0,"",COUNTIF(I21:AM21,"NO")) -> 1 | AS21: =COUNTIF(I21:AM21,"MED") -> 2 | AU21: =IF(SUM(AO21:AS21)=0,"",SUM(AO21:AS21)) -> 22 | AW21: =(F21/2*AS21)+(AO21*F21) -> 2800 | AY21: =F21/8*tFestivos46[[#This Row],[Columna2]] -> 0 | BH21: =tFestivos46[[#This Row],[Columna5]]+tFestivos46[[#This Row],[Columna7]]+tFestivos46[[#This Row],[Columna9]]+tFestivos46[[#This Row],[Columna11]] -> 0 | BI21: =(E21*13%)/2 -> 273 | BJ21: =(E21*2%)/2 -> 42 | BK21: =(E21*13%)/2 -> 273 | BL21: =(E21*2%)/2 -> 42 | BM21: =tFestivos46[[#This Row],[Columna13]]+tFestivos46[[#This Row],[Columna14]]+tFestivos46[[#This Row],[Columna15]]+tFestivos46[[#This Row],[Columna16]] -> 630 | BN21: =tFestivos46[[#This Row],[Columna12]]+tFestivos46[[#This Row],[Columna17]] -> 630 | BO21: =tFestivos46[[#This Row],[Columna1]]-tFestivos46[[#This Row],[Columna18]] -> 2170
C22: CHACON ORTIZ, JOSE ANTONIO | E22: 4200 | F22: =E22/30 -> 140 | G22: =IFERROR(VLOOKUP(C22,'DATOS GRALES 1'!$B$2:$E$50,4,0),"") -> OPERARIO | I22: SI | J22: SI | K22: SI | L22: SI | M22: SI | N22: SI | O22: SI | P22: SI | Q22: SI | R22: SI | S22: SI | T22: SI | U22: SI | V22: SI | W22: SI | X22: SI | Y22: SI | Z22: SI | AA22: SI | AB22: SI | AC22: SI | AD22: SI | AE22: SI | AF22: SI | AG22: SI | AH22: SI | AI22: SI | AJ22: SI | AK22: SI | AO22: =COUNTIF(I22:AM22,"SI") -> 29 | AQ22: =IF(COUNTIF(I22:AM22,"NO")=0,"",COUNTIF(I22:AM22,"NO")) | AS22: =COUNTIF(I22:AM22,"MED") -> 0 | AU22: =IF(SUM(AO22:AS22)=0,"",SUM(AO22:AS22)) -> 29 | AW22: =(F22/2*AS22)+(AO22*F22) -> 4060 | AY22: =F22/8*tFestivos46[[#This Row],[Columna2]] -> 0 | BH22: =tFestivos46[[#This Row],[Columna5]]+tFestivos46[[#This Row],[Columna7]]+tFestivos46[[#This Row],[Columna9]]+tFestivos46[[#This Row],[Columna11]] -> 0 | BI22: =(E22*13%)/2 -> 273 | BJ22: =(E22*2%)/2 -> 42 | BK22: =(E22*13%)/2 -> 273 | BL22: =(E22*2%)/2 -> 42 | BM22: =tFestivos46[[#This Row],[Columna13]]+tFestivos46[[#This Row],[Columna14]]+tFestivos46[[#This Row],[Columna15]]+tFestivos46[[#This Row],[Columna16]] -> 630 | BN22: =tFestivos46[[#This Row],[Columna12]]+tFestivos46[[#This Row],[Columna17]] -> 630 | BO22: =tFestivos46[[#This Row],[Columna1]]-tFestivos46[[#This Row],[Columna18]] -> 3430
C23: ORDOÑEZ CONDORI, GILBERTO | E23: 3300 | F23: =E23/30 -> 110 | G23: =IFERROR(VLOOKUP(C23,'DATOS GRALES 1'!$B$2:$E$50,4,0),"") -> PEON | I23: SI | J23: SI | K23: SI | L23: SI | M23: SI | N23: SI | O23: SI | P23: SI | Q23: SI | R23: SI | S23: SI | T23: SI | U23: SI | V23: SI | W23: SI | X23: SI | Y23: SI | Z23: SI | AA23: SI | AB23: SI | AC23: SI | AD23: SI | AE23: SI | AF23: SI | AG23: SI | AH23: SI | AI23: SI | AJ23: SI | AK23: SI | AO23: =COUNTIF(I23:AM23,"SI") -> 29 | AQ23: =IF(COUNTIF(I23:AM23,"NO")=0,"",COUNTIF(I23:AM23,"NO")) | AS23: =COUNTIF(I23:AM23,"MED") -> 0 | AU23: =IF(SUM(AO23:AS23)=0,"",SUM(AO23:AS23)) -> 29 | AW23: =(F23/2*AS23)+(AO23*F23) -> 3190 | AY23: =F23/8*tFestivos46[[#This Row],[Columna2]] -> 0 | BH23: =tFestivos46[[#This Row],[Columna5]]+tFestivos46[[#This Row],[Columna7]]+tFestivos46[[#This Row],[Columna9]]+tFestivos46[[#This Row],[Columna11]] -> 0 | BI23: =(E23*13%)/2 -> 214.5 | BJ23: =(E23*2%)/2 -> 33 | BK23: =(E23*13%)/2 -> 214.5 | BL23: =(E23*2%)/2 -> 33 | BM23: =tFestivos46[[#This Row],[Columna13]]+tFestivos46[[#This Row],[Columna14]]+tFestivos46[[#This Row],[Columna15]]+tFestivos46[[#This Row],[Columna16]] -> 495 | BN23: =tFestivos46[[#This Row],[Columna12]]+tFestivos46[[#This Row],[Columna17]] -> 495 | BO23: =tFestivos46[[#This Row],[Columna1]]-tFestivos46[[#This Row],[Columna18]] -> 2695
C24: GUTARATE SABINO, ADRIEL ANTONY | E24: 4200 | F24: =E24/30 -> 140 | G24: =IFERROR(VLOOKUP(C24,'DATOS GRALES 1'!B2:E50,4,0),"") -> OPERARIO | P24: SI | Q24: SI | R24: SI | S24: SI | T24: SI | U24: SI | V24: SI | W24: NO | X24: SI | Y24: SI | Z24: SI | AA24: SI | AB24: SI | AC24: NO | AD24: SI | AE24: SI | AF24: SI | AG24: SI | AH24: SI | AI24: SI | AJ24: SI | AK24: NO | AO24: =COUNTIF(I24:AM24,"SI") -> 19 | AQ24: =IF(COUNTIF(I24:AM24,"NO")=0,"",COUNTIF(I24:AM24,"NO")) -> 3 | AS24: =COUNTIF(I24:AM24,"MED") -> 0 | AU24: =IF(SUM(AO24:AS24)=0,"",SUM(AO24:AS24)) -> 22 | AW24: =(F24/2*AS24)+(AO24*F24) -> 2660 | AY24: =F24/8*tFestivos46[[#This Row],[Columna2]] -> 0 | BH24: =tFestivos46[[#This Row],[Columna5]]+tFestivos46[[#This Row],[Columna7]]+tFestivos46[[#This Row],[Columna9]]+tFestivos46[[#This Row],[Columna11]] -> 0 | BI24: =(E24*13%)/2 -> 273 | BJ24: =(E24*2%)/2 -> 42 | BK24: =(E24*13%)/2 -> 273 | BL24: =(E24*2%)/2 -> 42 | BM24: =tFestivos46[[#This Row],[Columna13]]+tFestivos46[[#This Row],[Columna14]]+tFestivos46[[#This Row],[Columna15]]+tFestivos46[[#This Row],[Columna16]] -> 630 | BN24: =tFestivos46[[#This Row],[Columna12]]+tFestivos46[[#This Row],[Columna17]] -> 630 | BO24: =tFestivos46[[#This Row],[Columna1]]-tFestivos46[[#This Row],[Columna18]] -> 2030
C25: QUISPE LIMACHE, ROGELIO | E25: 4200 | F25: =E25/30 -> 140 | G25: =IFERROR(VLOOKUP(C25,'DATOS GRALES 1'!B3:E47,4,0),"") -> OPERARIO | P25: SI | Q25: SI | R25: SI | S25: SI | T25: SI | U25: SI | V25: SI | W25: SI | X25: SI | Y25: SI | Z25: SI | AA25: SI | AB25: SI | AC25: SI | AD25: SI | AE25: SI | AF25: SI | AG25: SI | AH25: SI | AI25: SI | AJ25: SI | AK25: NO | AO25: =COUNTIF(I25:AM25,"SI") -> 21 | AQ25: =IF(COUNTIF(I25:AM25,"NO")=0,"",COUNTIF(I25:AM25,"NO")) -> 1 | AS25: =COUNTIF(I25:AM25,"MED") -> 0 | AU25: =IF(SUM(AO25:AS25)=0,"",SUM(AO25:AS25)) -> 22 | AW25: =(F25/2*AS25)+(AO25*F25) -> 2940 | AY25: =F25/8*tFestivos46[[#This Row],[Columna2]] -> 0 | BH25: =tFestivos46[[#This Row],[Columna5]]+tFestivos46[[#This Row],[Columna7]]+tFestivos46[[#This Row],[Columna9]]+tFestivos46[[#This Row],[Columna11]] -> 0 | BI25: =(E25*13%)/2 -> 273 | BJ25: =(E25*2%)/2 -> 42 | BK25: =(E25*13%)/2 -> 273 | BL25: =(E25*2%)/2 -> 42 | BM25: =tFestivos46[[#This Row],[Columna13]]+tFestivos46[[#This Row],[Columna14]]+tFestivos46[[#This Row],[Columna15]]+tFestivos46[[#This Row],[Columna16]] -> 630 | BN25: =tFestivos46[[#This Row],[Columna12]]+tFestivos46[[#This Row],[Columna17]] -> 630 | BO25: =tFestivos46[[#This Row],[Columna1]]-tFestivos46[[#This Row],[Columna18]] -> 2310
C26: APASTEGUI GRANDEZ, LUIS ALFREDO | E26: 3300 | F26: =E26/30 -> 110 | G26: =IFERROR(VLOOKUP(C26,'DATOS GRALES 1'!B4:E47,4,0),"") -> PEON | P26: SI | Q26: SI | R26: SI | S26: SI | T26: SI | U26: SI | V26: SI | W26: SI | X26: SI | Y26: SI | Z26: SI | AA26: SI | AB26: SI | AC26: SI | AD26: SI | AE26: SI | AF26: SI | AG26: SI | AH26: SI | AI26: SI | AJ26: SI | AK26: SI | AO26: =COUNTIF(I26:AM26,"SI") -> 22 | AQ26: =IF(COUNTIF(I26:AM26,"NO")=0,"",COUNTIF(I26:AM26,"NO")) | AS26: =COUNTIF(I26:AM26,"MED") -> 0 | AU26: =IF(SUM(AO26:AS26)=0,"",SUM(AO26:AS26)) -> 22 | AW26: =(F26/2*AS26)+(AO26*F26) -> 2420 | AY26: =F26/8*tFestivos46[[#This Row],[Columna2]] -> 0 | BH26: =tFestivos46[[#This Row],[Columna5]]+tFestivos46[[#This Row],[Columna7]]+tFestivos46[[#This Row],[Columna9]]+tFestivos46[[#This Row],[Columna11]] -> 0 | BI26: =(E26*13%)/2 -> 214.5 | BJ26: =(E26*2%)/2 -> 33 | BK26: =(E26*13%)/2 -> 214.5 | BL26: =(E26*2%)/2 -> 33 | BM26: =tFestivos46[[#This Row],[Columna13]]+tFestivos46[[#This Row],[Columna14]]+tFestivos46[[#This Row],[Columna15]]+tFestivos46[[#This Row],[Columna16]] -> 495 | BN26: =tFestivos46[[#This Row],[Columna12]]+tFestivos46[[#This Row],[Columna17]] -> 495 | BO26: =tFestivos46[[#This Row],[Columna1]]-tFestivos46[[#This Row],[Columna18]] -> 1925
C27: TUANAMA PILCO, CHRIS | E27: 3300 | F27: =E27/30 -> 110 | G27: =IFERROR(VLOOKUP(C27,'DATOS GRALES 1'!B5:E48,4,0),"") -> PEON | P27: NO | Q27: SI | R27: SI | S27: SI | T27: SI | U27: SI | V27: NO | W27: SI | X27: SI | Y27: SI | Z27: SI | AA27: SI | AB27: SI | AC27: SI | AD27: SI | AE27: SI | AF27: SI | AG27: SI | AH27: SI | AI27: SI | AJ27: SI | AK27: NO | AO27: =COUNTIF(I27:AM27,"SI") -> 19 | AQ27: =IF(COUNTIF(I27:AM27,"NO")=0,"",COUNTIF(I27:AM27,"NO")) -> 3 | AS27: =COUNTIF(I27:AM27,"MED") -> 0 | AU27: =IF(SUM(AO27:AS27)=0,"",SUM(AO27:AS27)) -> 22 | AW27: =(F27/2*AS27)+(AO27*F27) -> 2090 | AY27: =F27/8*tFestivos46[[#This Row],[Columna2]] -> 0 | BH27: =tFestivos46[[#This Row],[Columna5]]+tFestivos46[[#This Row],[Columna7]]+tFestivos46[[#This Row],[Columna9]]+tFestivos46[[#This Row],[Columna11]] -> 0 | BI27: =(E27*13%)/2 -> 214.5 | BJ27: =(E27*2%)/2 -> 33 | BK27: =(E27*13%)/2 -> 214.5 | BL27: =(E27*2%)/2 -> 33 | BM27: =tFestivos46[[#This Row],[Columna13]]+tFestivos46[[#This Row],[Columna14]]+tFestivos46[[#This Row],[Columna15]]+tFestivos46[[#This Row],[Columna16]] -> 495 | BN27: =tFestivos46[[#This Row],[Columna12]]+tFestivos46[[#This Row],[Columna17]] -> 495 | BO27: =tFestivos46[[#This Row],[Columna1]]-tFestivos46[[#This Row],[Columna18]] -> 1595
C28: CACERES CALACHUA, YEYSON JORGE | E28: 4200 | F28: =E28/30 -> 140 | G28: =IFERROR(VLOOKUP(C28,'DATOS GRALES 1'!B6:E52,4,0),"") -> OPERARIO | P28: SI | Q28: SI | R28: SI | S28: SI | T28: SI | U28: SI | V28: SI | W28: SI | X28: SI | Y28: SI | Z28: SI | AA28: SI | AB28: SI | AC28: SI | AD28: SI | AE28: SI | AF28: SI | AG28: SI | AH28: SI | AI28: SI | AJ28: SI | AK28: NO | AO28: =COUNTIF(I28:AM28,"SI") -> 21 | AQ28: =IF(COUNTIF(I28:AM28,"NO")=0,"",COUNTIF(I28:AM28,"NO")) -> 1 | AS28: =COUNTIF(I28:AM28,"MED") -> 0 | AU28: =IF(SUM(AO28:AS28)=0,"",SUM(AO28:AS28)) -> 22 | AW28: =(F28/2*AS28)+(AO28*F28) -> 2940 | AY28: =F28/8*tFestivos46[[#This Row],[Columna2]] -> 0 | BH28: =tFestivos46[[#This Row],[Columna5]]+tFestivos46[[#This Row],[Columna7]]+tFestivos46[[#This Row],[Columna9]]+tFestivos46[[#This Row],[Columna11]] -> 0 | BI28: =(E28*13%)/2 -> 273 | BJ28: =(E28*2%)/2 -> 42 | BK28: =(E28*13%)/2 -> 273 | BL28: =(E28*2%)/2 -> 42 | BM28: =tFestivos46[[#This Row],[Columna13]]+tFestivos46[[#This Row],[Columna14]]+tFestivos46[[#This Row],[Columna15]]+tFestivos46[[#This Row],[Columna16]] -> 630 | BN28: =tFestivos46[[#This Row],[Columna12]]+tFestivos46[[#This Row],[Columna17]] -> 630 | BO28: =tFestivos46[[#This Row],[Columna1]]-tFestivos46[[#This Row],[Columna18]] -> 2310
C29: MAQUERA QUISPE, LEONIDAS EDWIN | E29: 4200 | F29: =E29/30 -> 140 | G29: =IFERROR(VLOOKUP(C29,'DATOS GRALES 1'!B7:E53,4,0),"") -> OPERARIO | W29: SI | X29: SI | Y29: SI | Z29: SI | AA29: SI | AB29: SI | AC29: SI | AD29: SI | AE29: SI | AF29: SI | AG29: SI | AH29: SI | AI29: SI | AJ29: SI | AK29: SI | AO29: =COUNTIF(I29:AM29,"SI") -> 15 | AQ29: =IF(COUNTIF(I29:AM29,"NO")=0,"",COUNTIF(I29:AM29,"NO")) | AS29: =COUNTIF(I29:AM29,"MED") -> 0 | AU29: =IF(SUM(AO29:AS29)=0,"",SUM(AO29:AS29)) -> 15 | AW29: =(F29/2*AS29)+(AO29*F29) -> 2100 | AY29: =F29/8*tFestivos46[[#This Row],[Columna2]] -> 0 | BH29: =tFestivos46[[#This Row],[Columna5]]+tFestivos46[[#This Row],[Columna7]]+tFestivos46[[#This Row],[Columna9]]+tFestivos46[[#This Row],[Columna11]] -> 0 | BI29: =(E29*13%)/2 -> 273 | BJ29: =(E29*2%)/2 -> 42 | BK29: =(E29*13%)/2 -> 273 | BL29: =(E29*2%)/2 -> 42 | BM29: =tFestivos46[[#This Row],[Columna13]]+tFestivos46[[#This Row],[Columna14]]+tFestivos46[[#This Row],[Columna15]]+tFestivos46[[#This Row],[Columna16]] -> 630 | BN29: =tFestivos46[[#This Row],[Columna12]]+tFestivos46[[#This Row],[Columna17]] -> 630 | BO29: =tFestivos46[[#This Row],[Columna1]]-tFestivos46[[#This Row],[Columna18]] -> 1470
C30: TACANAHUI CALISAYA NESTOR | E30: 3300 | F30: =E30/30 -> 110 | G30: =IFERROR(VLOOKUP(C30,'DATOS GRALES 1'!B8:E54,4,0),"") -> PEÓN | AD30: SI | AE30: SI | AF30: SI | AG30: SI | AH30: SI | AI30: SI | AJ30: SI | AK30: SI | AO30: =COUNTIF(I30:AM30,"SI") -> 8 | AQ30: =IF(COUNTIF(I30:AM30,"NO")=0,"",COUNTIF(I30:AM30,"NO")) | AS30: =COUNTIF(I30:AM30,"MED") -> 0 | AU30: =IF(SUM(AO30:AS30)=0,"",SUM(AO30:AS30)) -> 8 | AW30: =(F30/2*AS30)+(AO30*F30) -> 880 | AY30: =F30/8*tFestivos46[[#This Row],[Columna2]] -> 0 | BH30: =tFestivos46[[#This Row],[Columna5]]+tFestivos46[[#This Row],[Columna7]]+tFestivos46[[#This Row],[Columna9]]+tFestivos46[[#This Row],[Columna11]] -> 0 | BI30: =(E30*13%)/2 -> 214.5 | BJ30: =(E30*2%)/2 -> 33 | BK30: =(E30*13%)/2 -> 214.5 | BL30: =(E30*2%)/2 -> 33 | BM30: =tFestivos46[[#This Row],[Columna13]]+tFestivos46[[#This Row],[Columna14]]+tFestivos46[[#This Row],[Columna15]]+tFestivos46[[#This Row],[Columna16]] -> 495 | BN30: =tFestivos46[[#This Row],[Columna12]]+tFestivos46[[#This Row],[Columna17]] -> 495 | BO30: =tFestivos46[[#This Row],[Columna1]]-tFestivos46[[#This Row],[Columna18]] -> 385
C31: GUTARATE SABINO, RONEL ARTURO | E31: 3300 | F31: =E31/30 -> 110 | G31: =IFERROR(VLOOKUP(C31,'DATOS GRALES 1'!B9:E55,4,0),"") -> PEÓN | AD31: SI | AE31: SI | AF31: SI | AG31: SI | AH31: SI | AI31: SI | AJ31: SI | AK31: NO | AO31: =COUNTIF(I31:AM31,"SI") -> 7 | AQ31: =IF(COUNTIF(I31:AM31,"NO")=0,"",COUNTIF(I31:AM31,"NO")) -> 1 | AS31: =COUNTIF(I31:AM31,"MED") -> 0 | AU31: =IF(SUM(AO31:AS31)=0,"",SUM(AO31:AS31)) -> 8 | AW31: =(F31/2*AS31)+(AO31*F31) -> 770 | AY31: =F31/8*tFestivos46[[#This Row],[Columna2]] -> 0 | BH31: =tFestivos46[[#This Row],[Columna5]]+tFestivos46[[#This Row],[Columna7]]+tFestivos46[[#This Row],[Columna9]]+tFestivos46[[#This Row],[Columna11]] -> 0 | BI31: =(E31*13%)/2 -> 214.5 | BJ31: =(E31*2%)/2 -> 33 | BK31: =(E31*13%)/2 -> 214.5 | BL31: =(E31*2%)/2 -> 33 | BM31: =tFestivos46[[#This Row],[Columna13]]+tFestivos46[[#This Row],[Columna14]]+tFestivos46[[#This Row],[Columna15]]+tFestivos46[[#This Row],[Columna16]] -> 495 | BN31: =tFestivos46[[#This Row],[Columna12]]+tFestivos46[[#This Row],[Columna17]] -> 495 | BO31: =tFestivos46[[#This Row],[Columna1]]-tFestivos46[[#This Row],[Columna18]] -> 275
C32: ROSAS CHACHAJE, WILSON JHONY | E32: 4200 | F32: =E32/30 -> 140 | G32: =IFERROR(VLOOKUP(C32,'DATOS GRALES 1'!B10:E56,4,0),"") -> OPERARIO | AD32: SI | AE32: SI | AF32: SI | AG32: SI | AH32: SI | AI32: SI | AJ32: SI | AK32: NO | AO32: =COUNTIF(I32:AM32,"SI") -> 7 | AQ32: =IF(COUNTIF(I32:AM32,"NO")=0,"",COUNTIF(I32:AM32,"NO")) -> 1 | AS32: =COUNTIF(I32:AM32,"MED") -> 0 | AU32: =IF(SUM(AO32:AS32)=0,"",SUM(AO32:AS32)) -> 8 | AW32: =(F32/2*AS32)+(AO32*F32) -> 980 | AY32: =F32/8*tFestivos46[[#This Row],[Columna2]] -> 0 | BH32: =tFestivos46[[#This Row],[Columna5]]+tFestivos46[[#This Row],[Columna7]]+tFestivos46[[#This Row],[Columna9]]+tFestivos46[[#This Row],[Columna11]] -> 0 | BI32: =(E32*13%)/2 -> 273 | BJ32: =(E32*2%)/2 -> 42 | BK32: =(E32*13%)/2 -> 273 | BL32: =(E32*2%)/2 -> 42 | BM32: =tFestivos46[[#This Row],[Columna13]]+tFestivos46[[#This Row],[Columna14]]+tFestivos46[[#This Row],[Columna15]]+tFestivos46[[#This Row],[Columna16]] -> 630 | BN32: =tFestivos46[[#This Row],[Columna12]]+tFestivos46[[#This Row],[Columna17]] -> 630 | BO32: =tFestivos46[[#This Row],[Columna1]]-tFestivos46[[#This Row],[Columna18]] -> 350
C33: GAMARRA CONDORI, ANGEL | E33: 4200 | F33: =E33/30 -> 140 | G33: =IFERROR(VLOOKUP(C33,'DATOS GRALES 1'!B11:E57,4,0),"") -> OPERARIO | AK33: SI | AO33: =COUNTIF(I33:AM33,"SI") -> 1 | AQ33: =IF(COUNTIF(I33:AM33,"NO")=0,"",COUNTIF(I33:AM33,"NO")) | AS33: =COUNTIF(I33:AM33,"MED") -> 0 | AU33: =IF(SUM(AO33:AS33)=0,"",SUM(AO33:AS33)) -> 1 | AW33: =(F33/2*AS33)+(AO33*F33) -> 140 | AY33: =F33/8*tFestivos46[[#This Row],[Columna2]] -> 0 | BH33: =tFestivos46[[#This Row],[Columna5]]+tFestivos46[[#This Row],[Columna7]]+tFestivos46[[#This Row],[Columna9]]+tFestivos46[[#This Row],[Columna11]] -> 0 | BI33: =(E33*13%)/2 -> 273 | BJ33: =(E33*2%)/2 -> 42 | BK33: =(E33*13%)/2 -> 273 | BL33: =(E33*2%)/2 -> 42 | BM33: =tFestivos46[[#This Row],[Columna13]]+tFestivos46[[#This Row],[Columna14]]+tFestivos46[[#This Row],[Columna15]]+tFestivos46[[#This Row],[Columna16]] -> 630 | BN33: =tFestivos46[[#This Row],[Columna12]]+tFestivos46[[#This Row],[Columna17]] -> 630 | BO33: =tFestivos46[[#This Row],[Columna1]]-tFestivos46[[#This Row],[Columna18]] -> -490
F34: =E34/30 -> 0 | G34: =IFERROR(VLOOKUP(C34,'DATOS GRALES 1'!B12:E58,4,0),"") | AO34: =COUNTIF(I34:AM34,"SI") -> 0 | AQ34: =IF(COUNTIF(I34:AM34,"NO")=0,"",COUNTIF(I34:AM34,"NO")) | AS34: =COUNTIF(I34:AM34,"MED") -> 0 | AU34: =IF(SUM(AO34:AS34)=0,"",SUM(AO34:AS34)) | AW34: =(F34/2*AS34)+(AO34*F34) -> 0 | AY34: =F34/8*tFestivos46[[#This Row],[Columna2]] -> 0 | BH34: =tFestivos46[[#This Row],[Columna5]]+tFestivos46[[#This Row],[Columna7]]+tFestivos46[[#This Row],[Columna9]]+tFestivos46[[#This Row],[Columna11]] -> 0 | BI34: =(E34*13%)/2 -> 0 | BJ34: =(E34*2%)/2 -> 0 | BK34: =(E34*13%)/2 -> 0 | BL34: =(E34*2%)/2 -> 0 | BM34: =tFestivos46[[#This Row],[Columna13]]+tFestivos46[[#This Row],[Columna14]]+tFestivos46[[#This Row],[Columna15]]+tFestivos46[[#This Row],[Columna16]] -> 0 | BN34: =tFestivos46[[#This Row],[Columna12]]+tFestivos46[[#This Row],[Columna17]] -> 0 | BO34: =tFestivos46[[#This Row],[Columna1]]-tFestivos46[[#This Row],[Columna18]] -> 0
F35: =E35/30 -> 0 | G35: =IFERROR(VLOOKUP(C35,'DATOS GRALES 1'!B13:E59,4,0),"") | AO35: =COUNTIF(I35:AM35,"SI") -> 0 | AQ35: =IF(COUNTIF(I35:AM35,"NO")=0,"",COUNTIF(I35:AM35,"NO")) | AS35: =COUNTIF(I35:AM35,"MED") -> 0 | AU35: =IF(SUM(AO35:AS35)=0,"",SUM(AO35:AS35)) | AW35: =(F35/2*AS35)+(AO35*F35) -> 0 | AY35: =F35/8*tFestivos46[[#This Row],[Columna2]] -> 0 | BH35: =tFestivos46[[#This Row],[Columna5]]+tFestivos46[[#This Row],[Columna7]]+tFestivos46[[#This Row],[Columna9]]+tFestivos46[[#This Row],[Columna11]] -> 0 | BI35: =(E35*13%)/2 -> 0 | BJ35: =(E35*2%)/2 -> 0 | BK35: =(E35*13%)/2 -> 0 | BL35: =(E35*2%)/2 -> 0 | BM35: =tFestivos46[[#This Row],[Columna13]]+tFestivos46[[#This Row],[Columna14]]+tFestivos46[[#This Row],[Columna15]]+tFestivos46[[#This Row],[Columna16]] -> 0 | BN35: =tFestivos46[[#This Row],[Columna12]]+tFestivos46[[#This Row],[Columna17]] -> 0 | BO35: =tFestivos46[[#This Row],[Columna1]]-tFestivos46[[#This Row],[Columna18]] -> 0
F36: =E36/30 -> 0 | G36: =IFERROR(VLOOKUP(C36,'DATOS GRALES 1'!B14:E60,4,0),"") | AO36: =COUNTIF(I36:AM36,"SI") -> 0 | AQ36: =IF(COUNTIF(I36:AM36,"NO")=0,"",COUNTIF(I36:AM36,"NO")) | AS36: =COUNTIF(I36:AM36,"MED") -> 0 | AU36: =IF(SUM(AO36:AS36)=0,"",SUM(AO36:AS36)) | AW36: =(F36/2*AS36)+(AO36*F36) -> 0 | AY36: =F36/8*tFestivos46[[#This Row],[Columna2]] -> 0 | BH36: =tFestivos46[[#This Row],[Columna5]]+tFestivos46[[#This Row],[Columna7]]+tFestivos46[[#This Row],[Columna9]]+tFestivos46[[#This Row],[Columna11]] -> 0 | BI36: =(E36*13%)/2 -> 0 | BJ36: =(E36*2%)/2 -> 0 | BK36: =(E36*13%)/2 -> 0 | BL36: =(E36*2%)/2 -> 0 | BM36: =tFestivos46[[#This Row],[Columna13]]+tFestivos46[[#This Row],[Columna14]]+tFestivos46[[#This Row],[Columna15]]+tFestivos46[[#This Row],[Columna16]] -> 0 | BN36: =tFestivos46[[#This Row],[Columna12]]+tFestivos46[[#This Row],[Columna17]] -> 0 | BO36: =tFestivos46[[#This Row],[Columna1]]-tFestivos46[[#This Row],[Columna18]] -> 0
F37: =E37/30 -> 0 | G37: =IFERROR(VLOOKUP(C37,'DATOS GRALES 1'!B15:E61,4,0),"") | AO37: =COUNTIF(I37:AM37,"SI") -> 0 | AQ37: =IF(COUNTIF(I37:AM37,"NO")=0,"",COUNTIF(I37:AM37,"NO")) | AS37: =COUNTIF(I37:AM37,"MED") -> 0 | AU37: =IF(SUM(AO37:AS37)=0,"",SUM(AO37:AS37)) | AW37: =(F37/2*AS37)+(AO37*F37) -> 0 | AY37: =F37/8*tFestivos46[[#This Row],[Columna2]] -> 0 | BH37: =tFestivos46[[#This Row],[Columna5]]+tFestivos46[[#This Row],[Columna7]]+tFestivos46[[#This Row],[Columna9]]+tFestivos46[[#This Row],[Columna11]] -> 0 | BI37: =(E37*13%)/2 -> 0 | BJ37: =(E37*2%)/2 -> 0 | BK37: =(E37*13%)/2 -> 0 | BL37: =(E37*2%)/2 -> 0 | BM37: =tFestivos46[[#This Row],[Columna13]]+tFestivos46[[#This Row],[Columna14]]+tFestivos46[[#This Row],[Columna15]]+tFestivos46[[#This Row],[Columna16]] -> 0 | BN37: =tFestivos46[[#This Row],[Columna12]]+tFestivos46[[#This Row],[Columna17]] -> 0 | BO37: =tFestivos46[[#This Row],[Columna1]]-tFestivos46[[#This Row],[Columna18]] -> 0
F38: =E38/30 -> 0 | G38: =IFERROR(VLOOKUP(C38,'DATOS GRALES 1'!B16:E62,4,0),"") | AO38: =COUNTIF(I38:AM38,"SI") -> 0 | AQ38: =IF(COUNTIF(I38:AM38,"NO")=0,"",COUNTIF(I38:AM38,"NO")) | AS38: =COUNTIF(I38:AM38,"MED") -> 0 | AU38: =IF(SUM(AO38:AS38)=0,"",SUM(AO38:AS38)) | AW38: =(F38/2*AS38)+(AO38*F38) -> 0 | AY38: =F38/8*tFestivos46[[#This Row],[Columna2]] -> 0 | BH38: =tFestivos46[[#This Row],[Columna5]]+tFestivos46[[#This Row],[Columna7]]+tFestivos46[[#This Row],[Columna9]]+tFestivos46[[#This Row],[Columna11]] -> 0 | BI38: =(E38*13%)/2 -> 0 | BJ38: =(E38*2%)/2 -> 0 | BK38: =(E38*13%)/2 -> 0 | BL38: =(E38*2%)/2 -> 0 | BM38: =tFestivos46[[#This Row],[Columna13]]+tFestivos46[[#This Row],[Columna14]]+tFestivos46[[#This Row],[Columna15]]+tFestivos46[[#This Row],[Columna16]] -> 0 | BN38: =tFestivos46[[#This Row],[Columna12]]+tFestivos46[[#This Row],[Columna17]] -> 0 | BO38: =tFestivos46[[#This Row],[Columna1]]-tFestivos46[[#This Row],[Columna18]] -> 0
F39: =E39/30 -> 0 | G39: =IFERROR(VLOOKUP(C39,'DATOS GRALES 1'!B17:E63,4,0),"") | AO39: =COUNTIF(I39:AM39,"SI") -> 0 | AQ39: =IF(COUNTIF(I39:AM39,"NO")=0,"",COUNTIF(I39:AM39,"NO")) | AS39: =COUNTIF(I39:AM39,"MED") -> 0 | AU39: =IF(SUM(AO39:AS39)=0,"",SUM(AO39:AS39)) | AW39: =(F39/2*AS39)+(AO39*F39) -> 0 | AY39: =F39/8*tFestivos46[[#This Row],[Columna2]] -> 0 | BH39: =tFestivos46[[#This Row],[Columna5]]+tFestivos46[[#This Row],[Columna7]]+tFestivos46[[#This Row],[Columna9]]+tFestivos46[[#This Row],[Columna11]] -> 0 | BI39: =(E39*13%)/2 -> 0 | BJ39: =(E39*2%)/2 -> 0 | BK39: =(E39*13%)/2 -> 0 | BL39: =(E39*2%)/2 -> 0 | BM39: =tFestivos46[[#This Row],[Columna13]]+tFestivos46[[#This Row],[Columna14]]+tFestivos46[[#This Row],[Columna15]]+tFestivos46[[#This Row],[Columna16]] -> 0 | BN39: =tFestivos46[[#This Row],[Columna12]]+tFestivos46[[#This Row],[Columna17]] -> 0 | BO39: =tFestivos46[[#This Row],[Columna1]]-tFestivos46[[#This Row],[Columna18]] -> 0
F40: =E40/30 -> 0 | G40: =IFERROR(VLOOKUP(C40,'DATOS GRALES 1'!B18:E64,4,0),"") | AO40: =COUNTIF(I40:AM40,"SI") -> 0 | AQ40: =IF(COUNTIF(I40:AM40,"NO")=0,"",COUNTIF(I40:AM40,"NO")) | AS40: =COUNTIF(I40:AM40,"MED") -> 0 | AU40: =IF(SUM(AO40:AS40)=0,"",SUM(AO40:AS40)) | AW40: =(F40/2*AS40)+(AO40*F40) -> 0 | AY40: =F40/8*tFestivos46[[#This Row],[Columna2]] -> 0 | BH40: =tFestivos46[[#This Row],[Columna5]]+tFestivos46[[#This Row],[Columna7]]+tFestivos46[[#This Row],[Columna9]]+tFestivos46[[#This Row],[Columna11]] -> 0 | BI40: =(E40*13%)/2 -> 0 | BJ40: =(E40*2%)/2 -> 0 | BK40: =(E40*13%)/2 -> 0 | BL40: =(E40*2%)/2 -> 0 | BM40: =tFestivos46[[#This Row],[Columna13]]+tFestivos46[[#This Row],[Columna14]]+tFestivos46[[#This Row],[Columna15]]+tFestivos46[[#This Row],[Columna16]] -> 0 | BN40: =tFestivos46[[#This Row],[Columna12]]+tFestivos46[[#This Row],[Columna17]] -> 0 | BO40: =tFestivos46[[#This Row],[Columna1]]-tFestivos46[[#This Row],[Columna18]] -> 0
F41: =E41/30 -> 0 | G41: =IFERROR(VLOOKUP(C41,'DATOS GRALES 1'!B19:E65,4,0),"") | AO41: =COUNTIF(I41:AM41,"SI") -> 0 | AQ41: =IF(COUNTIF(I41:AM41,"NO")=0,"",COUNTIF(I41:AM41,"NO")) | AS41: =COUNTIF(I41:AM41,"MED") -> 0 | AU41: =IF(SUM(AO41:AS41)=0,"",SUM(AO41:AS41)) | AW41: =(F41/2*AS41)+(AO41*F41) -> 0 | AY41: =F41/8*tFestivos46[[#This Row],[Columna2]] -> 0 | BH41: =tFestivos46[[#This Row],[Columna5]]+tFestivos46[[#This Row],[Columna7]]+tFestivos46[[#This Row],[Columna9]]+tFestivos46[[#This Row],[Columna11]] -> 0 | BI41: =(E41*13%)/2 -> 0 | BJ41: =(E41*2%)/2 -> 0 | BK41: =(E41*13%)/2 -> 0 | BL41: =(E41*2%)/2 -> 0 | BM41: =tFestivos46[[#This Row],[Columna13]]+tFestivos46[[#This Row],[Columna14]]+tFestivos46[[#This Row],[Columna15]]+tFestivos46[[#This Row],[Columna16]] -> 0 | BN41: =tFestivos46[[#This Row],[Columna12]]+tFestivos46[[#This Row],[Columna17]] -> 0 | BO41: =tFestivos46[[#This Row],[Columna1]]-tFestivos46[[#This Row],[Columna18]] -> 0
F42: =E42/30 -> 0 | G42: =IFERROR(VLOOKUP(C42,'DATOS GRALES 1'!B20:E66,4,0),"") | AO42: =COUNTIF(I42:AM42,"SI") -> 0 | AQ42: =IF(COUNTIF(I42:AM42,"NO")=0,"",COUNTIF(I42:AM42,"NO")) | AS42: =COUNTIF(I42:AM42,"MED") -> 0 | AU42: =IF(SUM(AO42:AS42)=0,"",SUM(AO42:AS42)) | AW42: =(F42/2*AS42)+(AO42*F42) -> 0 | AY42: =F42/8*tFestivos46[[#This Row],[Columna2]] -> 0 | BH42: =tFestivos46[[#This Row],[Columna5]]+tFestivos46[[#This Row],[Columna7]]+tFestivos46[[#This Row],[Columna9]]+tFestivos46[[#This Row],[Columna11]] -> 0 | BI42: =(E42*13%)/2 -> 0 | BJ42: =(E42*2%)/2 -> 0 | BK42: =(E42*13%)/2 -> 0 | BL42: =(E42*2%)/2 -> 0 | BM42: =tFestivos46[[#This Row],[Columna13]]+tFestivos46[[#This Row],[Columna14]]+tFestivos46[[#This Row],[Columna15]]+tFestivos46[[#This Row],[Columna16]] -> 0 | BN42: =tFestivos46[[#This Row],[Columna12]]+tFestivos46[[#This Row],[Columna17]] -> 0 | BO42: =tFestivos46[[#This Row],[Columna1]]-tFestivos46[[#This Row],[Columna18]] -> 0
F43: =E43/30 -> 0 | G43: =IFERROR(VLOOKUP(C43,'DATOS GRALES 1'!B21:E67,4,0),"") | AO43: =COUNTIF(I43:AM43,"SI") -> 0 | AQ43: =IF(COUNTIF(I43:AM43,"NO")=0,"",COUNTIF(I43:AM43,"NO")) | AS43: =COUNTIF(I43:AM43,"MED") -> 0 | AU43: =IF(SUM(AO43:AS43)=0,"",SUM(AO43:AS43)) | AW43: =(F43/2*AS43)+(AO43*F43) -> 0 | AY43: =F43/8*tFestivos46[[#This Row],[Columna2]] -> 0 | BH43: =tFestivos46[[#This Row],[Columna5]]+tFestivos46[[#This Row],[Columna7]]+tFestivos46[[#This Row],[Columna9]]+tFestivos46[[#This Row],[Columna11]] -> 0 | BI43: =(E43*13%)/2 -> 0 | BJ43: =(E43*2%)/2 -> 0 | BK43: =(E43*13%)/2 -> 0 | BL43: =(E43*2%)/2 -> 0 | BM43: =tFestivos46[[#This Row],[Columna13]]+tFestivos46[[#This Row],[Columna14]]+tFestivos46[[#This Row],[Columna15]]+tFestivos46[[#This Row],[Columna16]] -> 0 | BN43: =tFestivos46[[#This Row],[Columna12]]+tFestivos46[[#This Row],[Columna17]] -> 0 | BO43: =tFestivos46[[#This Row],[Columna1]]-tFestivos46[[#This Row],[Columna18]] -> 0
F44: =E44/30 -> 0 | G44: =IFERROR(VLOOKUP(C44,'DATOS GRALES 1'!B22:E68,4,0),"") | AO44: =COUNTIF(I44:AM44,"SI") -> 0 | AQ44: =IF(COUNTIF(I44:AM44,"NO")=0,"",COUNTIF(I44:AM44,"NO")) | AS44: =COUNTIF(I44:AM44,"MED") -> 0 | AU44: =IF(SUM(AO44:AS44)=0,"",SUM(AO44:AS44)) | AW44: =(F44/2*AS44)+(AO44*F44) -> 0 | AY44: =F44/8*tFestivos46[[#This Row],[Columna2]] -> 0 | BH44: =tFestivos46[[#This Row],[Columna5]]+tFestivos46[[#This Row],[Columna7]]+tFestivos46[[#This Row],[Columna9]]+tFestivos46[[#This Row],[Columna11]] -> 0 | BI44: =(E44*13%)/2 -> 0 | BJ44: =(E44*2%)/2 -> 0 | BK44: =(E44*13%)/2 -> 0 | BL44: =(E44*2%)/2 -> 0 | BM44: =tFestivos46[[#This Row],[Columna13]]+tFestivos46[[#This Row],[Columna14]]+tFestivos46[[#This Row],[Columna15]]+tFestivos46[[#This Row],[Columna16]] -> 0 | BN44: =tFestivos46[[#This Row],[Columna12]]+tFestivos46[[#This Row],[Columna17]] -> 0 | BO44: =tFestivos46[[#This Row],[Columna1]]-tFestivos46[[#This Row],[Columna18]] -> 0
F45: =E45/30 -> 0 | G45: =IFERROR(VLOOKUP(C45,'DATOS GRALES 1'!B23:E69,4,0),"") | AO45: =COUNTIF(I45:AM45,"SI") -> 0 | AQ45: =IF(COUNTIF(I45:AM45,"NO")=0,"",COUNTIF(I45:AM45,"NO")) | AS45: =COUNTIF(I45:AM45,"MED") -> 0 | AU45: =IF(SUM(AO45:AS45)=0,"",SUM(AO45:AS45)) | AW45: =(F45/2*AS45)+(AO45*F45) -> 0 | AY45: =F45/8*tFestivos46[[#This Row],[Columna2]] -> 0 | BH45: =tFestivos46[[#This Row],[Columna5]]+tFestivos46[[#This Row],[Columna7]]+tFestivos46[[#This Row],[Columna9]]+tFestivos46[[#This Row],[Columna11]] -> 0 | BI45: =(E45*13%)/2 -> 0 | BJ45: =(E45*2%)/2 -> 0 | BK45: =(E45*13%)/2 -> 0 | BL45: =(E45*2%)/2 -> 0 | BM45: =tFestivos46[[#This Row],[Columna13]]+tFestivos46[[#This Row],[Columna14]]+tFestivos46[[#This Row],[Columna15]]+tFestivos46[[#This Row],[Columna16]] -> 0 | BN45: =tFestivos46[[#This Row],[Columna12]]+tFestivos46[[#This Row],[Columna17]] -> 0 | BO45: =tFestivos46[[#This Row],[Columna1]]-tFestivos46[[#This Row],[Columna18]] -> 0
... F51: =E51/30 -> 0 | G51: =IFERROR(VLOOKUP(C51,'DATOS GRALES 1'!B29:E75,4,0),"") | AO51: =COUNTIF(I51:AM51,"SI") -> 0 | AQ51: =IF(COUNTIF(I51:AM51,"NO")=0,"",COUNTIF(I51:AM51,"NO")) | AS51: =COUNTIF(I51:AM51,"MED") -> 0 | AU51: =IF(SUM(AO51:AS51)=0,"",SUM(AO51:AS51)) | AW51: =(F51/2*AS51)+(AO51*F51) -> 0 | AY51: =F51/8*tFestivos46[[#This Row],[Columna2]] -> 0 | BH51: =tFestivos46[[#This Row],[Columna5]]+tFestivos46[[#This Row],[Columna7]]+tFestivos46[[#This Row],[Columna9]]+tFestivos46[[#This Row],[Columna11]] -> 0 | BI51: =(E51*13%)/2 -> 0 | BJ51: =(E51*2%)/2 -> 0 | BK51: =(E51*13%)/2 -> 0 | BL51: =(E51*2%)/2 -> 0 | BM51: =tFestivos46[[#This Row],[Columna13]]+tFestivos46[[#This Row],[Columna14]]+tFestivos46[[#This Row],[Columna15]]+tFestivos46[[#This Row],[Columna16]] -> 0 | BN51: =tFestivos46[[#This Row],[Columna12]]+tFestivos46[[#This Row],[Columna17]] -> 0 | BO51: =tFestivos46[[#This Row],[Columna1]]-tFestivos46[[#This Row],[Columna18]] -> 0
AW52: =SUBTOTAL(109,tFestivos46[Columna1]) -> 42180 | AY52: =SUBTOTAL(109,tFestivos46[Columna3]) -> 206.25 | BA52: =SUBTOTAL(109,tFestivos46[Columna5]) -> 520 | BC52: =SUBTOTAL(109,tFestivos46[Columna7]) -> 350 | BE52: =SUBTOTAL(109,tFestivos46[Columna9]) -> 250 | BG52: =SUBTOTAL(109,tFestivos46[Columna11]) -> 150 | BH52: =SUBTOTAL(109,tFestivos46[Columna12]) -> 1270 | BI52: =SUBTOTAL(109,tFestivos46[Columna13]) -> 4602 | BJ52: =SUBTOTAL(109,tFestivos46[Columna14]) -> 708 | BK52: =SUBTOTAL(109,tFestivos46[Columna15]) -> 4602 | BL52: =SUBTOTAL(109,tFestivos46[Columna16]) -> 708 | BM52: =SUBTOTAL(109,tFestivos46[Columna17]) -> 10620 | BN52: =SUBTOTAL(109,tFestivos46[Columna18]) -> 11890 | BO52: =SUBTOTAL(109,tFestivos46[Columna19]) -> 30290

Sheet SET - OCT
B2: SETIEMBRE | D2: OCTUBRE
B4: 2025
H9: =DATE(B4,MONTH(B2&1),8) -> 45908 | I9: =H9+1 -> 45909 | J9: =I9+1 -> 45910 | K9: =J9+1 -> 45911 | L9: =K9+1 -> 45912 | M9: =L9+1 -> 45913 | N9: =M9+1 -> 45914 | O9: =N9+1 -> 45915 | P9: =O9+1 -> 45916 | ... AX9: =AW9+1 -> 45950 | BI9: ADELANTOS A LOS TRABAJADORES | BS9: DESCUENTOS | CF9: AFP | CG9: 0.13
B11: APELLIDOS Y NOMBRES | D11: CARGO | E11: SUELDO MENSUAL | F11: SUELDO X DIA | H11: =PROPER(LEFT(TEXT(H9,"dddd"),3)) -> Lun | I11: =PROPER(LEFT(TEXT(I9,"dddd"),3)) -> Mar | J11: =PROPER(LEFT(TEXT(J9,"dddd"),3)) -> Mié | K11: =PROPER(LEFT(TEXT(K9,"dddd"),3)) -> Jue | L11: =PROPER(LEFT(TEXT(L9,"dddd"),3)) -> Vie | M11: =PROPER(LEFT(TEXT(M9,"dddd"),3)) -> Sáb | N11: =PROPER(LEFT(TEXT(N9,"dddd"),3)) -> Dom | O11: =PROPER(LEFT(TEXT(O9,"dddd"),3)) -> Lun | ... AX11: =PROPER(LEFT(TEXT(AX9,"dddd"),3)) -> Lun | AZ11: ASISTIO | BA11: FALTO | BB11: MEDIO DIA (MED) | BC11: TOTAL | BE11: SUELDO | BF11: HORAS EXTRAS | BG11: HORAS EXTRAS A PAGAR | BI11: FECHA | BJ11: ADELANTO 1 | BK11: FECHA | BL11: ADELANTO 2 | BM11: FECHA | BN11: ADELANTO 3 | BO11: FECHA | BP11: ADELANTO 4 | BQ11: TOTAL ADELANTOS | BS11: AFP SETIEMBRE MITAD FINAL | BT11: CONAFOVICER AGOSTO MITAD | BU11: AFP OCTUBRE 1ERA MITAD | BV11: CONAFOVICER SETIEMBRE MITAD | BW11: TOTAL DESCUENTOS | BY11: SUMA TOTAL ADELANTOS Y DSCTOS | CA11: SUELDO NETO A DEPOSITAR | CF11: ONP | CG11: 0.09
B12: SALAZAR BAZAN, ROCÍO DALILA | D12: =IFERROR(VLOOKUP(B12,'DATOS GRALES 1'!$B$2:$E$91,4,0),"") -> RESIDENTE | F12: =E12/30 -> 0 | H12: SI | I12: SI | J12: SI | K12: SI | L12: SI | M12: SI | N12: SI | O12: SI | P12: SI | Q12: SI | R12: SI | S12: SI | T12: SI | U12: SI | V12: NO | W12: SI | X12: SI | Y12: SI | Z12: SI | AA12: SI | AB12: SI | AC12: SI | AD12: SI | AE12: SI | AF12: SI | AG12: SI | AH12: SI | AI12: SI | AJ12: SI | AK12: SI | AL12: SI | AM12: SI | AN12: SI | AO12: SI | AP12: SI | AQ12: SI | AR12: SI | AS12: SI | AT12: SI | AU12: NO | AV12: NO | AW12: NO | AX12: NO | AZ12: =IF(COUNTIF(H12:AX12,"SI")=0,"",COUNTIF(H12:AX12,"SI")) -> 38 | BA12: =IF(COUNTIF(H12:AX12,"NO")=0,"",COUNTIF(H12:AX12,"NO")) -> 5 | BB12: =COUNTIF(H12:AL12,"MED") -> 0 | BC12: =IF(SUM(AZ12:BB12)=0,"",SUM(AZ12:BB12)) -> 43 | BE12: =(F12/2*BB12)+(AZ12*F12) -> 0 | BG12: =F12/8*BF12 -> 0 | BQ12: =BJ12+BL12+BN12+BP12 -> 0 | BS12: =E12*13%/2 -> 0 | BT12: =E12*2%/2 -> 0 | BU12: =E12*13%/2 -> 0 | BV12: =E12*2%/2 -> 0 | BW12: =SUM(BS12:BV12) -> 0 | BY12: =BQ12+BW12 -> 0 | CA12: =BE12-BY12 -> 0 | CB12: AFP | CD12: =IF(CB12=$CF$9,(E12*$CG$9/2),(E12*$CG$11/2)) -> 0
B13: ALEJO CHARCA, DENNYS MIRIAM | D13: =IFERROR(VLOOKUP(B13,'DATOS GRALES 1'!$B$2:$E$91,4,0),"") -> ING. CALIDAD | F13: =E13/30 -> 0 | I13: SI | J13: SI | K13: SI | L13: SI | M13: SI | N13: SI | O13: SI | P13: SI | Q13: SI | R13: SI | S13: SI | T13: SI | U13: SI | V13: SI | W13: SI | X13: SI | Y13: SI | Z13: SI | AA13: SI | AB13: SI | AC13: SI | AD13: SI | AE13: SI | AF13: SI | AG13: SI | AH13: SI | AI13: SI | AJ13: SI | AK13: SI | AL13: SI | AM13: SI | AN13: NO | AO13: SI | AP13: SI | AQ13: SI | AR13: SI | AS13: SI | AT13: SI | AU13: SI | AV13: SI | AW13: SI | AX13: SI | AZ13: =IF(COUNTIF(H13:AX13,"SI")=0,"",COUNTIF(H13:AX13,"SI")) -> 41 | BA13: =IF(COUNTIF(H13:AX13,"NO")=0,"",COUNTIF(H13:AX13,"NO")) -> 1 | BB13: =COUNTIF(H13:AL13,"MED") -> 0 | BC13: =IF(SUM(AZ13:BB13)=0,"",SUM(AZ13:BB13)) -> 42 | BE13: =(F13/2*BB13)+(AZ13*F13) -> 0 | BG13: =F13/8*BF13 -> 0 | BQ13: =BJ13+BL13+BN13+BP13 -> 0 | BS13: =E13*13%/2 -> 0 | BT13: =E13*2%/2 -> 0 | BU13: =E13*13%/2 -> 0 | BV13: =E13*2%/2 -> 0 | BW13: =SUM(BS13:BV13) -> 0 | BY13: =BQ13+BW13 -> 0 | CA13: =BE13-BY13 -> 0 | CB13: AFP | CD13: =IF(CB13=$CF$9,(E13*$CG$9/2),(E13*$CG$11/2)) -> 0
B14: MOGROVEJO FALCON, OSMAR ADOLFO | D14: =IFERROR(VLOOKUP(B14,'DATOS GRALES 1'!$B$2:$E$91,4,0),"") -> ESP. SEGURIDAD | F14: =E14/30 -> 0 | AC14: SI | AD14: SI | AE14: SI | AF14: SI | AG14: SI | AH14: SI | AI14: SI | AJ14: SI | AK14: SI | AL14: SI | AM14: SI | AN14: SI | AO14: SI | AP14: SI | AQ14: SI | AR14: SI | AS14: SI | AT14: SI | AU14: SI | AV14: SI | AW14: SI | AX14: SI | AZ14: =IF(COUNTIF(H14:AX14,"SI")=0,"",COUNTIF(H14:AX14,"SI")) -> 22 | BA14: =IF(COUNTIF(H14:AX14,"NO")=0,"",COUNTIF(H14:AX14,"NO")) | BB14: =COUNTIF(H14:AL14,"MED") -> 0 | BC14: =IF(SUM(AZ14:BB14)=0,"",SUM(AZ14:BB14)) -> 22 | BE14: =(F14/2*BB14)+(AZ14*F14) -> 0 | BG14: =F14/8*BF14 -> 0 | BQ14: =BJ14+BL14+BN14+BP14 -> 0 | BS14: =E14*13%/2 -> 0 | BT14: =E14*2%/2 -> 0 | BU14: =E14*13%/2 -> 0 | BV14: =E14*2%/2 -> 0 | BW14: =SUM(BS14:BV14) -> 0 | BY14: =BQ14+BW14 -> 0 | CA14: =BE14-BY14 -> 0 | CB14: ONP | CD14: =IF(CB14=$CF$9,(E14*$CG$9/2),(E14*$CG$11/2)) -> 0
B15: SILVA BORDA, ARLETTE NINOSKA | D15: =IFERROR(VLOOKUP(B15,'DATOS GRALES 1'!$B$2:$E$91,4,0),"") -> ASIS. ING. | F15: =E15/30 -> 0 | J15: SI | K15: SI | L15: SI | M15: SI | N15: SI | O15: SI | P15: SI | Q15: SI | R15: SI | S15: SI | T15: SI | U15: SI | V15: SI | W15: SI | X15: SI | Y15: SI | Z15: SI | AA15: SI | AB15: SI | AC15: SI | AD15: SI | AE15: SI | AF15: SI | AG15: SI | AH15: SI | AI15: SI | AJ15: SI | AK15: SI | AL15: SI | AM15: SI | AN15: SI | AO15: SI | AP15: SI | AQ15: SI | AR15: SI | AS15: SI | AT15: SI | AU15: SI | AV15: SI | AW15: SI | AX15: SI | AZ15: =IF(COUNTIF(H15:AX15,"SI")=0,"",COUNTIF(H15:AX15,"SI")) -> 41 | BA15: =IF(COUNTIF(H15:AX15,"NO")=0,"",COUNTIF(H15:AX15,"NO")) | BB15: =COUNTIF(H15:AL15,"MED") -> 0 | BC15: =IF(SUM(AZ15:BB15)=0,"",SUM(AZ15:BB15)) -> 41 | BE15: =(F15/2*BB15)+(AZ15*F15) -> 0 | BG15: =F15/8*BF15 -> 0 | BQ15: =BJ15+BL15+BN15+BP15 -> 0 | BS15: =E15*13%/2 -> 0 | BT15: =E15*2%/2 -> 0 | BU15: =E15*13%/2 -> 0 | BV15: =E15*2%/2 -> 0 | BW15: =SUM(BS15:BV15) -> 0 | BY15: =BQ15+BW15 -> 0 | CA15: =BE15-BY15 -> 0 | CB15: ONP | CD15: =IF(CB15=$CF$9,(E15*$CG$9/2),(E15*$CG$11/2)) -> 0
B16: LOZA YAPUCHURA, KENNY GUILLERMO | D16: =IFERROR(VLOOKUP(B16,'DATOS GRALES 1'!$B$2:$E$91,4,0),"") -> TOPOGRAFO | F16: =E16/30 -> 0 | V16: SI | W16: SI | X16: SI | Y16: SI | Z16: SI | AA16: SI | AB16: SI | AC16: SI | AD16: SI | AE16: SI | AF16: SI | AG16: SI | AH16: SI | AI16: SI | AJ16: SI | AK16: SI | AL16: SI | AM16: MED | AN16: SI | AO16: SI | AP16: SI | AQ16: SI | AR16: SI | AS16: SI | AT16: SI | AU16: SI | AV16: SI | AW16: SI | AX16: SI | AZ16: =IF(COUNTIF(H16:AX16,"SI")=0,"",COUNTIF(H16:AX16,"SI")) -> 28 | BA16: =IF(COUNTIF(H16:AX16,"NO")=0,"",COUNTIF(H16:AX16,"NO")) | BB16: =COUNTIF(H16:AL16,"MED") -> 0 | BC16: =IF(SUM(AZ16:BB16)=0,"",SUM(AZ16:BB16)) -> 28 | BE16: =(F16/2*BB16)+(AZ16*F16) -> 0 | BG16: =F16/8*BF16 -> 0 | BQ16: =BJ16+BL16+BN16+BP16 -> 0 | BS16: =E16*13%/2 -> 0 | BT16: =E16*2%/2 -> 0 | BU16: =E16*13%/2 -> 0 | BV16: =E16*2%/2 -> 0 | BW16: =SUM(BS16:BV16) -> 0 | BY16: =BQ16+BW16 -> 0 | CA16: =BE16-BY16 -> 0 | CB16: AFP | CD16: =IF(CB16=$CF$9,(E16*$CG$9/2),(E16*$CG$11/2)) -> 0
B17: ADUVIRE ARGUATA, MARIO ARTURO | D17: =IFERROR(VLOOKUP(B17,'DATOS GRALES 1'!$B$2:$E$91,4,0),"") -> MAESTRO OBRA | F17: =E17/30 -> 0 | H17: SI | I17: SI | J17: SI | K17: SI | L17: SI | M17: SI | N17: SI | O17: SI | P17: SI | Q17: SI | R17: SI | S17: SI | T17: SI | U17: SI | V17: SI | W17: SI | X17: SI | Y17: SI | Z17: SI | AA17: SI | AB17: SI | AC17: SI | AD17: SI | AE17: SI | AF17: SI | AG17: SI | AH17: SI | AI17: SI | AJ17: SI | AK17: SI | AL17: SI | AM17: SI | AN17: SI | AO17: SI | AP17: SI | AQ17: SI | AR17: SI | AS17: SI | AT17: SI | AU17: SI | AV17: SI | AW17: SI | AX17: SI | AZ17: =IF(COUNTIF(H17:AX17,"SI")=0,"",COUNTIF(H17:AX17,"SI")) -> 43 | BA17: =IF(COUNTIF(H17:AX17,"NO")=0,"",COUNTIF(H17:AX17,"NO")) | BB17: =COUNTIF(H17:AL17,"MED") -> 0 | BC17: =IF(SUM(AZ17:BB17)=0,"",SUM(AZ17:BB17)) -> 43 | BE17: =(F17/2*BB17)+(AZ17*F17) -> 0 | BG17: =F17/8*BF17 -> 0 | BQ17: =BJ17+BL17+BN17+BP17 -> 0 | BS17: =E17*13%/2 -> 0 | BT17: =E17*2%/2 -> 0 | BU17: =E17*13%/2 -> 0 | BV17: =E17*2%/2 -> 0 | BW17: =SUM(BS17:BV17) -> 0 | BY17: =BQ17+BW17 -> 0 | CA17: =BE17-BY17 -> 0 | CB17: ONP | CD17: =IF(CB17=$CF$9,(E17*$CG$9/2),(E17*$CG$11/2)) -> 0
B18: ACUACHI LANCHIPA, ERNESTO ALONSO | D18: =IFERROR(VLOOKUP(B18,'DATOS GRALES 1'!$B$2:$E$91,4,0),"") -> LOGISTICO | E18: 3000 | F18: =E18/30 -> 100 | H18: SI | I18: SI | J18: SI | K18: SI | L18: SI | M18: SI | N18: SI | O18: SI | P18: SI | Q18: SI | R18: SI | S18: SI | T18: SI | U18: SI | V18: SI | W18: SI | X18: SI | Y18: SI | Z18: SI | AA18: SI | AB18: SI | AC18: SI | AD18: SI | AE18: MED | AF18: SI | AG18: SI | AH18: SI | AI18: SI | AJ18: SI | AK18: SI | AL18: SI | AM18: SI | AN18: SI | AO18: SI | AP18: SI | AQ18: SI | AR18: SI | AS18: SI | AT18: SI | AU18: SI | AV18: SI | AW18: SI | AX18: SI | AZ18: =IF(COUNTIF(H18:AX18,"SI")=0,"",COUNTIF(H18:AX18,"SI")) -> 42 | BA18: =IF(COUNTIF(H18:AX18,"NO")=0,"",COUNTIF(H18:AX18,"NO")) | BB18: =COUNTIF(H18:AL18,"MED") -> 1 | BC18: =IF(SUM(AZ18:BB18)=0,"",SUM(AZ18:BB18)) -> 43 | BE18: =(F18/2*BB18)+(AZ18*F18) -> 4250 | BG18: =F18/8*BF18 -> 0 | BI18: 45935 | BJ18: 1000 | BQ18: =BJ18+BL18+BN18+BP18 -> 1000 | BS18: =E18*13%/2 -> 195 | BT18: =E18*2%/2 -> 30 | BU18: =E18*13%/2 -> 195 | BV18: =E18*2%/2 -> 30 | BW18: =SUM(BS18:BV18) -> 450 | BY18: =BQ18+BW18 -> 1450 | CA18: =BE18-BY18 -> 2800 | CB18: ONP | CD18: =IF(CB18=$CF$9,(E18*$CG$9/2),(E18*$CG$11/2)) -> 135
AZ19: =IF(COUNTIF(H19:AX19,"SI")=0,"",COUNTIF(H19:AX19,"SI")) | BA19: =IF(COUNTIF(H19:AX19,"NO")=0,"",COUNTIF(H19:AX19,"NO")) | BC19: =IF(SUM(AZ19:BB19)=0,"",SUM(AZ19:BB19))
B20: OBREROS | AZ20: =IF(COUNTIF(H20:AX20,"SI")=0,"",COUNTIF(H20:AX20,"SI")) | BA20: =IF(COUNTIF(H20:AX20,"NO")=0,"",COUNTIF(H20:AX20,"NO")) | BC20: =IF(SUM(AZ20:BB20)=0,"",SUM(AZ20:BB20))
B21: NAVARRO LOZANO, ANGEL JAROL | D21: =IFERROR(VLOOKUP(B21,'DATOS GRALES 1'!$B$2:$E$91,4,0),"") -> PEON | E21: =IF(D21="","",IF(D21="PEON","3300","4200")) -> 3300 | F21: =IFERROR((E21/30),"") -> 110 | U21: SI | V21: SI | W21: SI | X21: SI | Y21: SI | Z21: SI | AA21: SI | AB21: SI | AC21: SI | AD21: SI | AE21: SI | AF21: SI | AG21: SI | AH21: SI | AI21: SI | AJ21: SI | AK21: SI | AL21: SI | AM21: SI | AN21: SI | AO21: SI | AP21: SI | AQ21: SI | AR21: SI | AS21: SI | AT21: SI | AU21: SI | AV21: SI | AW21: SI | AX21: SI | AZ21: =IF(COUNTIF(H21:AX21,"SI")=0,"",COUNTIF(H21:AX21,"SI")) -> 30 | BA21: =IF(COUNTIF(H21:AX21,"NO")=0,"",COUNTIF(H21:AX21,"NO")) | BB21: =COUNTIF(H21:AL21,"MED") -> 0 | BC21: =IF(SUM(AZ21:BB21)=0,"",SUM(AZ21:BB21)) -> 30 | BE21: =IFERROR((F21/2*BB21)+(AZ21*F21),"") -> 3300 | BG21: =IFERROR((F21/8*BF21),"") -> 0 | BQ21: =BJ21+BL21+BN21+BP21 -> 0 | BS21: =IFERROR((E21*13%/2),"") -> 214.5 | BT21: =IFERROR((E21*2%/2),"") -> 33 | BU21: =IFERROR((E21*13%/2),"") -> 214.5 | BV21: =IFERROR((E21*2%/2),"") -> 33 | BW21: =SUM(BS21:BV21) -> 495 | BY21: =BQ21+BW21 -> 495 | CA21: =IFERROR((BE21-BW21),"") -> 2805 | CB21: AFP | CD21: =IF(CB21=$CF$9,(E21*$CG$9/2),(E21*$CG$11/2)) -> 214.5
B22: JEREMIAS PALOMINO, NORBERTO LEONCIO | D22: =IFERROR(VLOOKUP(B22,'DATOS GRALES 1'!$B$2:$E$91,4,0),"") -> PEON | E22: =IF(D22="","",IF(D22="PEON","3300","4200")) -> 3300 | F22: =IFERROR((E22/30),"") -> 110 | U22: SI | V22: SI | W22: SI | X22: SI | Y22: SI | Z22: SI | AA22: SI | AB22: SI | AC22: SI | AD22: SI | AE22: SI | AF22: SI | AG22: SI | AH22: SI | AI22: SI | AJ22: SI | AK22: SI | AL22: SI | AM22: SI | AN22: SI | AO22: SI | AP22: SI | AQ22: SI | AR22: SI | AS22: SI | AT22: SI | AU22: SI | AV22: SI | AW22: SI | AX22: SI | AZ22: =IF(COUNTIF(H22:AX22,"SI")=0,"",COUNTIF(H22:AX22,"SI")) -> 30 | BA22: =IF(COUNTIF(H22:AX22,"NO")=0,"",COUNTIF(H22:AX22,"NO")) | BB22: =COUNTIF(H22:AL22,"MED") -> 0 | BC22: =IF(SUM(AZ22:BB22)=0,"",SUM(AZ22:BB22)) -> 30 | BE22: =IFERROR((F22/2*BB22)+(AZ22*F22),"") -> 3300 | BG22: =IFERROR((F22/8*BF22),"") -> 0 | BQ22: =BJ22+BL22+BN22+BP22 -> 0 | BS22: =IFERROR((E22*13%/2),"") -> 214.5 | BT22: =IFERROR((E22*2%/2),"") -> 33 | BU22: =IFERROR((E22*13%/2),"") -> 214.5 | BV22: =IFERROR((E22*2%/2),"") -> 33 | BW22: =SUM(BS22:BV22) -> 495 | BY22: =BQ22+BW22 -> 495 | CA22: =IFERROR((BE22-BW22),"") -> 2805 | CB22: AFP | CD22: =IF(CB22=$CF$9,(E22*$CG$9/2),(E22*$CG$11/2)) -> 214.5
B23: LOZANO MALDONADO, HERNAN | D23: =IFERROR(VLOOKUP(B23,'DATOS GRALES 1'!$B$2:$E$91,4,0),"") -> PEON | E23: =IF(D23="","",IF(D23="PEON","3300","4200")) -> 3300 | F23: =IFERROR((E23/30),"") -> 110 | U23: SI | V23: SI | W23: SI | X23: SI | Y23: SI | Z23: SI | AA23: SI | AB23: SI | AC23: SI | AD23: SI | AE23: SI | AF23: SI | AG23: SI | AH23: SI | AI23: SI | AJ23: SI | AK23: SI | AL23: SI | AM23: SI | AN23: SI | AO23: SI | AP23: SI | AQ23: SI | AR23: SI | AS23: SI | AT23: SI | AU23: SI | AV23: SI | AW23: SI | AX23: SI | AZ23: =IF(COUNTIF(H23:AX23,"SI")=0,"",COUNTIF(H23:AX23,"SI")) -> 30 | BA23: =IF(COUNTIF(H23:AX23,"NO")=0,"",COUNTIF(H23:AX23,"NO")) | BB23: =COUNTIF(H23:AL23,"MED") -> 0 | BC23: =IF(SUM(AZ23:BB23)=0,"",SUM(AZ23:BB23)) -> 30 | BE23: =IFERROR((F23/2*BB23)+(AZ23*F23),"") -> 3300 | BG23: =IFERROR((F23/8*BF23),"") -> 0 | BQ23: =BJ23+BL23+BN23+BP23 -> 0 | BS23: =IFERROR((E23*13%/2),"") -> 214.5 | BT23: =IFERROR((E23*2%/2),"") -> 33 | BU23: =IFERROR((E23*13%/2),"") -> 214.5 | BV23: =IFERROR((E23*2%/2),"") -> 33 | BW23: =SUM(BS23:BV23) -> 495 | BY23: =BQ23+BW23 -> 495 | CA23: =IFERROR((BE23-BW23),"") -> 2805 | CB23: ONP | CD23: =IF(CB23=$CF$9,(E23*$CG$9/2),(E23*$CG$11/2)) -> 148.5
B24: PIÑA CHUJANDAMA, KEVIN | D24: =IFERROR(VLOOKUP(B24,'DATOS GRALES 1'!$B$2:$E$91,4,0),"") -> PEON | E24: =IF(D24="","",IF(D24="PEON","3300","4200")) -> 3300 | F24: =IFERROR((E24/30),"") -> 110 | V24: SI | W24: SI | X24: SI | Y24: SI | Z24: SI | AA24: SI | AB24: SI | AC24: SI | AD24: SI | AE24: SI | AF24: SI | AG24: SI | AH24: SI | AI24: SI | AJ24: SI | AK24: SI | AL24: SI | AM24: SI | AN24: SI | AO24: SI | AP24: SI | AQ24: SI | AR24: SI | AS24: SI | AT24: SI | AU24: SI | AV24: SI | AW24: SI | AX24: SI | AZ24: =IF(COUNTIF(H24:AX24,"SI")=0,"",COUNTIF(H24:AX24,"SI")) -> 29 | BA24: =IF(COUNTIF(H24:AX24,"NO")=0,"",COUNTIF(H24:AX24,"NO")) | BB24: =COUNTIF(H24:AL24,"MED") -> 0 | BC24: =IF(SUM(AZ24:BB24)=0,"",SUM(AZ24:BB24)) -> 29 | BE24: =IFERROR((F24/2*BB24)+(AZ24*F24),"") -> 3190 | BG24: =IFERROR((F24/8*BF24),"") -> 0 | BQ24: =BJ24+BL24+BN24+BP24 -> 0 | BS24: =IFERROR((E24*13%/2),"") -> 214.5 | BT24: =IFERROR((E24*2%/2),"") -> 33 | BU24: =IFERROR((E24*13%/2),"") -> 214.5 | BV24: =IFERROR((E24*2%/2),"") -> 33 | BW24: =SUM(BS24:BV24) -> 495 | BY24: =BQ24+BW24 -> 495 | CA24: =IFERROR((BE24-BW24),"") -> 2695
B25: MAYTAHUARI ACOSTA, SAMMER AXEL | D25: =IFERROR(VLOOKUP(B25,'DATOS GRALES 1'!$B$2:$E$91,4,0),"") -> OPERARIO | E25: =IF(D25="","",IF(D25="PEON","3300","4200")) -> 4200 | F25: =IFERROR((E25/30),"") -> 140 | V25: SI | W25: SI | X25: SI | Y25: SI | Z25: SI | AA25: SI | AB25: SI | AC25: SI | AD25: SI | AE25: SI | AF25: SI | AG25: SI | AH25: SI | AI25: SI | AJ25: SI | AK25: SI | AL25: SI | AM25: SI | AN25: SI | AO25: SI | AP25: SI | AQ25: SI | AR25: SI | AS25: SI | AT25: SI | AU25: SI | AV25: SI | AW25: SI | AX25: SI | AZ25: =IF(COUNTIF(H25:AX25,"SI")=0,"",COUNTIF(H25:AX25,"SI")) -> 29 | BA25: =IF(COUNTIF(H25:AX25,"NO")=0,"",COUNTIF(H25:AX25,"NO")) | BB25: =COUNTIF(H25:AL25,"MED") -> 0 | BC25: =IF(SUM(AZ25:BB25)=0,"",SUM(AZ25:BB25)) -> 29 | BE25: =IFERROR((F25/2*BB25)+(AZ25*F25),"") -> 4060 | BG25: =IFERROR((F25/8*BF25),"") -> 0 | BQ25: =BJ25+BL25+BN25+BP25 -> 0 | BS25: =IFERROR((E25*13%/2),"") -> 273 | BT25: =IFERROR((E25*2%/2),"") -> 42 | BU25: =IFERROR((E25*13%/2),"") -> 273 | BV25: =IFERROR((E25*2%/2),"") -> 42 | BW25: =SUM(BS25:BV25) -> 630 | BY25: =BQ25+BW25 -> 630 | CA25: =IFERROR((BE25-BW25),"") -> 3430
B26: CORDOVA ANGULO, JUAN | D26: =IFERROR(VLOOKUP(B26,'DATOS GRALES 1'!$B$2:$E$91,4,0),"") -> PEON | E26: =IF(D26="","",IF(D26="PEON","3300","4200")) -> 3300 | F26: =IFERROR((E26/30),"") -> 110 | U26: SI | V26: SI | W26: SI | X26: SI | Y26: SI | Z26: SI | AA26: SI | AB26: SI | AC26: SI | AD26: SI | AE26: SI | AF26: SI | AG26: SI | AH26: SI | AI26: SI | AJ26: SI | AK26: SI | AL26: SI | AM26: SI | AN26: SI | AO26: SI | AP26: SI | AQ26: SI | AR26: SI | AS26: SI | AT26: SI | AU26: SI | AV26: SI | AW26: SI | AX26: SI | AZ26: =IF(COUNTIF(H26:AX26,"SI")=0,"",COUNTIF(H26:AX26,"SI")) -> 30 | BA26: =IF(COUNTIF(H26:AX26,"NO")=0,"",COUNTIF(H26:AX26,"NO")) | BB26: =COUNTIF(H26:AL26,"MED") -> 0 | BC26: =IF(SUM(AZ26:BB26)=0,"",SUM(AZ26:BB26)) -> 30 | BE26: =IFERROR((F26/2*BB26)+(AZ26*F26),"") -> 3300 | BG26: =IFERROR((F26/8*BF26),"") -> 0 | BQ26: =BJ26+BL26+BN26+BP26 -> 0 | BS26: =IFERROR((E26*13%/2),"") -> 214.5 | BT26: =IFERROR((E26*2%/2),"") -> 33 | BU26: =IFERROR((E26*13%/2),"") -> 214.5 | BV26: =IFERROR((E26*2%/2),"") -> 33 | BW26: =SUM(BS26:BV26) -> 495 | BY26: =BQ26+BW26 -> 495 | CA26: =IFERROR((BE26-BW26),"") -> 2805
B27: ROJAS SANDOVAL, JAVIER ELOY | D27: =IFERROR(VLOOKUP(B27,'DATOS GRALES 1'!$B$2:$E$91,4,0),"") -> OPERARIO/VOLQUETERO | E27: =IF(D27="","",IF(D27="PEON","3300","4200")) -> 4200 | F27: =IFERROR((E27/30),"") -> 140 | V27: SI | W27: SI | X27: SI | Y27: SI | Z27: SI | AA27: SI | AB27: SI | AC27: SI | AD27: SI | AE27: SI | AF27: SI | AG27: SI | AH27: SI | AI27: SI | AJ27: SI | AK27: SI | AL27: SI | AM27: SI | AN27: SI | AO27: SI | AP27: SI | AQ27: NO | AR27: SI | AS27: SI | AT27: SI | AU27: SI | AV27: SI | AW27: NO | AX27: SI | AZ27: =IF(COUNTIF(H27:AX27,"SI")=0,"",COUNTIF(H27:AX27,"SI")) -> 27 | BA27: =IF(COUNTIF(H27:AX27,"NO")=0,"",COUNTIF(H27:AX27,"NO")) -> 2 | BB27: =COUNTIF(H27:AL27,"MED") -> 0 | BC27: =IF(SUM(AZ27:BB27)=0,"",SUM(AZ27:BB27)) -> 29 | BE27: =IFERROR((F27/2*BB27)+(AZ27*F27),"") -> 3780 | BG27: =IFERROR((F27/8*BF27),"") -> 0 | BQ27: =BJ27+BL27+BN27+BP27 -> 0 | BS27: =IFERROR((E27*13%/2),"") -> 273 | BT27: =IFERROR((E27*2%/2),"") -> 42 | BU27: =IFERROR((E27*13%/2),"") -> 273 | BV27: =IFERROR((E27*2%/2),"") -> 42 | BW27: =SUM(BS27:BV27) -> 630 | BY27: =BQ27+BW27 -> 630 | CA27: =IFERROR((BE27-BW27),"") -> 3150
B28: CHACON ORTIZ, JOSE ANTONIO | D28: =IFERROR(VLOOKUP(B28,'DATOS GRALES 1'!$B$2:$E$91,4,0),"") -> OPERARIO | E28: =IF(D28="","",IF(D28="PEON","3300","4200")) -> 4200 | F28: =IFERROR((E28/30),"") -> 140 | N28: SI | O28: SI | P28: SI | Q28: SI | R28: SI | S28: SI | T28: SI | U28: SI | V28: SI | W28: SI | X28: SI | Y28: SI | Z28: SI | AA28: SI | AB28: SI | AC28: SI | AD28: SI | AE28: SI | AF28: SI | AG28: SI | AH28: SI | AI28: SI | AJ28: SI | AK28: SI | AL28: SI | AM28: SI | AN28: SI | AO28: SI | AP28: SI | AQ28: SI | AR28: SI | AS28: SI | AT28: SI | AU28: SI | AV28: SI | AW28: SI | AX28: SI | AZ28: =IF(COUNTIF(H28:AX28,"SI")=0,"",COUNTIF(H28:AX28,"SI")) -> 37 | BA28: =IF(COUNTIF(H28:AX28,"NO")=0,"",COUNTIF(H28:AX28,"NO")) | BB28: =COUNTIF(H28:AL28,"MED") -> 0 | BC28: =IF(SUM(AZ28:BB28)=0,"",SUM(AZ28:BB28)) -> 37 | BE28: =IFERROR((F28/2*BB28)+(AZ28*F28),"") -> 5180 | BG28: =IFERROR((F28/8*BF28),"") -> 0 | BQ28: =BJ28+BL28+BN28+BP28 -> 0 | BS28: =IFERROR((E28*13%/2),"") -> 273 | BT28: =IFERROR((E28*2%/2),"") -> 42 | BU28: =IFERROR((E28*13%/2),"") -> 273 | BV28: =IFERROR((E28*2%/2),"") -> 42 | BW28: =SUM(BS28:BV28) -> 630 | BY28: =BQ28+BW28 -> 630 | CA28: =IFERROR((BE28-BW28),"") -> 4550
B29: ORDOÑEZ CONDORI, GILBERTO | D29: =IFERROR(VLOOKUP(B29,'DATOS GRALES 1'!$B$2:$E$91,4,0),"") -> PEON | E29: =IF(D29="","",IF(D29="PEON","3300","4200")) -> 3300 | F29: =IFERROR((E29/30),"") -> 110 | N29: SI | O29: SI | P29: SI | Q29: SI | R29: SI | S29: SI | T29: SI | U29: SI | V29: SI | W29: SI | X29: SI | Y29: SI | Z29: SI | AA29: SI | AB29: SI | AC29: SI | AD29: SI | AE29: SI | AF29: SI | AG29: SI | AH29: SI | AI29: SI | AJ29: SI | AK29: SI | AL29: SI | AM29: SI | AN29: SI | AO29: SI | AP29: SI | AQ29: SI | AR29: SI | AS29: SI | AT29: SI | AU29: SI | AV29: SI | AW29: SI | AX29: SI | AZ29: =IF(COUNTIF(H29:AX29,"SI")=0,"",COUNTIF(H29:AX29,"SI")) -> 37 | BA29: =IF(COUNTIF(H29:AX29,"NO")=0,"",COUNTIF(H29:AX29,"NO")) | BB29: =COUNTIF(H29:AL29,"MED") -> 0 | BC29: =IF(SUM(AZ29:BB29)=0,"",SUM(AZ29:BB29)) -> 37 | BE29: =IFERROR((F29/2*BB29)+(AZ29*F29),"") -> 4070 | BG29: =IFERROR((F29/8*BF29),"") -> 0 | BQ29: =BJ29+BL29+BN29+BP29 -> 0 | BS29: =IFERROR((E29*13%/2),"") -> 214.5 | BT29: =IFERROR((E29*2%/2),"") -> 33 | BU29: =IFERROR((E29*13%/2),"") -> 214.5 | BV29: =IFERROR((E29*2%/2),"") -> 33 | BW29: =SUM(BS29:BV29) -> 495 | BY29: =BQ29+BW29 -> 495 | CA29: =IFERROR((BE29-BW29),"") -> 3575
B30: GUTARATE SABINO, ADRIEL ANTONY | D30: =IFERROR(VLOOKUP(B30,'DATOS GRALES 1'!$B$2:$E$91,4,0),"") -> OPERARIO | E30: =IF(D30="","",IF(D30="PEON","3300","4200")) -> 4200 | F30: =IFERROR((E30/30),"") -> 140 | V30: SI | W30: SI | X30: SI | Y30: SI | Z30: SI | AA30: SI | AB30: SI | AC30: SI | AD30: SI | AE30: SI | AF30: SI | AG30: SI | AH30: SI | AI30: SI | AJ30: SI | AK30: SI | AL30: SI | AM30: SI | AN30: SI | AO30: SI | AP30: SI | AQ30: SI | AR30: SI | AS30: SI | AT30: SI | AU30: SI | AV30: SI | AW30: SI | AX30: SI | AZ30: =IF(COUNTIF(H30:AX30,"SI")=0,"",COUNTIF(H30:AX30,"SI")) -> 29 | BA30: =IF(COUNTIF(H30:AX30,"NO")=0,"",COUNTIF(H30:AX30,"NO")) | BB30: =COUNTIF(H30:AL30,"MED") -> 0 | BC30: =IF(SUM(AZ30:BB30)=0,"",SUM(AZ30:BB30)) -> 29 | BE30: =IFERROR((F30/2*BB30)+(AZ30*F30),"") -> 4060 | BG30: =IFERROR((F30/8*BF30),"") -> 0 | BQ30: =BJ30+BL30+BN30+BP30 -> 0 | BS30: =IFERROR((E30*13%/2),"") -> 273 | BT30: =IFERROR((E30*2%/2),"") -> 42 | BU30: =IFERROR((E30*13%/2),"") -> 273 | BV30: =IFERROR((E30*2%/2),"") -> 42 | BW30: =SUM(BS30:BV30) -> 630 | BY30: =BQ30+BW30 -> 630 | CA30: =IFERROR((BE30-BW30),"") -> 3430
B31: QUISPE LIMACHE, ROGELIO | D31: =IFERROR(VLOOKUP(B31,'DATOS GRALES 1'!$B$2:$E$91,4,0),"") -> OPERARIO | E31: =IF(D31="","",IF(D31="PEON","3300","4200")) -> 4200 | F31: =IFERROR((E31/30),"") -> 140 | U31: SI | V31: SI | W31: SI | X31: SI | Y31: SI | Z31: SI | AA31: SI | AB31: SI | AC31: SI | AD31: SI | AE31: SI | AF31: SI | AG31: SI | AH31: SI | AI31: SI | AJ31: SI | AK31: SI | AL31: SI | AM31: SI | AN31: SI | AO31: SI | AP31: SI | AQ31: NO | AR31: NO | AS31: NO | AT31: NO | AU31: NO | AV31: NO | AW31: NO | AX31: SI | AZ31: =IF(COUNTIF(H31:AX31,"SI")=0,"",COUNTIF(H31:AX31,"SI")) -> 23 | BA31: =IF(COUNTIF(H31:AX31,"NO")=0,"",COUNTIF(H31:AX31,"NO")) -> 7 | BB31: =COUNTIF(H31:AL31,"MED") -> 0 | BC31: =IF(SUM(AZ31:BB31)=0,"",SUM(AZ31:BB31)) -> 30 | BE31: =IFERROR((F31/2*BB31)+(AZ31*F31),"") -> 3220 | BG31: =IFERROR((F31/8*BF31),"") -> 0 | BQ31: =BJ31+BL31+BN31+BP31 -> 0 | BS31: =IFERROR((E31*13%/2),"") -> 273 | BT31: =IFERROR((E31*2%/2),"") -> 42 | BU31: =IFERROR((E31*13%/2),"") -> 273 | BV31: =IFERROR((E31*2%/2),"") -> 42 | BW31: =SUM(BS31:BV31) -> 630 | BY31: =BQ31+BW31 -> 630 | CA31: =IFERROR((BE31-BW31),"") -> 2590
B32: APASTEGUI GRANDEZ, LUIS ALFREDO | D32: =IFERROR(VLOOKUP(B32,'DATOS GRALES 1'!$B$2:$E$91,4,0),"") -> PEON | E32: =IF(D32="","",IF(D32="PEON","3300","4200")) -> 3300 | F32: =IFERROR((E32/30),"") -> 110 | U32: SI | V32: SI | W32: SI | X32: SI | Y32: SI | Z32: SI | AA32: SI | AB32: SI | AC32: SI | AD32: SI | AE32: SI | AF32: SI | AG32: SI | AH32: SI | AI32: SI | AJ32: SI | AK32: SI | AL32: SI | AM32: SI | AN32: SI | AO32: SI | AP32: SI | AQ32: SI | AR32: SI | AS32: SI | AT32: SI | AU32: SI | AV32: SI | AW32: SI | AX32: SI | AZ32: =IF(COUNTIF(H32:AX32,"SI")=0,"",COUNTIF(H32:AX32,"SI")) -> 30 | BA32: =IF(COUNTIF(H32:AX32,"NO")=0,"",COUNTIF(H32:AX32,"NO")) | BB32: =COUNTIF(H32:AL32,"MED") -> 0 | BC32: =IF(SUM(AZ32:BB32)=0,"",SUM(AZ32:BB32)) -> 30 | BE32: =IFERROR((F32/2*BB32)+(AZ32*F32),"") -> 3300 | BG32: =IFERROR((F32/8*BF32),"") -> 0 | BQ32: =BJ32+BL32+BN32+BP32 -> 0 | BS32: =IFERROR((E32*13%/2),"") -> 214.5 | BT32: =IFERROR((E32*2%/2),"") -> 33 | BU32: =IFERROR((E32*13%/2),"") -> 214.5 | BV32: =IFERROR((E32*2%/2),"") -> 33 | BW32: =SUM(BS32:BV32) -> 495 | BY32: =BQ32+BW32 -> 495 | CA32: =IFERROR((BE32-BW32),"") -> 2805
B33: TUANAMA PILCO, CHRIS | D33: =IFERROR(VLOOKUP(B33,'DATOS GRALES 1'!$B$2:$E$91,4,0),"") -> PEON | E33: =IF(D33="","",IF(D33="PEON","3300","4200")) -> 3300 | F33: =IFERROR((E33/30),"") -> 110 | V33: SI | W33: SI | X33: SI | Y33: SI | Z33: SI | AA33: SI | AB33: SI | AC33: SI | AD33: SI | AE33: SI | AF33: SI | AG33: SI | AH33: SI | AI33: SI | AJ33: SI | AK33: SI | AL33: SI | AM33: SI | AN33: SI | AO33: SI | AP33: SI | AQ33: SI | AR33: SI | AS33: SI | AT33: SI | AU33: SI | AV33: SI | AW33: SI | AX33: SI | AZ33: =IF(COUNTIF(H33:AX33,"SI")=0,"",COUNTIF(H33:AX33,"SI")) -> 29 | BA33: =IF(COUNTIF(H33:AX33,"NO")=0,"",COUNTIF(H33:AX33,"NO")) | BB33: =COUNTIF(H33:AL33,"MED") -> 0 | BC33: =IF(SUM(AZ33:BB33)=0,"",SUM(AZ33:BB33)) -> 29 | BE33: =IFERROR((F33/2*BB33)+(AZ33*F33),"") -> 3190 | BG33: =IFERROR((F33/8*BF33),"") -> 0 | BQ33: =BJ33+BL33+BN33+BP33 -> 0 | BS33: =IFERROR((E33*13%/2),"") -> 214.5 | BT33: =IFERROR((E33*2%/2),"") -> 33 | BU33: =IFERROR((E33*13%/2),"") -> 214.5 | BV33: =IFERROR((E33*2%/2),"") -> 33 | BW33: =SUM(BS33:BV33) -> 495 | BY33: =BQ33+BW33 -> 495 | CA33: =IFERROR((BE33-BW33),"") -> 2695
B34: CACERES CALACHUA, YEYSON JORGE | D34: =IFERROR(VLOOKUP(B34,'DATOS GRALES 1'!$B$2:$E$91,4,0),"") -> OPERARIO | E34: =IF(D34="","",IF(D34="PEON","3300","4200")) -> 4200 | F34: =IFERROR((E34/30),"") -> 140 | V34: SI | W34: SI | X34: SI | Y34: SI | Z34: SI | AA34: SI | AB34: SI | AC34: SI | AD34: SI | AE34: SI | AF34: SI | AG34: SI | AH34: SI | AI34: SI | AJ34: SI | AK34: SI | AL34: SI | AM34: SI | AN34: SI | AO34: SI | AP34: SI | AQ34: SI | AR34: SI | AS34: SI | AT34: SI | AU34: SI | AV34: SI | AW34: SI | AX34: SI | AZ34: =IF(COUNTIF(H34:AX34,"SI")=0,"",COUNTIF(H34:AX34,"SI")) -> 29 | BA34: =IF(COUNTIF(H34:AX34,"NO")=0,"",COUNTIF(H34:AX34,"NO")) | BB34: =COUNTIF(H34:AL34,"MED") -> 0 | BC34: =IF(SUM(AZ34:BB34)=0,"",SUM(AZ34:BB34)) -> 29 | BE34: =IFERROR((F34/2*BB34)+(AZ34*F34),"") -> 4060 | BG34: =IFERROR((F34/8*BF34),"") -> 0 | BQ34: =BJ34+BL34+BN34+BP34 -> 0 | BS34: =IFERROR((E34*13%/2),"") -> 273 | BT34: =IFERROR((E34*2%/2),"") -> 42 | BU34: =IFERROR((E34*13%/2),"") -> 273 | BV34: =IFERROR((E34*2%/2),"") -> 42 | BW34: =SUM(BS34:BV34) -> 630 | BY34: =BQ34+BW34 -> 630 | CA34: =IFERROR((BE34-BW34),"") -> 3430
B35: MAQUERA QUISPE, LEONIDAS EDWIN | D35: =IFERROR(VLOOKUP(B35,'DATOS GRALES 1'!$B$2:$E$91,4,0),"") -> OPERARIO | E35: =IF(D35="","",IF(D35="PEON","3300","4200")) -> 4200 | F35: =IFERROR((E35/30),"") -> 140 | AB35: SI | AC35: SI | AD35: SI | AE35: SI | AF35: SI | AG35: SI | AH35: SI | AI35: SI | AJ35: SI | AK35: SI | AL35: SI | AM35: SI | AN35: SI | AO35: SI | AP35: SI | AQ35: SI | AR35: SI | AS35: SI | AT35: SI | AU35: SI | AV35: SI | AW35: SI | AX35: SI | AZ35: =IF(COUNTIF(H35:AX35,"SI")=0,"",COUNTIF(H35:AX35,"SI")) -> 23 | BA35: =IF(COUNTIF(H35:AX35,"NO")=0,"",COUNTIF(H35:AX35,"NO")) | BB35: =COUNTIF(H35:AL35,"MED") -> 0 | BC35: =IF(SUM(AZ35:BB35)=0,"",SUM(AZ35:BB35)) -> 23 | BE35: =IFERROR((F35/2*BB35)+(AZ35*F35),"") -> 3220 | BG35: =IFERROR((F35/8*BF35),"") -> 0 | BQ35: =BJ35+BL35+BN35+BP35 -> 0 | BS35: =IFERROR((E35*13%/2),"") -> 273 | BT35: =IFERROR((E35*2%/2),"") -> 42 | BU35: =IFERROR((E35*13%/2),"") -> 273 | BV35: =IFERROR((E35*2%/2),"") -> 42 | BW35: =SUM(BS35:BV35) -> 630 | BY35: =BQ35+BW35 -> 630 | CA35: =IFERROR((BE35-BW35),"") -> 2590
B36: TACANAHUI CALISAYA NESTOR | D36: PEON | E36: =IF(D36="","",IF(D36="PEON","3300","4200")) -> 3300 | F36: =IFERROR((E36/30),"") -> 110 | AH36: SI | AI36: SI | AJ36: SI | AK36: SI | AL36: SI | AM36: SI | AN36: SI | AO36: SI | AP36: SI | AQ36: SI | AR36: SI | AS36: SI | AT36: SI | AU36: SI | AV36: SI | AW36: SI | AX36: SI | AZ36: =IF(COUNTIF(H36:AX36,"SI")=0,"",COUNTIF(H36:AX36,"SI")) -> 17 | BA36: =IF(COUNTIF(H36:AX36,"NO")=0,"",COUNTIF(H36:AX36,"NO")) | BB36: =COUNTIF(H36:AL36,"MED") -> 0 | BC36: =IF(SUM(AZ36:BB36)=0,"",SUM(AZ36:BB36)) -> 17 | BE36: =IFERROR((F36/2*BB36)+(AZ36*F36),"") -> 1870 | BG36: =IFERROR((F36/8*BF36),"") -> 0 | BQ36: =BJ36+BL36+BN36+BP36 -> 0 | BS36: =IFERROR((E36*13%/2),"") -> 214.5 | BT36: =IFERROR((E36*2%/2),"") -> 33 | BU36: =IFERROR((E36*13%/2),"") -> 214.5 | BV36: =IFERROR((E36*2%/2),"") -> 33 | BW36: =SUM(BS36:BV36) -> 495 | BY36: =BQ36+BW36 -> 495 | CA36: =IFERROR((BE36-BW36),"") -> 1375
B37: GUTARATE SABINO, RONEL ARTURO | D37: PEON | E37: =IF(D37="","",IF(D37="PEON","3300","4200")) -> 3300 | F37: =IFERROR((E37/30),"") -> 110 | AI37: SI | AJ37: SI | AK37: SI | AL37: SI | AM37: SI | AN37: SI | AO37: SI | AP37: SI | AQ37: SI | AR37: SI | AS37: SI | AT37: SI | AU37: SI | AV37: SI | AW37: SI | AX37: NO | AZ37: =IF(COUNTIF(H37:AX37,"SI")=0,"",COUNTIF(H37:AX37,"SI")) -> 15 | BA37: =IF(COUNTIF(H37:AX37,"NO")=0,"",COUNTIF(H37:AX37,"NO")) -> 1 | BB37: =COUNTIF(H37:AL37,"MED") -> 0 | BC37: =IF(SUM(AZ37:BB37)=0,"",SUM(AZ37:BB37)) -> 16 | BE37: =IFERROR((F37/2*BB37)+(AZ37*F37),"") -> 1650 | BG37: =IFERROR((F37/8*BF37),"") -> 0 | BQ37: =BJ37+BL37+BN37+BP37 -> 0 | BS37: =IFERROR((E37*13%/2),"") -> 214.5 | BT37: =IFERROR((E37*2%/2),"") -> 33 | BU37: =IFERROR((E37*13%/2),"") -> 214.5 | BV37: =IFERROR((E37*2%/2),"") -> 33 | BW37: =SUM(BS37:BV37) -> 495 | BY37: =BQ37+BW37 -> 495 | CA37: =IFERROR((BE37-BW37),"") -> 1155
B38: ROSAS CHACHAJE, WILSON JHONY | D38: =IFERROR(VLOOKUP(B38,'DATOS GRALES 1'!$B$2:$E$91,4,0),"") -> OPERARIO | E38: =IF(D38="","",IF(D38="PEON","3300","4200")) -> 4200 | F38: =IFERROR((E38/30),"") -> 140 | AZ38: =IF(COUNTIF(H38:AX38,"SI")=0,"",COUNTIF(H38:AX38,"SI")) | BA38: =IF(COUNTIF(H38:AX38,"NO")=0,"",COUNTIF(H38:AX38,"NO")) | BB38: =COUNTIF(H38:AL38,"MED") -> 0 | BC38: =IF(SUM(AZ38:BB38)=0,"",SUM(AZ38:BB38)) | BE38: =IFERROR((F38/2*BB38)+(AZ38*F38),"") | BG38: =IFERROR((F38/8*BF38),"") -> 0 | BQ38: =BJ38+BL38+BN38+BP38 -> 0 | BS38: =IFERROR((E38*13%/2),"") -> 273 | BT38: =IFERROR((E38*2%/2),"") -> 42 | BU38: =IFERROR((E38*13%/2),"") -> 273 | BV38: =IFERROR((E38*2%/2),"") -> 42 | BW38: =SUM(BS38:BV38) -> 630 | BY38: =BQ38+BW38 -> 630 | CA38: =IFERROR((BE38-BW38),"")
B39: GAMARRA CONDORI, ANGEL | D39: =IFERROR(VLOOKUP(B39,'DATOS GRALES 1'!$B$2:$E$91,4,0),"") -> OPERARIO | E39: =IF(D39="","",IF(D39="PEON","3300","4200")) -> 4200 | F39: =IFERROR((E39/30),"") -> 140 | AP39: SI | AQ39: SI | AR39: SI | AS39: SI | AT39: SI | AU39: SI | AV39: SI | AW39: SI | AX39: SI | AZ39: =IF(COUNTIF(H39:AX39,"SI")=0,"",COUNTIF(H39:AX39,"SI")) -> 9 | BA39: =IF(COUNTIF(H39:AX39,"NO")=0,"",COUNTIF(H39:AX39,"NO")) | BB39: =COUNTIF(H39:AL39,"MED") -> 0 | BC39: =IF(SUM(AZ39:BB39)=0,"",SUM(AZ39:BB39)) -> 9 | BE39: =IFERROR((F39/2*BB39)+(AZ39*F39),"") -> 1260 | BG39: =IFERROR((F39/8*BF39),"") -> 0 | BQ39: =BJ39+BL39+BN39+BP39 -> 0 | BS39: =IFERROR((E39*13%/2),"") -> 273 | BT39: =IFERROR((E39*2%/2),"") -> 42 | BU39: =IFERROR((E39*13%/2),"") -> 273 | BV39: =IFERROR((E39*2%/2),"") -> 42 | BW39: =SUM(BS39:BV39) -> 630 | BY39: =BQ39+BW39 -> 630 | CA39: =IFERROR((BE39-BW39),"") -> 630
B40: QUISPE MAQUERA, MARCO ANTONIO | D40: =IFERROR(VLOOKUP(B40,'DATOS GRALES 1'!$B$2:$E$91,4,0),"") -> PEON | E40: =IF(D40="","",IF(D40="PEON","3300","4200")) -> 3300 | F40: =IFERROR((E40/30),"") -> 110 | AZ40: =IF(COUNTIF(H40:AX40,"SI")=0,"",COUNTIF(H40:AX40,"SI")) | BA40: =IF(COUNTIF(H40:AX40,"NO")=0,"",COUNTIF(H40:AX40,"NO")) | BB40: =COUNTIF(H40:AL40,"MED") -> 0 | BC40: =IF(SUM(AZ40:BB40)=0,"",SUM(AZ40:BB40)) | BE40: =IFERROR((F40/2*BB40)+(AZ40*F40),"") | BG40: =IFERROR((F40/8*BF40),"") -> 0 | BQ40: =BJ40+BL40+BN40+BP40 -> 0 | BS40: =IFERROR((E40*13%/2),"") -> 214.5 | BT40: =IFERROR((E40*2%/2),"") -> 33 | BU40: =IFERROR((E40*13%/2),"") -> 214.5 | BV40: =IFERROR((E40*2%/2),"") -> 33 | BW40: =SUM(BS40:BV40) -> 495 | BY40: =BQ40+BW40 -> 495 | CA40: =IFERROR((BE40-BW40),"")
B41: PUMAYALLI LICONA, ENOCH | D41: =IFERROR(VLOOKUP(B41,'DATOS GRALES 1'!$B$2:$E$91,4,0),"") -> PEON | E41: =IF(D41="","",IF(D41="PEON","3300","4200")) -> 3300 | F41: =IFERROR((E41/30),"") -> 110 | AZ41: =IF(COUNTIF(H41:AX41,"SI")=0,"",COUNTIF(H41:AX41,"SI")) | BA41: =IF(COUNTIF(H41:AX41,"NO")=0,"",COUNTIF(H41:AX41,"NO")) | BB41: =COUNTIF(H41:AL41,"MED") -> 0 | BC41: =IF(SUM(AZ41:BB41)=0,"",SUM(AZ41:BB41)) | BE41: =IFERROR((F41/2*BB41)+(AZ41*F41),"") | BG41: =IFERROR((F41/8*BF41),"") -> 0 | BQ41: =BJ41+BL41+BN41+BP41 -> 0 | BS41: =IFERROR((E41*13%/2),"") -> 214.5 | BT41: =IFERROR((E41*2%/2),"") -> 33 | BU41: =IFERROR((E41*13%/2),"") -> 214.5 | BV41: =IFERROR((E41*2%/2),"") -> 33 | BW41: =SUM(BS41:BV41) -> 495 | BY41: =BQ41+BW41 -> 495 | CA41: =IFERROR((BE41-BW41),"")
B42: CURMAYARI MANUYAMA, VICTOR RAUL | D42: =IFERROR(VLOOKUP(B42,'DATOS GRALES 1'!$B$2:$E$91,4,0),"") -> OPERARIO | E42: =IF(D42="","",IF(D42="PEON","3300","4200")) -> 4200 | F42: =IFERROR((E42/30),"") -> 140 | AZ42: =IF(COUNTIF(H42:AX42,"SI")=0,"",COUNTIF(H42:AX42,"SI")) | BA42: =IF(COUNTIF(H42:AX42,"NO")=0,"",COUNTIF(H42:AX42,"NO")) | BB42: =COUNTIF(H42:AL42,"MED") -> 0 | BC42: =IF(SUM(AZ42:BB42)=0,"",SUM(AZ42:BB42)) | BE42: =IFERROR((F42/2*BB42)+(AZ42*F42),"") | BG42: =IFERROR((F42/8*BF42),"") -> 0 | BQ42: =BJ42+BL42+BN42+BP42 -> 0 | BS42: =IFERROR((E42*13%/2),"") -> 273 | BT42: =IFERROR((E42*2%/2),"") -> 42 | BU42: =IFERROR((E42*13%/2),"") -> 273 | BV42: =IFERROR((E42*2%/2),"") -> 42 | BW42: =SUM(BS42:BV42) -> 630 | BY42: =BQ42+BW42 -> 630 | CA42: =IFERROR((BE42-BW42),"")
B43: CURMAYARI GUZMAN, JOFFRE | D43: =IFERROR(VLOOKUP(B43,'DATOS GRALES 1'!$B$2:$E$91,4,0),"") -> OPERARIO | E43: =IF(D43="","",IF(D43="PEON","3300","4200")) -> 4200 | F43: =IFERROR((E43/30),"") -> 140 | AZ43: =IF(COUNTIF(H43:AX43,"SI")=0,"",COUNTIF(H43:AX43,"SI")) | BA43: =IF(COUNTIF(H43:AX43,"NO")=0,"",COUNTIF(H43:AX43,"NO")) | BB43: =COUNTIF(H43:AL43,"MED") -> 0 | BC43: =IF(SUM(AZ43:BB43)=0,"",SUM(AZ43:BB43)) | BE43: =IFERROR((F43/2*BB43)+(AZ43*F43),"") | BG43: =IFERROR((F43/8*BF43),"") -> 0 | BQ43: =BJ43+BL43+BN43+BP43 -> 0 | BS43: =IFERROR((E43*13%/2),"") -> 273 | BT43: =IFERROR((E43*2%/2),"") -> 42 | BU43: =IFERROR((E43*13%/2),"") -> 273 | BV43: =IFERROR((E43*2%/2),"") -> 42 | BW43: =SUM(BS43:BV43) -> 630 | BY43: =BQ43+BW43 -> 630 | CA43: =IFERROR((BE43-BW43),"")
B44: OLIVA TARAPA, TOMAS | D44: =IFERROR(VLOOKUP(B44,'DATOS GRALES 1'!$B$2:$E$91,4,0),"") -> PEON | E44: =IF(D44="","",IF(D44="PEON","3300","4200")) -> 3300 | F44: =IFERROR((E44/30),"") -> 110 | AX44: SI | AZ44: =IF(COUNTIF(H44:AX44,"SI")=0,"",COUNTIF(H44:AX44,"SI")) -> 1 | BA44: =IF(COUNTIF(H44:AX44,"NO")=0,"",COUNTIF(H44:AX44,"NO")) | BB44: =COUNTIF(H44:AL44,"MED") -> 0 | BC44: =IF(SUM(AZ44:BB44)=0,"",SUM(AZ44:BB44)) -> 1 | BE44: =IFERROR((F44/2*BB44)+(AZ44*F44),"") -> 110 | BG44: =IFERROR((F44/8*BF44),"") -> 0 | BQ44: =BJ44+BL44+BN44+BP44 -> 0 | BS44: =IFERROR((E44*13%/2),"") -> 214.5 | BT44: =IFERROR((E44*2%/2),"") -> 33 | BU44: =IFERROR((E44*13%/2),"") -> 214.5 | BV44: =IFERROR((E44*2%/2),"") -> 33 | BW44: =SUM(BS44:BV44) -> 495 | BY44: =BQ44+BW44 -> 495 | CA44: =IFERROR((BE44-BW44),"") -> -385
B45: MACHUCA NAVARRO, OMAR JIAN FRANCO | D45: =IFERROR(VLOOKUP(B45,'DATOS GRALES 1'!$B$2:$E$91,4,0),"") -> PEON | E45: =IF(D45="","",IF(D45="PEON","3300","4200")) -> 3300 | F45: =IFERROR((E45/30),"") -> 110 | AX45: SI | AZ45: =IF(COUNTIF(H45:AX45,"SI")=0,"",COUNTIF(H45:AX45,"SI")) -> 1 | BA45: =IF(COUNTIF(H45:AX45,"NO")=0,"",COUNTIF(H45:AX45,"NO")) | BB45: =COUNTIF(H45:AL45,"MED") -> 0 | BC45: =IF(SUM(AZ45:BB45)=0,"",SUM(AZ45:BB45)) -> 1 | BE45: =IFERROR((F45/2*BB45)+(AZ45*F45),"") -> 110 | BG45: =IFERROR((F45/8*BF45),"") -> 0 | BQ45: =BJ45+BL45+BN45+BP45 -> 0 | BS45: =IFERROR((E45*13%/2),"") -> 214.5 | BT45: =IFERROR((E45*2%/2),"") -> 33 | BU45: =IFERROR((E45*13%/2),"") -> 214.5 | BV45: =IFERROR((E45*2%/2),"") -> 33 | BW45: =SUM(BS45:BV45) -> 495 | BY45: =BQ45+BW45 -> 495 | CA45: =IFERROR((BE45-BW45),"") -> -385
D46: =IFERROR(VLOOKUP(B46,'DATOS GRALES 1'!$B$2:$E$91,4,0),"") | E46: =IF(D46="","",IF(D46="PEON","3300","4200")) | F46: =IFERROR((E46/30),"") | AZ46: =IF(COUNTIF(H46:AX46,"SI")=0,"",COUNTIF(H46:AX46,"SI")) | BA46: =IF(COUNTIF(H46:AX46,"NO")=0,"",COUNTIF(H46:AX46,"NO")) | BB46: =COUNTIF(H46:AL46,"MED") -> 0 | BC46: =IF(SUM(AZ46:BB46)=0,"",SUM(AZ46:BB46)) | BE46: =IFERROR((F46/2*BB46)+(AZ46*F46),"") | BG46: =IFERROR((F46/8*BF46),"") | BQ46: =BJ46+BL46+BN46+BP46 -> 0 | BS46: =IFERROR((E46*13%/2),"") | BT46: =IFERROR((E46*2%/2),"") | BU46: =IFERROR((E46*13%/2),"") | BV46: =IFERROR((E46*2%/2),"") | BW46: =SUM(BS46:BV46) -> 0 | BY46: =BQ46+BW46 -> 0 | CA46: =IFERROR((BE46-BW46),"")
D47: =IFERROR(VLOOKUP(B47,'DATOS GRALES 1'!$B$2:$E$91,4,0),"") | E47: =IF(D47="","",IF(D47="PEON","3300","4200")) | F47: =IFERROR((E47/30),"") | AZ47: =IF(COUNTIF(H47:AX47,"SI")=0,"",COUNTIF(H47:AX47,"SI")) | BA47: =IF(COUNTIF(H47:AX47,"NO")=0,"",COUNTIF(H47:AX47,"NO")) | BB47: =COUNTIF(H47:AL47,"MED") -> 0 | BC47: =IF(SUM(AZ47:BB47)=0,"",SUM(AZ47:BB47)) | BE47: =IFERROR((F47/2*BB47)+(AZ47*F47),"") | BG47: =IFERROR((F47/8*BF47),"") | BQ47: =BJ47+BL47+BN47+BP47 -> 0 | BS47: =IFERROR((E47*13%/2),"") | BT47: =IFERROR((E47*2%/2),"") | BU47: =IFERROR((E47*13%/2),"") | BV47: =IFERROR((E47*2%/2),"") | BW47: =SUM(BS47:BV47) -> 0 | BY47: =BQ47+BW47 -> 0 | CA47: =IFERROR((BE47-BW47),"")
D48: =IFERROR(VLOOKUP(B48,'DATOS GRALES 1'!$B$2:$E$91,4,0),"") | E48: =IF(D48="","",IF(D48="PEON","3300","4200")) | F48: =IFERROR((E48/30),"") | AZ48: =IF(COUNTIF(H48:AX48,"SI")=0,"",COUNTIF(H48:AX48,"SI")) | BA48: =IF(COUNTIF(H48:AX48,"NO")=0,"",COUNTIF(H48:AX48,"NO")) | BB48: =COUNTIF(H48:AL48,"MED") -> 0 | BC48: =IF(SUM(AZ48:BB48)=0,"",SUM(AZ48:BB48)) | BE48: =IFERROR((F48/2*BB48)+(AZ48*F48),"") | BG48: =IFERROR((F48/8*BF48),"") | BQ48: =BJ48+BL48+BN48+BP48 -> 0 | BS48: =IFERROR((E48*13%/2),"") | BT48: =IFERROR((E48*2%/2),"") | BU48: =IFERROR((E48*13%/2),"") | BV48: =IFERROR((E48*2%/2),"") | BW48: =SUM(BS48:BV48) -> 0 | BY48: =BQ48+BW48 -> 0 | CA48: =IFERROR((BE48-BW48),"")
D49: =IFERROR(VLOOKUP(B49,'DATOS GRALES 1'!$B$2:$E$91,4,0),"") | E49: =IF(D49="","",IF(D49="PEON","3300","4200")) | F49: =IFERROR((E49/30),"") | AZ49: =IF(COUNTIF(H49:AX49,"SI")=0,"",COUNTIF(H49:AX49,"SI")) | BA49: =IF(COUNTIF(H49:AX49,"NO")=0,"",COUNTIF(H49:AX49,"NO")) | BB49: =COUNTIF(H49:AL49,"MED") -> 0 | BC49: =IF(SUM(AZ49:BB49)=0,"",SUM(AZ49:BB49)) | BE49: =IFERROR((F49/2*BB49)+(AZ49*F49),"") | BG49: =IFERROR((F49/8*BF49),"") | BQ49: =BJ49+BL49+BN49+BP49 -> 0 | BS49: =IFERROR((E49*13%/2),"") | BT49: =IFERROR((E49*2%/2),"") | BU49: =IFERROR((E49*13%/2),"") | BV49: =IFERROR((E49*2%/2),"") | BW49: =SUM(BS49:BV49) -> 0 | BY49: =BQ49+BW49 -> 0 | CA49: =IFERROR((BE49-BW49),"")
D50: =IFERROR(VLOOKUP(B50,'DATOS GRALES 1'!$B$2:$E$91,4,0),"") | E50: =IF(D50="","",IF(D50="PEON","3300","4200")) | F50: =IFERROR((E50/30),"") | AZ50: =IF(COUNTIF(H50:AX50,"SI")=0,"",COUNTIF(H50:AX50,"SI")) | BA50: =IF(COUNTIF(H50:AX50,"NO")=0,"",COUNTIF(H50:AX50,"NO")) | BB50: =COUNTIF(H50:AL50,"MED") -> 0 | BC50: =IF(SUM(AZ50:BB50)=0,"",SUM(AZ50:BB50)) | BE50: =IFERROR((F50/2*BB50)+(AZ50*F50),"") | BG50: =IFERROR((F50/8*BF50),"") | BQ50: =BJ50+BL50+BN50+BP50 -> 0 | BS50: =IFERROR((E50*13%/2),"") | BT50: =IFERROR((E50*2%/2),"") | BU50: =IFERROR((E50*13%/2),"") | BV50: =IFERROR((E50*2%/2),"") | BW50: =SUM(BS50:BV50) -> 0 | BY50: =BQ50+BW50 -> 0 | CA50: =IFERROR((BE50-BW50),"")
D51: =IFERROR(VLOOKUP(B51,'DATOS GRALES 1'!$B$2:$E$91,4,0),"") | E51: =IF(D51="","",IF(D51="PEON","3300","4200")) | F51: =IFERROR((E51/30),"") | AZ51: =IF(COUNTIF(H51:AX51,"SI")=0,"",COUNTIF(H51:AX51,"SI")) | BA51: =IF(COUNTIF(H51:AX51,"NO")=0,"",COUNTIF(H51:AX51,"NO")) | BB51: =COUNTIF(H51:AL51,"MED") -> 0 | BC51: =IF(SUM(AZ51:BB51)=0,"",SUM(AZ51:BB51)) | BE51: =IFERROR((F51/2*BB51)+(AZ51*F51),"") | BG51: =IFERROR((F51/8*BF51),"") | BQ51: =BJ51+BL51+BN51+BP51 -> 0 | BS51: =IFERROR((E51*13%/2),"") | BT51: =IFERROR((E51*2%/2),"") | BU51: =IFERROR((E51*13%/2),"") | BV51: =IFERROR((E51*2%/2),"") | BW51: =SUM(BS51:BV51) -> 0 | BY51: =BQ51+BW51 -> 0 | CA51: =IFERROR((BE51-BW51),"")
D52: =IFERROR(VLOOKUP(B52,'DATOS GRALES 1'!$B$2:$E$91,4,0),"") | E52: =IF(D52="","",IF(D52="PEON","3300","4200")) | F52: =IFERROR((E52/30),"") | AZ52: =IF(COUNTIF(H52:AX52,"SI")=0,"",COUNTIF(H52:AX52,"SI")) | BA52: =IF(COUNTIF(H52:AX52,"NO")=0,"",COUNTIF(H52:AX52,"NO")) | BB52: =COUNTIF(H52:AL52,"MED") -> 0 | BC52: =IF(SUM(AZ52:BB52)=0,"",SUM(AZ52:BB52)) | BE52: =IFERROR((F52/2*BB52)+(AZ52*F52),"") | BG52: =IFERROR((F52/8*BF52),"") | BQ52: =BJ52+BL52+BN52+BP52 -> 0 | BS52: =IFERROR((E52*13%/2),"") | BT52: =IFERROR((E52*2%/2),"") | BU52: =IFERROR((E52*13%/2),"") | BV52: =IFERROR((E52*2%/2),"") | BW52: =SUM(BS52:BV52) -> 0 | BY52: =BQ52+BW52 -> 0 | CA52: =IFERROR((BE52-BW52),"")
D53: =IFERROR(VLOOKUP(B53,'DATOS GRALES 1'!$B$2:$E$91,4,0),"") | E53: =IF(D53="","",IF(D53="PEON","3300","4200")) | F53: =IFERROR((E53/30),"") | AZ53: =IF(COUNTIF(H53:AX53,"SI")=0,"",COUNTIF(H53:AX53,"SI")) | BA53: =IF(COUNTIF(H53:AX53,"NO")=0,"",COUNTIF(H53:AX53,"NO")) | BB53: =COUNTIF(H53:AL53,"MED") -> 0 | BC53: =IF(SUM(AZ53:BB53)=0,"",SUM(AZ53:BB53)) | BE53: =IFERROR((F53/2*BB53)+(AZ53*F53),"") | BG53: =IFERROR((F53/8*BF53),"") | BQ53: =BJ53+BL53+BN53+BP53 -> 0 | BS53: =IFERROR((E53*13%/2),"") | BT53: =IFERROR((E53*2%/2),"") | BU53: =IFERROR((E53*13%/2),"") | BV53: =IFERROR((E53*2%/2),"") | BW53: =SUM(BS53:BV53) -> 0 | BY53: =BQ53+BW53 -> 0 | CA53: =IFERROR((BE53-BW53),"")
D54: =IFERROR(VLOOKUP(B54,'DATOS GRALES 1'!$B$2:$E$91,4,0),"") | E54: =IF(D54="","",IF(D54="PEON","3300","4200")) | F54: =IFERROR((E54/30),"") | AZ54: =IF(COUNTIF(H54:AX54,"SI")=0,"",COUNTIF(H54:AX54,"SI")) | BA54: =IF(COUNTIF(H54:AX54,"NO")=0,"",COUNTIF(H54:AX54,"NO")) | BB54: =COUNTIF(H54:AL54,"MED") -> 0 | BC54: =IF(SUM(AZ54:BB54)=0,"",SUM(AZ54:BB54)) | BE54: =IFERROR((F54/2*BB54)+(AZ54*F54),"") | BG54: =IFERROR((F54/8*BF54),"") | BQ54: =BJ54+BL54+BN54+BP54 -> 0 | BS54: =IFERROR((E54*13%/2),"") | BT54: =IFERROR((E54*2%/2),"") | BU54: =IFERROR((E54*13%/2),"") | BV54: =IFERROR((E54*2%/2),"") | BW54: =SUM(BS54:BV54) -> 0 | BY54: =BQ54+BW54 -> 0 | CA54: =IFERROR((BE54-BW54),"")
D55: =IFERROR(VLOOKUP(B55,'DATOS GRALES 1'!$B$2:$E$91,4,0),"") | E55: =IF(D55="","",IF(D55="PEON","3300","4200")) | F55: =IFERROR((E55/30),"") | AZ55: =IF(COUNTIF(H55:AX55,"SI")=0,"",COUNTIF(H55:AX55,"SI")) | BA55: =IF(COUNTIF(H55:AX55,"NO")=0,"",COUNTIF(H55:AX55,"NO")) | BB55: =COUNTIF(H55:AL55,"MED") -> 0 | BC55: =IF(SUM(AZ55:BB55)=0,"",SUM(AZ55:BB55)) | BE55: =IFERROR((F55/2*BB55)+(AZ55*F55),"") | BG55: =IFERROR((F55/8*BF55),"") | BQ55: =BJ55+BL55+BN55+BP55 -> 0 | BS55: =IFERROR((E55*13%/2),"") | BT55: =IFERROR((E55*2%/2),"") | BU55: =IFERROR((E55*13%/2),"") | BV55: =IFERROR((E55*2%/2),"") | BW55: =SUM(BS55:BV55) -> 0 | BY55: =BQ55+BW55 -> 0 | CA55: =IFERROR((BE55-BW55),"")
D56: =IFERROR(VLOOKUP(B56,'DATOS GRALES 1'!$B$2:$E$91,4,0),"") | E56: =IF(D56="","",IF(D56="PEON","3300","4200")) | F56: =IFERROR((E56/30),"") | AZ56: =IF(COUNTIF(H56:AX56,"SI")=0,"",COUNTIF(H56:AX56,"SI")) | BA56: =IF(COUNTIF(H56:AX56,"NO")=0,"",COUNTIF(H56:AX56,"NO")) | BB56: =COUNTIF(H56:AL56,"MED") -> 0 | BC56: =IF(SUM(AZ56:BB56)=0,"",SUM(AZ56:BB56)) | BE56: =IFERROR((F56/2*BB56)+(AZ56*F56),"") | BG56: =IFERROR((F56/8*BF56),"") | BQ56: =BJ56+BL56+BN56+BP56 -> 0 | BS56: =IFERROR((E56*13%/2),"") | BT56: =IFERROR((E56*2%/2),"") | BU56: =IFERROR((E56*13%/2),"") | BV56: =IFERROR((E56*2%/2),"") | BW56: =SUM(BS56:BV56) -> 0 | BY56: =BQ56+BW56 -> 0 | CA56: =IFERROR((BE56-BW56),"")
D57: =IFERROR(VLOOKUP(B57,'DATOS GRALES 1'!$B$2:$E$91,4,0),"") | E57: =IF(D57="","",IF(D57="PEON","3300","4200")) | F57: =IFERROR((E57/30),"") | AZ57: =IF(COUNTIF(H57:AX57,"SI")=0,"",COUNTIF(H57:AX57,"SI")) | BA57: =IF(COUNTIF(H57:AX57,"NO")=0,"",COUNTIF(H57:AX57,"NO")) | BB57: =COUNTIF(H57:AL57,"MED") -> 0 | BC57: =IF(SUM(AZ57:BB57)=0,"",SUM(AZ57:BB57)) | BE57: =IFERROR((F57/2*BB57)+(AZ57*F57),"") | BG57: =IFERROR((F57/8*BF57),"") | BQ57: =BJ57+BL57+BN57+BP57 -> 0 | BS57: =IFERROR((E57*13%/2),"") | BT57: =IFERROR((E57*2%/2),"") | BU57: =IFERROR((E57*13%/2),"") | BV57: =IFERROR((E57*2%/2),"") | BW57: =SUM(BS57:BV57) -> 0 | BY57: =BQ57+BW57 -> 0 | CA57: =IFERROR((BE57-BW57),"")
... D61: =IFERROR(VLOOKUP(B61,'DATOS GRALES 1'!$B$2:$E$91,4,0),"") | E61: =IF(D61="","",IF(D61="PEON","3300","4200")) | F61: =IFERROR((E61/30),"") | AZ61: =IF(COUNTIF(H61:AX61,"SI")=0,"",COUNTIF(H61:AX61,"SI")) | BA61: =IF(COUNTIF(H61:AX61,"NO")=0,"",COUNTIF(H61:AX61,"NO")) | BB61: =COUNTIF(H61:AL61,"MED") -> 0 | BC61: =IF(SUM(AZ61:BB61)=0,"",SUM(AZ61:BB61)) | BE61: =IFERROR((F61/2*BB61)+(AZ61*F61),"") | BG61: =IFERROR((F61/8*BF61),"") | BQ61: =BJ61+BL61+BN61+BP61 -> 0 | BS61: =IFERROR((E61*13%/2),"") | BT61: =IFERROR((E61*2%/2),"") | BU61: =IFERROR((E61*13%/2),"") | BV61: =IFERROR((E61*2%/2),"") | BW61: =SUM(BS61:BV61) -> 0 | BY61: =BQ61+BW61 -> 0 | CA61: =IFERROR((BE61-BW61),"")

Sheet OCT - NOV
B2: OCTUBRE | D2: NOVIEMBRE
B4: 2025
H9: =DATE(B4,MONTH(B2&1),21) -> 45951 | I9: =H9+1 -> 45952 | J9: =I9+1 -> 45953 | K9: =J9+1 -> 45954 | L9: =K9+1 -> 45955 | M9: =L9+1 -> 45956 | N9: =M9+1 -> 45957 | O9: =N9+1 -> 45958 | P9: =O9+1 -> 45959 | ... AL9: =AK9+1 -> 45981 | AN9: ADICIONAL 1 | AO9: ADICIONAL 2 | AP9: ADICIONAL 3 | AQ9: ADICIONAL 4 | AR9: ADICIONAL 5 | BI9: ADELANTOS A LOS TRABAJADORES | BS9: DESCUENTOS | CF9: AFP | CG9: 0.13 | CI9: CONAFO | CJ9: 0.02
B11: APELLIDOS Y NOMBRES | D11: CARGO | E11: SUELDO MENSUAL | F11: SUELDO X DIA | H11: =PROPER(LEFT(TEXT(H9,"dddd"),3)) -> Mar | I11: =PROPER(LEFT(TEXT(I9,"dddd"),3)) -> Mié | J11: =PROPER(LEFT(TEXT(J9,"dddd"),3)) -> Jue | K11: =PROPER(LEFT(TEXT(K9,"dddd"),3)) -> Vie | L11: =PROPER(LEFT(TEXT(L9,"dddd"),3)) -> Sáb | M11: =PROPER(LEFT(TEXT(M9,"dddd"),3)) -> Dom | N11: =PROPER(LEFT(TEXT(N9,"dddd"),3)) -> Lun | O11: =PROPER(LEFT(TEXT(O9,"dddd"),3)) -> Mar | ... AX11: =PROPER(LEFT(TEXT(AX9,"dddd"),3)) -> Sáb | AZ11: ASISTIO | BA11: FALTO | BB11: MEDIO DIA (MED) | BC11: TOTAL | BE11: SUELDO | BF11: HORAS EXTRAS | BG11: HORAS EXTRAS A PAGAR | BI11: FECHA | BJ11: ADELANTO 1 | BK11: FECHA | BL11: ADELANTO 2 | BM11: FECHA | BN11: ADELANTO 3 | BO11: FECHA | BP11: ADELANTO 4 | BQ11: TOTAL ADELANTOS | BS11: AFP SETIEMBRE MITAD FINAL | BT11: CONAFOVICER AGOSTO MITAD | BU11: AFP OCTUBRE 1ERA MITAD | BV11: CONAFOVICER SETIEMBRE MITAD | BW11: TOTAL DESCUENTOS | BY11: SUMA TOTAL ADELANTOS Y DSCTOS | CA11: SUELDO NETO A DEPOSITAR | CF11: ONP | CG11: 0.09
B12: SALAZAR BAZAN, ROCÍO DALILA | D12: =IFERROR(VLOOKUP(B12,'DATOS GRALES 1'!$B$2:$E$91,4,0),"") -> RESIDENTE | F12: =E12/30 -> 0 | H12: SI | I12: SI | J12: SI | K12: SI | L12: SI | M12: SI | N12: SI | O12: SI | P12: SI | Q12: SI | R12: SI | S12: SI | T12: SI | U12: SI | V12: SI | W12: SI | X12: SI | Y12: SI | AZ12: =IF(COUNTIF(H12:AX12,"SI")=0,"",COUNTIF(H12:AX12,"SI")) -> 18 | BA12: =IF(COUNTIF(H12:AX12,"NO")=0,"",COUNTIF(H12:AX12,"NO")) | BB12: =COUNTIF(H12:AL12,"MED") -> 0 | BC12: =IF(SUM(AZ12:BB12)=0,"",SUM(AZ12:BB12)) -> 18 | BE12: =IFERROR((F12/2*BB12)+(AZ12*F12),0) -> 0 | BG12: =F12/8*BF12 -> 0 | BQ12: =BJ12+BL12+BN12+BP12 -> 0 | BS12: =IF(CB12=$CF$9,(E12*$CG$9/2),IF(CB12=$CF$11,(E12*$CG$11/2),0)) -> 0 | BT12: =IF(CB12=$CF$9,(E12*$CJ$9/2),IF(CB12=$CF$11,(E12*$CJ$9/2),0)) -> 0 | BU12: =IF(CB12=$CF$9,(E12*$CG$9/2),IF(CB12=$CF$11,(E12*$CG$11/2),0)) -> 0 | BV12: =IF(CB12=$CF$9,(E12*$CJ$9/2),IF(CB12=$CF$11,(E12*$CJ$9/2),0)) -> 0 | BW12: =SUM(BS12:BV12) -> 0 | BY12: =BQ12+BW12 -> 0 | CA12: =BE12-BY12 -> 0 | CB12: AFP
B13: ALEJO CHARCA, DENNYS MIRIAM | D13: =IFERROR(VLOOKUP(B13,'DATOS GRALES 1'!$B$2:$E$91,4,0),"") -> ING. CALIDAD | F13: =E13/30 -> 0 | H13: SI | I13: SI | J13: SI | K13: SI | L13: SI | M13: SI | N13: SI | O13: SI | P13: SI | Q13: SI | R13: SI | S13: SI | T13: SI | U13: SI | V13: SI | W13: SI | X13: SI | Y13: SI | AZ13: =IF(COUNTIF(H13:AX13,"SI")=0,"",COUNTIF(H13:AX13,"SI")) -> 18 | BA13: =IF(COUNTIF(H13:AX13,"NO")=0,"",COUNTIF(H13:AX13,"NO")) | BB13: =COUNTIF(H13:AL13,"MED") -> 0 | BC13: =IF(SUM(AZ13:BB13)=0,"",SUM(AZ13:BB13)) -> 18 | BE13: =IFERROR((F13/2*BB13)+(AZ13*F13),0) -> 0 | BG13: =F13/8*BF13 -> 0 | BQ13: =BJ13+BL13+BN13+BP13 -> 0 | BS13: =IF(CB13=$CF$9,(E13*$CG$9/2),IF(CB13=$CF$11,(E13*$CG$11/2),0)) -> 0 | BT13: =IF(CB13=$CF$9,(E13*$CJ$9/2),IF(CB13=$CF$11,(E13*$CJ$9/2),0)) -> 0 | BU13: =IF(CB13=$CF$9,(E13*$CG$9/2),IF(CB13=$CF$11,(E13*$CG$11/2),0)) -> 0 | BV13: =IF(CB13=$CF$9,(E13*$CJ$9/2),IF(CB13=$CF$11,(E13*$CJ$9/2),0)) -> 0 | BW13: =SUM(BS13:BV13) -> 0 | BY13: =BQ13+BW13 -> 0 | CA13: =BE13-BY13 -> 0 | CB13: AFP
B14: MOGROVEJO FALCON, OSMAR ADOLFO | D14: =IFERROR(VLOOKUP(B14,'DATOS GRALES 1'!$B$2:$E$91,4,0),"") -> ESP. SEGURIDAD | F14: =E14/30 -> 0 | H14: SI | I14: SI | J14: SI | K14: SI | L14: SI | M14: SI | N14: SI | O14: SI | P14: SI | Q14: SI | R14: SI | S14: SI | T14: SI | U14: SI | V14: SI | W14: MED | X14: SI | Y14: SI | AZ14: =IF(COUNTIF(H14:AX14,"SI")=0,"",COUNTIF(H14:AX14,"SI")) -> 17 | BA14: =IF(COUNTIF(H14:AX14,"NO")=0,"",COUNTIF(H14:AX14,"NO")) | BB14: =COUNTIF(H14:AL14,"MED") -> 1 | BC14: =IF(SUM(AZ14:BB14)=0,"",SUM(AZ14:BB14)) -> 18 | BE14: =IFERROR((F14/2*BB14)+(AZ14*F14),0) -> 0 | BG14: =F14/8*BF14 -> 0 | BQ14: =BJ14+BL14+BN14+BP14 -> 0 | BS14: =IF(CB14=$CF$9,(E14*$CG$9/2),IF(CB14=$CF$11,(E14*$CG$11/2),0)) -> 0 | BT14: =IF(CB14=$CF$9,(E14*$CJ$9/2),IF(CB14=$CF$11,(E14*$CJ$9/2),0)) -> 0 | BU14: =IF(CB14=$CF$9,(E14*$CG$9/2),IF(CB14=$CF$11,(E14*$CG$11/2),0)) -> 0 | BV14: =IF(CB14=$CF$9,(E14*$CJ$9/2),IF(CB14=$CF$11,(E14*$CJ$9/2),0)) -> 0 | BW14: =SUM(BS14:BV14) -> 0 | BY14: =BQ14+BW14 -> 0 | CA14: =BE14-BY14 -> 0 | CB14: ONP
B15: SILVA BORDA, ARLETTE NINOSKA | D15: =IFERROR(VLOOKUP(B15,'DATOS GRALES 1'!$B$2:$E$91,4,0),"") -> ASIS. ING. | F15: =E15/30 -> 0 | H15: SI | I15: SI | J15: SI | K15: SI | L15: SI | M15: SI | N15: SI | O15: SI | P15: SI | Q15: SI | R15: SI | S15: SI | T15: SI | U15: SI | V15: SI | W15: SI | X15: SI | Y15: SI | AZ15: =IF(COUNTIF(H15:AX15,"SI")=0,"",COUNTIF(H15:AX15,"SI")) -> 18 | BA15: =IF(COUNTIF(H15:AX15,"NO")=0,"",COUNTIF(H15:AX15,"NO")) | BB15: =COUNTIF(H15:AL15,"MED") -> 0 | BC15: =IF(SUM(AZ15:BB15)=0,"",SUM(AZ15:BB15)) -> 18 | BE15: =IFERROR((F15/2*BB15)+(AZ15*F15),0) -> 0 | BG15: =F15/8*BF15 -> 0 | BQ15: =BJ15+BL15+BN15+BP15 -> 0 | BS15: =IF(CB15=$CF$9,(E15*$CG$9/2),IF(CB15=$CF$11,(E15*$CG$11/2),0)) -> 0 | BT15: =IF(CB15=$CF$9,(E15*$CJ$9/2),IF(CB15=$CF$11,(E15*$CJ$9/2),0)) -> 0 | BU15: =IF(CB15=$CF$9,(E15*$CG$9/2),IF(CB15=$CF$11,(E15*$CG$11/2),0)) -> 0 | BV15: =IF(CB15=$CF$9,(E15*$CJ$9/2),IF(CB15=$CF$11,(E15*$CJ$9/2),0)) -> 0 | BW15: =SUM(BS15:BV15) -> 0 | BY15: =BQ15+BW15 -> 0 | CA15: =BE15-BY15 -> 0 | CB15: RH
B16: LOZA YAPUCHURA, KENNY GUILLERMO | D16: =IFERROR(VLOOKUP(B16,'DATOS GRALES 1'!$B$2:$E$91,4,0),"") -> TOPOGRAFO | F16: =E16/30 -> 0 | H16: SI | I16: SI | J16: SI | K16: SI | L16: SI | M16: SI | N16: SI | O16: SI | P16: SI | Q16: SI | R16: SI | S16: SI | T16: SI | U16: NO | V16: SI | W16: SI | X16: SI | Y16: SI | AZ16: =IF(COUNTIF(H16:AX16,"SI")=0,"",COUNTIF(H16:AX16,"SI")) -> 17 | BA16: =IF(COUNTIF(H16:AX16,"NO")=0,"",COUNTIF(H16:AX16,"NO")) -> 1 | BB16: =COUNTIF(H16:AL16,"MED") -> 0 | BC16: =IF(SUM(AZ16:BB16)=0,"",SUM(AZ16:BB16)) -> 18 | BE16: =IFERROR((F16/2*BB16)+(AZ16*F16),0) -> 0 | BG16: =F16/8*BF16 -> 0 | BQ16: =BJ16+BL16+BN16+BP16 -> 0 | BS16: =IF(CB16=$CF$9,(E16*$CG$9/2),IF(CB16=$CF$11,(E16*$CG$11/2),0)) -> 0 | BT16: =IF(CB16=$CF$9,(E16*$CJ$9/2),IF(CB16=$CF$11,(E16*$CJ$9/2),0)) -> 0 | BU16: =IF(CB16=$CF$9,(E16*$CG$9/2),IF(CB16=$CF$11,(E16*$CG$11/2),0)) -> 0 | BV16: =IF(CB16=$CF$9,(E16*$CJ$9/2),IF(CB16=$CF$11,(E16*$CJ$9/2),0)) -> 0 | BW16: =SUM(BS16:BV16) -> 0 | BY16: =BQ16+BW16 -> 0 | CA16: =BE16-BY16 -> 0 | CB16: RH
B17: ADUVIRE ARGUATA, MARIO ARTURO | D17: =IFERROR(VLOOKUP(B17,'DATOS GRALES 1'!$B$2:$E$91,4,0),"") -> MAESTRO OBRA | F17: =E17/30 -> 0 | H17: SI | I17: SI | J17: SI | K17: SI | L17: SI | M17: SI | N17: SI | O17: SI | P17: SI | Q17: SI | R17: SI | S17: SI | T17: SI | U17: SI | V17: SI | W17: SI | X17: SI | Y17: SI | AZ17: =IF(COUNTIF(H17:AX17,"SI")=0,"",COUNTIF(H17:AX17,"SI")) -> 18 | BA17: =IF(COUNTIF(H17:AX17,"NO")=0,"",COUNTIF(H17:AX17,"NO")) | BB17: =COUNTIF(H17:AL17,"MED") -> 0 | BC17: =IF(SUM(AZ17:BB17)=0,"",SUM(AZ17:BB17)) -> 18 | BE17: =IFERROR((F17/2*BB17)+(AZ17*F17),0) -> 0 | BG17: =F17/8*BF17 -> 0 | BQ17: =BJ17+BL17+BN17+BP17 -> 0 | BS17: =IF(CB17=$CF$9,(E17*$CG$9/2),IF(CB17=$CF$11,(E17*$CG$11/2),0)) -> 0 | BT17: =IF(CB17=$CF$9,(E17*$CJ$9/2),IF(CB17=$CF$11,(E17*$CJ$9/2),0)) -> 0 | BU17: =IF(CB17=$CF$9,(E17*$CG$9/2),IF(CB17=$CF$11,(E17*$CG$11/2),0)) -> 0 | BV17: =IF(CB17=$CF$9,(E17*$CJ$9/2),IF(CB17=$CF$11,(E17*$CJ$9/2),0)) -> 0 | BW17: =SUM(BS17:BV17) -> 0 | BY17: =BQ17+BW17 -> 0 | CA17: =BE17-BY17 -> 0 | CB17: AFP
B18: ACUACHI LANCHIPA, ERNESTO ALONSO | D18: =IFERROR(VLOOKUP(B18,'DATOS GRALES 1'!$B$2:$E$91,4,0),"") -> LOGISTICO | E18: 3000 | F18: =E18/30 -> 100 | H18: SI | I18: SI | J18: SI | K18: SI | L18: SI | M18: SI | N18: SI | O18: SI | P18: SI | Q18: SI | R18: SI | S18: SI | T18: SI | U18: SI | V18: SI | W18: SI | X18: SI | Y18: SI | AZ18: =IF(COUNTIF(H18:AX18,"SI")=0,"",COUNTIF(H18:AX18,"SI")) -> 18 | BA18: =IF(COUNTIF(H18:AX18,"NO")=0,"",COUNTIF(H18:AX18,"NO")) | BB18: =COUNTIF(H18:AL18,"MED") -> 0 | BC18: =IF(SUM(AZ18:BB18)=0,"",SUM(AZ18:BB18)) -> 18 | BE18: =IFERROR((F18/2*BB18)+(AZ18*F18),0) -> 1800 | BG18: =F18/8*BF18 -> 0 | BQ18: =BJ18+BL18+BN18+BP18 -> 0 | BS18: =IF(CB18=$CF$9,(E18*$CG$9/2),IF(CB18=$CF$11,(E18*$CG$11/2),0)) -> 0 | BT18: =IF(CB18=$CF$9,(E18*$CJ$9/2),IF(CB18=$CF$11,(E18*$CJ$9/2),0)) -> 0 | BU18: =IF(CB18=$CF$9,(E18*$CG$9/2),IF(CB18=$CF$11,(E18*$CG$11/2),0)) -> 0 | BV18: =IF(CB18=$CF$9,(E18*$CJ$9/2),IF(CB18=$CF$11,(E18*$CJ$9/2),0)) -> 0 | BW18: =SUM(BS18:BV18) -> 0 | BY18: =BQ18+BW18 -> 0 | CA18: =BE18-BY18 -> 1800 | CB18: RH | CD18: =IF(CB18=$CF$9,(E18*$CG$9/2),IF(CB18=$CF$11,(E18*$CG$11/2),""))
AZ19: =IF(COUNTIF(H19:AX19,"SI")=0,"",COUNTIF(H19:AX19,"SI")) | BA19: =IF(COUNTIF(H19:AX19,"NO")=0,"",COUNTIF(H19:AX19,"NO")) | BC19: =IF(SUM(AZ19:BB19)=0,"",SUM(AZ19:BB19))
B20: OBREROS | AZ20: =IF(COUNTIF(H20:AX20,"SI")=0,"",COUNTIF(H20:AX20,"SI")) | BA20: =IF(COUNTIF(H20:AX20,"NO")=0,"",COUNTIF(H20:AX20,"NO")) | BC20: =IF(SUM(AZ20:BB20)=0,"",SUM(AZ20:BB20))
B21: NAVARRO LOZANO, ANGEL JAROL | D21: =IFERROR(VLOOKUP(B21,'DATOS GRALES 1'!$B$2:$E$91,4,0),"") -> PEON | E21: =IF(D21="",0,IF(D21="PEON",3300,4200)) -> 3300 | F21: =IFERROR((E21/30),"") -> 110 | H21: SI | I21: SI | J21: SI | K21: SI | L21: SI | M21: SI | N21: SI | O21: SI | P21: SI | Q21: SI | R21: SI | S21: SI | T21: SI | U21: SI | V21: SI | W21: SI | X21: SI | Y21: SI | AZ21: =IF(COUNTIF(H21:AX21,"SI")=0,"",COUNTIF(H21:AX21,"SI")) -> 18 | BA21: =IF(COUNTIF(H21:AX21,"NO")=0,"",COUNTIF(H21:AX21,"NO")) | BB21: =COUNTIF(H21:AL21,"MED") -> 0 | BC21: =IF(SUM(AZ21:BB21)=0,"",SUM(AZ21:BB21)) -> 18 | BE21: =IFERROR((F21/2*BB21)+(AZ21*F21),"") -> 1980 | BF21: =_xlfn.XLOOKUP(B21,'TAREO HORAS EXTRAS'!$C$15:$C$51,'TAREO HORAS EXTRAS'!$AO$15:$AO$51,0) -> 0 | BG21: =IFERROR((F21/8*BF21),"") -> 0 | BQ21: =BJ21+BL21+BN21+BP21 -> 0 | BS21: =IF(CB21=$CF$9,(E21*$CG$9/2),IF(CB21=$CF$11,(E21*$CG$11/2),0)) -> 148.5 | BT21: =IF(CB21=$CF$9,(E21*$CJ$9/2),IF(CB21=$CF$11,(E21*$CJ$9/2),0)) -> 33 | BU21: =IF(CB21=$CF$9,(E21*$CG$9/2),IF(CB21=$CF$11,(E21*$CG$11/2),0)) -> 148.5 | BV21: =IF(CB21=$CF$9,(E21*$CJ$9/2),IF(CB21=$CF$11,(E21*$CJ$9/2),0)) -> 33 | BW21: =SUM(BS21:BV21) -> 363 | BY21: =BQ21+BW21 -> 363 | CA21: =IFERROR((BE21-BW21),0) -> 1617 | CB21: ONP
B22: JEREMIAS PALOMINO, NORBERTO LEONCIO | D22: =IFERROR(VLOOKUP(B22,'DATOS GRALES 1'!$B$2:$E$91,4,0),"") -> PEON | E22: =IF(D22="",0,IF(D22="PEON",3300,4200)) -> 3300 | F22: =IFERROR((E22/30),"") -> 110 | H22: SI | I22: SI | J22: SI | K22: SI | L22: SI | M22: SI | N22: NO | O22: SI | P22: SI | Q22: SI | R22: SI | S22: SI | T22: NO | U22: SI | V22: SI | W22: SI | X22: SI | Y22: SI | AZ22: =IF(COUNTIF(H22:AX22,"SI")=0,"",COUNTIF(H22:AX22,"SI")) -> 16 | BA22: =IF(COUNTIF(H22:AX22,"NO")=0,"",COUNTIF(H22:AX22,"NO")) -> 2 | BB22: =COUNTIF(H22:AL22,"MED") -> 0 | BC22: =IF(SUM(AZ22:BB22)=0,"",SUM(AZ22:BB22)) -> 18 | BE22: =IFERROR((F22/2*BB22)+(AZ22*F22),"") -> 1760 | BF22: =_xlfn.XLOOKUP(B22,'TAREO HORAS EXTRAS'!$C$15:$C$51,'TAREO HORAS EXTRAS'!$AO$15:$AO$51,0) -> 0 | BG22: =IFERROR((F22/8*BF22),"") -> 0 | BQ22: =BJ22+BL22+BN22+BP22 -> 0 | BS22: =IF(CB22=$CF$9,(E22*$CG$9/2),IF(CB22=$CF$11,(E22*$CG$11/2),0)) -> 214.5 | BT22: =IF(CB22=$CF$9,(E22*$CJ$9/2),IF(CB22=$CF$11,(E22*$CJ$9/2),0)) -> 33 | BU22: =IF(CB22=$CF$9,(E22*$CG$9/2),IF(CB22=$CF$11,(E22*$CG$11/2),0)) -> 214.5 | BV22: =IF(CB22=$CF$9,(E22*$CJ$9/2),IF(CB22=$CF$11,(E22*$CJ$9/2),0)) -> 33 | BW22: =SUM(BS22:BV22) -> 495 | BY22: =BQ22+BW22 -> 495 | CA22: =IFERROR((BE22-BW22),0) -> 1265 | CB22: AFP
B23: LOZANO MALDONADO, HERNAN | D23: =IFERROR(VLOOKUP(B23,'DATOS GRALES 1'!$B$2:$E$91,4,0),"") -> PEON | E23: =IF(D23="",0,IF(D23="PEON",3300,4200)) -> 3300 | F23: =IFERROR((E23/30),"") -> 110 | H23: SI | I23: SI | J23: NO | K23: SI | L23: SI | M23: NO | N23: SI | O23: SI | P23: SI | Q23: SI | R23: SI | S23: SI | T23: SI | U23: SI | V23: SI | W23: SI | X23: SI | Y23: SI | AZ23: =IF(COUNTIF(H23:AX23,"SI")=0,"",COUNTIF(H23:AX23,"SI")) -> 16 | BA23: =IF(COUNTIF(H23:AX23,"NO")=0,"",COUNTIF(H23:AX23,"NO")) -> 2 | BB23: =COUNTIF(H23:AL23,"MED") -> 0 | BC23: =IF(SUM(AZ23:BB23)=0,"",SUM(AZ23:BB23)) -> 18 | BE23: =IFERROR((F23/2*BB23)+(AZ23*F23),"") -> 1760 | BF23: =_xlfn.XLOOKUP(B23,'TAREO HORAS EXTRAS'!$C$15:$C$51,'TAREO HORAS EXTRAS'!$AO$15:$AO$51,0) -> 7 | BG23: =IFERROR((F23/8*BF23),"") -> 96.25 | BQ23: =BJ23+BL23+BN23+BP23 -> 0 | BS23: =IF(CB23=$CF$9,(E23*$CG$9/2),IF(CB23=$CF$11,(E23*$CG$11/2),0)) -> 214.5 | BT23: =IF(CB23=$CF$9,(E23*$CJ$9/2),IF(CB23=$CF$11,(E23*$CJ$9/2),0)) -> 33 | BU23: =IF(CB23=$CF$9,(E23*$CG$9/2),IF(CB23=$CF$11,(E23*$CG$11/2),0)) -> 214.5 | BV23: =IF(CB23=$CF$9,(E23*$CJ$9/2),IF(CB23=$CF$11,(E23*$CJ$9/2),0)) -> 33 | BW23: =SUM(BS23:BV23) -> 495 | BY23: =BQ23+BW23 -> 495 | CA23: =IFERROR((BE23-BW23),0) -> 1265 | CB23: AFP
B24: PIÑA CHUJANDAMA, KEVIN | D24: =IFERROR(VLOOKUP(B24,'DATOS GRALES 1'!$B$2:$E$91,4,0),"") -> PEON | E24: =IF(D24="",0,IF(D24="PEON",3300,4200)) -> 3300 | F24: =IFERROR((E24/30),"") -> 110 | H24: SI | I24: SI | J24: NO | K24: SI | L24: SI | M24: NO | N24: SI | O24: SI | P24: SI | Q24: SI | R24: SI | S24: SI | T24: SI | U24: SI | V24: SI | W24: SI | X24: SI | Y24: SI | AZ24: =IF(COUNTIF(H24:AX24,"SI")=0,"",COUNTIF(H24:AX24,"SI")) -> 16 | BA24: =IF(COUNTIF(H24:AX24,"NO")=0,"",COUNTIF(H24:AX24,"NO")) -> 2 | BB24: =COUNTIF(H24:AL24,"MED") -> 0 | BC24: =IF(SUM(AZ24:BB24)=0,"",SUM(AZ24:BB24)) -> 18 | BE24: =IFERROR((F24/2*BB24)+(AZ24*F24),"") -> 1760 | BF24: =_xlfn.XLOOKUP(B24,'TAREO HORAS EXTRAS'!$C$15:$C$51,'TAREO HORAS EXTRAS'!$AO$15:$AO$51,0) -> 4 | BG24: =IFERROR((F24/8*BF24),"") -> 55 | BQ24: =BJ24+BL24+BN24+BP24 -> 0 | BS24: =IF(CB24=$CF$9,(E24*$CG$9/2),IF(CB24=$CF$11,(E24*$CG$11/2),0)) -> 214.5 | BT24: =IF(CB24=$CF$9,(E24*$CJ$9/2),IF(CB24=$CF$11,(E24*$CJ$9/2),0)) -> 33 | BU24: =IF(CB24=$CF$9,(E24*$CG$9/2),IF(CB24=$CF$11,(E24*$CG$11/2),0)) -> 214.5 | BV24: =IF(CB24=$CF$9,(E24*$CJ$9/2),IF(CB24=$CF$11,(E24*$CJ$9/2),0)) -> 33 | BW24: =SUM(BS24:BV24) -> 495 | BY24: =BQ24+BW24 -> 495 | CA24: =IFERROR((BE24-BW24),0) -> 1265 | CB24: AFP
B25: MAYTAHUARI ACOSTA, SAMMER AXEL | D25: =IFERROR(VLOOKUP(B25,'DATOS GRALES 1'!$B$2:$E$91,4,0),"") -> OPERARIO | E25: =IF(D25="",0,IF(D25="PEON",3300,4200)) -> 4200 | F25: =IFERROR((E25/30),"") -> 140 | H25: SI | I25: SI | J25: NO | K25: SI | L25: SI | M25: NO | N25: SI | O25: SI | P25: SI | Q25: SI | R25: SI | S25: SI | T25: SI | U25: SI | V25: SI | W25: SI | X25: SI | Y25: SI | AZ25: =IF(COUNTIF(H25:AX25,"SI")=0,"",COUNTIF(H25:AX25,"SI")) -> 16 | BA25: =IF(COUNTIF(H25:AX25,"NO")=0,"",COUNTIF(H25:AX25,"NO")) -> 2 | BB25: =COUNTIF(H25:AL25,"MED") -> 0 | BC25: =IF(SUM(AZ25:BB25)=0,"",SUM(AZ25:BB25)) -> 18 | BE25: =IFERROR((F25/2*BB25)+(AZ25*F25),"") -> 2240 | BF25: =_xlfn.XLOOKUP(B25,'TAREO HORAS EXTRAS'!$C$15:$C$51,'TAREO HORAS EXTRAS'!$AO$15:$AO$51,0) -> 0 | BG25: =IFERROR((F25/8*BF25),"") -> 0 | BQ25: =BJ25+BL25+BN25+BP25 -> 0 | BS25: =IF(CB25=$CF$9,(E25*$CG$9/2),IF(CB25=$CF$11,(E25*$CG$11/2),0)) -> 273 | BT25: =IF(CB25=$CF$9,(E25*$CJ$9/2),IF(CB25=$CF$11,(E25*$CJ$9/2),0)) -> 42 | BU25: =IF(CB25=$CF$9,(E25*$CG$9/2),IF(CB25=$CF$11,(E25*$CG$11/2),0)) -> 273 | BV25: =IF(CB25=$CF$9,(E25*$CJ$9/2),IF(CB25=$CF$11,(E25*$CJ$9/2),0)) -> 42 | BW25: =SUM(BS25:BV25) -> 630 | BY25: =BQ25+BW25 -> 630 | CA25: =IFERROR((BE25-BW25),0) -> 1610 | CB25: AFP
B26: CORDOVA ANGULO, JUAN | D26: =IFERROR(VLOOKUP(B26,'DATOS GRALES 1'!$B$2:$E$91,4,0),"") -> PEON | E26: =IF(D26="",0,IF(D26="PEON",3300,4200)) -> 3300 | F26: =IFERROR((E26/30),"") -> 110 | H26: SI | I26: SI | J26: SI | K26: SI | L26: SI | M26: SI | N26: SI | O26: SI | P26: SI | Q26: SI | R26: SI | S26: SI | T26: SI | U26: SI | V26: SI | W26: SI | X26: SI | Y26: SI | AZ26: =IF(COUNTIF(H26:AX26,"SI")=0,"",COUNTIF(H26:AX26,"SI")) -> 18 | BA26: =IF(COUNTIF(H26:AX26,"NO")=0,"",COUNTIF(H26:AX26,"NO")) | BB26: =COUNTIF(H26:AL26,"MED") -> 0 | BC26: =IF(SUM(AZ26:BB26)=0,"",SUM(AZ26:BB26)) -> 18 | BE26: =IFERROR((F26/2*BB26)+(AZ26*F26),"") -> 1980 | BF26: =_xlfn.XLOOKUP(B26,'TAREO HORAS EXTRAS'!$C$15:$C$51,'TAREO HORAS EXTRAS'!$AO$15:$AO$51,0) -> 0 | BG26: =IFERROR((F26/8*BF26),"") -> 0 | BQ26: =BJ26+BL26+BN26+BP26 -> 0 | BS26: =IF(CB26=$CF$9,(E26*$CG$9/2),IF(CB26=$CF$11,(E26*$CG$11/2),0)) -> 214.5 | BT26: =IF(CB26=$CF$9,(E26*$CJ$9/2),IF(CB26=$CF$11,(E26*$CJ$9/2),0)) -> 33 | BU26: =IF(CB26=$CF$9,(E26*$CG$9/2),IF(CB26=$CF$11,(E26*$CG$11/2),0)) -> 214.5 | BV26: =IF(CB26=$CF$9,(E26*$CJ$9/2),IF(CB26=$CF$11,(E26*$CJ$9/2),0)) -> 33 | BW26: =SUM(BS26:BV26) -> 495 | BY26: =BQ26+BW26 -> 495 | CA26: =IFERROR((BE26-BW26),0) -> 1485 | CB26: AFP
B27: ROJAS SANDOVAL, JAVIER ELOY | D27: =IFERROR(VLOOKUP(B27,'DATOS GRALES 1'!$B$2:$E$91,4,0),"") -> OPERARIO/VOLQUETERO | E27: =IF(D27="",0,IF(D27="PEON",3300,4200)) -> 4200 | F27: =IFERROR((E27/30),"") -> 140 | H27: SI | I27: NO | J27: NO | K27: NO | L27: NO | M27: NO | N27: NO | O27: NO | P27: NO | Q27: NO | R27: NO | S27: NO | T27: NO | U27: NO | V27: NO | W27: NO | X27: NO | Y27: NO | AZ27: =IF(COUNTIF(H27:AX27,"SI")=0,"",COUNTIF(H27:AX27,"SI")) -> 1 | BA27: =IF(COUNTIF(H27:AX27,"NO")=0,"",COUNTIF(H27:AX27,"NO")) -> 17 | BB27: =COUNTIF(H27:AL27,"MED") -> 0 | BC27: =IF(SUM(AZ27:BB27)=0,"",SUM(AZ27:BB27)) -> 18 | BE27: =IFERROR((F27/2*BB27)+(AZ27*F27),"") -> 140 | BF27: =_xlfn.XLOOKUP(B27,'TAREO HORAS EXTRAS'!$C$15:$C$51,'TAREO HORAS EXTRAS'!$AO$15:$AO$51,0) -> 0 | BG27: =IFERROR((F27/8*BF27),"") -> 0 | BQ27: =BJ27+BL27+BN27+BP27 -> 0 | BS27: =IF(CB27=$CF$9,(E27*$CG$9/2),IF(CB27=$CF$11,(E27*$CG$11/2),0)) -> 273 | BT27: =IF(CB27=$CF$9,(E27*$CJ$9/2),IF(CB27=$CF$11,(E27*$CJ$9/2),0)) -> 42 | BU27: =IF(CB27=$CF$9,(E27*$CG$9/2),IF(CB27=$CF$11,(E27*$CG$11/2),0)) -> 273 | BV27: =IF(CB27=$CF$9,(E27*$CJ$9/2),IF(CB27=$CF$11,(E27*$CJ$9/2),0)) -> 42 | BW27: =SUM(BS27:BV27) -> 630 | BY27: =BQ27+BW27 -> 630 | CA27: =IFERROR((BE27-BW27),0) -> -490 | CB27: AFP
B28: CHACON ORTIZ, JOSE ANTONIO | D28: =IFERROR(VLOOKUP(B28,'DATOS GRALES 1'!$B$2:$E$91,4,0),"") -> OPERARIO | E28: =IF(D28="",0,IF(D28="PEON",3300,4200)) -> 4200 | F28: =IFERROR((E28/30),"") -> 140 | H28: SI | I28: SI | J28: SI | K28: SI | L28: SI | M28: SI | N28: SI | O28: SI | P28: SI | Q28: SI | R28: SI | S28: SI | T28: SI | U28: SI | V28: SI | W28: SI | X28: SI | Y28: SI | AZ28: =IF(COUNTIF(H28:AX28,"SI")=0,"",COUNTIF(H28:AX28,"SI")) -> 18 | BA28: =IF(COUNTIF(H28:AX28,"NO")=0,"",COUNTIF(H28:AX28,"NO")) | BB28: =COUNTIF(H28:AL28,"MED") -> 0 | BC28: =IF(SUM(AZ28:BB28)=0,"",SUM(AZ28:BB28)) -> 18 | BE28: =IFERROR((F28/2*BB28)+(AZ28*F28),"") -> 2520 | BF28: =_xlfn.XLOOKUP(B28,'TAREO HORAS EXTRAS'!$C$15:$C$51,'TAREO HORAS EXTRAS'!$AO$15:$AO$51,0) -> 0 | BG28: =IFERROR((F28/8*BF28),"") -> 0 | BQ28: =BJ28+BL28+BN28+BP28 -> 0 | BS28: =IF(CB28=$CF$9,(E28*$CG$9/2),IF(CB28=$CF$11,(E28*$CG$11/2),0)) -> 273 | BT28: =IF(CB28=$CF$9,(E28*$CJ$9/2),IF(CB28=$CF$11,(E28*$CJ$9/2),0)) -> 42 | BU28: =IF(CB28=$CF$9,(E28*$CG$9/2),IF(CB28=$CF$11,(E28*$CG$11/2),0)) -> 273 | BV28: =IF(CB28=$CF$9,(E28*$CJ$9/2),IF(CB28=$CF$11,(E28*$CJ$9/2),0)) -> 42 | BW28: =SUM(BS28:BV28) -> 630 | BY28: =BQ28+BW28 -> 630 | CA28: =IFERROR((BE28-BW28),0) -> 1890 | CB28: AFP
B29: ORDOÑEZ CONDORI, GILBERTO | D29: =IFERROR(VLOOKUP(B29,'DATOS GRALES 1'!$B$2:$E$91,4,0),"") -> PEON | E29: =IF(D29="",0,IF(D29="PEON",3300,4200)) -> 3300 | F29: =IFERROR((E29/30),"") -> 110 | H29: SI | I29: SI | J29: SI | K29: SI | L29: SI | M29: SI | N29: SI | O29: SI | P29: SI | Q29: SI | R29: SI | S29: SI | T29: SI | U29: SI | V29: SI | W29: SI | X29: SI | Y29: SI | AZ29: =IF(COUNTIF(H29:AX29,"SI")=0,"",COUNTIF(H29:AX29,"SI")) -> 18 | BA29: =IF(COUNTIF(H29:AX29,"NO")=0,"",COUNTIF(H29:AX29,"NO")) | BB29: =COUNTIF(H29:AL29,"MED") -> 0 | BC29: =IF(SUM(AZ29:BB29)=0,"",SUM(AZ29:BB29)) -> 18 | BE29: =IFERROR((F29/2*BB29)+(AZ29*F29),"") -> 1980 | BF29: =_xlfn.XLOOKUP(B29,'TAREO HORAS EXTRAS'!$C$15:$C$51,'TAREO HORAS EXTRAS'!$AO$15:$AO$51,0) -> 0 | BG29: =IFERROR((F29/8*BF29),"") -> 0 | BQ29: =BJ29+BL29+BN29+BP29 -> 0 | BS29: =IF(CB29=$CF$9,(E29*$CG$9/2),IF(CB29=$CF$11,(E29*$CG$11/2),0)) -> 214.5 | BT29: =IF(CB29=$CF$9,(E29*$CJ$9/2),IF(CB29=$CF$11,(E29*$CJ$9/2),0)) -> 33 | BU29: =IF(CB29=$CF$9,(E29*$CG$9/2),IF(CB29=$CF$11,(E29*$CG$11/2),0)) -> 214.5 | BV29: =IF(CB29=$CF$9,(E29*$CJ$9/2),IF(CB29=$CF$11,(E29*$CJ$9/2),0)) -> 33 | BW29: =SUM(BS29:BV29) -> 495 | BY29: =BQ29+BW29 -> 495 | CA29: =IFERROR((BE29-BW29),0) -> 1485 | CB29: AFP
B30: GUTARATE SABINO, ADRIEL ANTONY | D30: =IFERROR(VLOOKUP(B30,'DATOS GRALES 1'!$B$2:$E$91,4,0),"") -> OPERARIO | E30: =IF(D30="",0,IF(D30="PEON",3300,4200)) -> 4200 | F30: =IFERROR((E30/30),"") -> 140 | H30: SI | I30: SI | J30: SI | K30: SI | L30: SI | M30: SI | N30: MED | O30: SI | P30: SI | Q30: SI | R30: SI | S30: SI | T30: SI | U30: SI | V30: SI | W30: SI | X30: SI | Y30: SI | AZ30: =IF(COUNTIF(H30:AX30,"SI")=0,"",COUNTIF(H30:AX30,"SI")) -> 17 | BA30: =IF(COUNTIF(H30:AX30,"NO")=0,"",COUNTIF(H30:AX30,"NO")) | BB30: =COUNTIF(H30:AL30,"MED") -> 1 | BC30: =IF(SUM(AZ30:BB30)=0,"",SUM(AZ30:BB30)) -> 18 | BE30: =IFERROR((F30/2*BB30)+(AZ30*F30),"") -> 2450 | BF30: =_xlfn.XLOOKUP(B30,'TAREO HORAS EXTRAS'!$C$15:$C$51,'TAREO HORAS EXTRAS'!$AO$15:$AO$51,0) -> 0 | BG30: =IFERROR((F30/8*BF30),"") -> 0 | BQ30: =BJ30+BL30+BN30+BP30 -> 0 | BS30: =IF(CB30=$CF$9,(E30*$CG$9/2),IF(CB30=$CF$11,(E30*$CG$11/2),0)) -> 273 | BT30: =IF(CB30=$CF$9,(E30*$CJ$9/2),IF(CB30=$CF$11,(E30*$CJ$9/2),0)) -> 42 | BU30: =IF(CB30=$CF$9,(E30*$CG$9/2),IF(CB30=$CF$11,(E30*$CG$11/2),0)) -> 273 | BV30: =IF(CB30=$CF$9,(E30*$CJ$9/2),IF(CB30=$CF$11,(E30*$CJ$9/2),0)) -> 42 | BW30: =SUM(BS30:BV30) -> 630 | BY30: =BQ30+BW30 -> 630 | CA30: =IFERROR((BE30-BW30),0) -> 1820 | CB30: AFP
B31: QUISPE LIMACHE, ROGELIO | D31: =IFERROR(VLOOKUP(B31,'DATOS GRALES 1'!$B$2:$E$91,4,0),"") -> OPERARIO | E31: =IF(D31="",0,IF(D31="PEON",3300,4200)) -> 4200 | F31: =IFERROR((E31/30),"") -> 140 | H31: SI | I31: SI | J31: NO | K31: NO | L31: NO | M31: NO | N31: NO | O31: NO | P31: NO | Q31: NO | R31: NO | S31: NO | T31: NO | U31: NO | V31: NO | W31: NO | X31: NO | Y31: NO | AZ31: =IF(COUNTIF(H31:AX31,"SI")=0,"",COUNTIF(H31:AX31,"SI")) -> 2 | BA31: =IF(COUNTIF(H31:AX31,"NO")=0,"",COUNTIF(H31:AX31,"NO")) -> 16 | BB31: =COUNTIF(H31:AL31,"MED") -> 0 | BC31: =IF(SUM(AZ31:BB31)=0,"",SUM(AZ31:BB31)) -> 18 | BE31: =IFERROR((F31/2*BB31)+(AZ31*F31),"") -> 280 | BF31: =_xlfn.XLOOKUP(B31,'TAREO HORAS EXTRAS'!$C$15:$C$51,'TAREO HORAS EXTRAS'!$AO$15:$AO$51,0) -> 4 | BG31: =IFERROR((F31/8*BF31),"") -> 70 | BQ31: =BJ31+BL31+BN31+BP31 -> 0 | BS31: =IF(CB31=$CF$9,(E31*$CG$9/2),IF(CB31=$CF$11,(E31*$CG$11/2),0)) -> 273 | BT31: =IF(CB31=$CF$9,(E31*$CJ$9/2),IF(CB31=$CF$11,(E31*$CJ$9/2),0)) -> 42 | BU31: =IF(CB31=$CF$9,(E31*$CG$9/2),IF(CB31=$CF$11,(E31*$CG$11/2),0)) -> 273 | BV31: =IF(CB31=$CF$9,(E31*$CJ$9/2),IF(CB31=$CF$11,(E31*$CJ$9/2),0)) -> 42 | BW31: =SUM(BS31:BV31) -> 630 | BY31: =BQ31+BW31 -> 630 | CA31: =IFERROR((BE31-BW31),0) -> -350 | CB31: AFP
B32: APASTEGUI GRANDEZ, LUIS ALFREDO | D32: =IFERROR(VLOOKUP(B32,'DATOS GRALES 1'!$B$2:$E$91,4,0),"") -> PEON | E32: =IF(D32="",0,IF(D32="PEON",3300,4200)) -> 3300 | F32: =IFERROR((E32/30),"") -> 110 | H32: SI | I32: SI | J32: SI | K32: SI | L32: SI | M32: SI | N32: NO | O32: NO | P32: NO | Q32: NO | R32: NO | S32: NO | T32: NO | U32: NO | V32: NO | W32: NO | X32: NO | Y32: NO | AZ32: =IF(COUNTIF(H32:AX32,"SI")=0,"",COUNTIF(H32:AX32,"SI")) -> 6 | BA32: =IF(COUNTIF(H32:AX32,"NO")=0,"",COUNTIF(H32:AX32,"NO")) -> 12 | BB32: =COUNTIF(H32:AL32,"MED") -> 0 | BC32: =IF(SUM(AZ32:BB32)=0,"",SUM(AZ32:BB32)) -> 18 | BE32: =IFERROR((F32/2*BB32)+(AZ32*F32),"") -> 660 | BF32: =_xlfn.XLOOKUP(B32,'TAREO HORAS EXTRAS'!$C$15:$C$51,'TAREO HORAS EXTRAS'!$AO$15:$AO$51,0) -> 0 | BG32: =IFERROR((F32/8*BF32),"") -> 0 | BQ32: =BJ32+BL32+BN32+BP32 -> 0 | BS32: =IF(CB32=$CF$9,(E32*$CG$9/2),IF(CB32=$CF$11,(E32*$CG$11/2),0)) -> 214.5 | BT32: =IF(CB32=$CF$9,(E32*$CJ$9/2),IF(CB32=$CF$11,(E32*$CJ$9/2),0)) -> 33 | BU32: =IF(CB32=$CF$9,(E32*$CG$9/2),IF(CB32=$CF$11,(E32*$CG$11/2),0)) -> 214.5 | BV32: =IF(CB32=$CF$9,(E32*$CJ$9/2),IF(CB32=$CF$11,(E32*$CJ$9/2),0)) -> 33 | BW32: =SUM(BS32:BV32) -> 495 | BY32: =BQ32+BW32 -> 495 | CA32: =IFERROR((BE32-BW32),0) -> 165 | CB32: AFP
... B35: TACANAHUI CALISAYA NESTOR | D35: =IFERROR(VLOOKUP(B35,'DATOS GRALES 1'!$B$2:$E$91,4,0),"") -> PEÓN | E35: =IF(D35="",0,IF(D35="PEON",3300,4200)) -> 4200 | F35: =IFERROR((E35/30),"") -> 140 | H35: SI | I35: SI | J35: SI | K35: SI | L35: SI | M35: SI | N35: SI | O35: SI | P35: SI | Q35: SI | R35: SI | S35: SI | T35: SI | U35: SI | V35: SI | W35: SI | X35: SI | Y35: SI | AZ35: =IF(COUNTIF(H35:AX35,"SI")=0,"",COUNTIF(H35:AX35,"SI")) -> 18 | BA35: =IF(COUNTIF(H35:AX35,"NO")=0,"",COUNTIF(H35:AX35,"NO")) | BB35: =COUNTIF(H35:AL35,"MED") -> 0 | BC35: =IF(SUM(AZ35:BB35)=0,"",SUM(AZ35:BB35)) -> 18 | BE35: =IFERROR((F35/2*BB35)+(AZ35*F35),"") -> 2520 | BF35: =_xlfn.XLOOKUP(B35,'TAREO HORAS EXTRAS'!$C$15:$C$51,'TAREO HORAS EXTRAS'!$AO$15:$AO$51,0) -> 7 | BG35: =IFERROR((F35/8*BF35),"") -> 122.5 | BQ35: =BJ35+BL35+BN35+BP35 -> 0 | BS35: =IF(CB35=$CF$9,(E35*$CG$9/2),IF(CB35=$CF$11,(E35*$CG$11/2),0)) -> 273 | BT35: =IF(CB35=$CF$9,(E35*$CJ$9/2),IF(CB35=$CF$11,(E35*$CJ$9/2),0)) -> 42 | BU35: =IF(CB35=$CF$9,(E35*$CG$9/2),IF(CB35=$CF$11,(E35*$CG$11/2),0)) -> 273 | BV35: =IF(CB35=$CF$9,(E35*$CJ$9/2),IF(CB35=$CF$11,(E35*$CJ$9/2),0)) -> 42 | BW35: =SUM(BS35:BV35) -> 630 | BY35: =BQ35+BW35 -> 630 | CA35: =IFERROR((BE35-BW35),0) -> 1890 | CB35: AFP
B36: ROSAS CHACHAJE, WILSON JHONY | D36: PEON | E36: =IF(D36="",0,IF(D36="PEON",3300,4200)) -> 3300 | F36: =IFERROR((E36/30),"") -> 110 | H36: SI | I36: SI | J36: SI | K36: SI | L36: SI | M36: SI | N36: SI | O36: SI | P36: SI | Q36: SI | R36: SI | S36: SI | T36: SI | U36: SI | V36: SI | W36: SI | X36: SI | Y36: SI | AZ36: =IF(COUNTIF(H36:AX36,"SI")=0,"",COUNTIF(H36:AX36,"SI")) -> 18 | BA36: =IF(COUNTIF(H36:AX36,"NO")=0,"",COUNTIF(H36:AX36,"NO")) | BB36: =COUNTIF(H36:AL36,"MED") -> 0 | BC36: =IF(SUM(AZ36:BB36)=0,"",SUM(AZ36:BB36)) -> 18 | BE36: =IFERROR((F36/2*BB36)+(AZ36*F36),"") -> 1980 | BF36: =_xlfn.XLOOKUP(B36,'TAREO HORAS EXTRAS'!$C$15:$C$51,'TAREO HORAS EXTRAS'!$AO$15:$AO$51,0) -> 6 | BG36: =IFERROR((F36/8*BF36),"") -> 82.5 | BQ36: =BJ36+BL36+BN36+BP36 -> 0 | BS36: =IF(CB36=$CF$9,(E36*$CG$9/2),IF(CB36=$CF$11,(E36*$CG$11/2),0)) -> 214.5 | BT36: =IF(CB36=$CF$9,(E36*$CJ$9/2),IF(CB36=$CF$11,(E36*$CJ$9/2),0)) -> 33 | BU36: =IF(CB36=$CF$9,(E36*$CG$9/2),IF(CB36=$CF$11,(E36*$CG$11/2),0)) -> 214.5 | BV36: =IF(CB36=$CF$9,(E36*$CJ$9/2),IF(CB36=$CF$11,(E36*$CJ$9/2),0)) -> 33 | BW36: =SUM(BS36:BV36) -> 495 | BY36: =BQ36+BW36 -> 495 | CA36: =IFERROR((BE36-BW36),0) -> 1485 | CB36: AFP
B37: GAMARRA CONDORI, ANGEL | D37: PEON | E37: =IF(D37="",0,IF(D37="PEON",3300,4200)) -> 3300 | F37: =IFERROR((E37/30),"") -> 110 | H37: SI | I37: SI | J37: SI | K37: SI | L37: SI | M37: SI | N37: SI | O37: SI | P37: SI | Q37: SI | R37: SI | S37: SI | T37: SI | U37: SI | V37: SI | W37: SI | X37: SI | Y37: SI | AZ37: =IF(COUNTIF(H37:AX37,"SI")=0,"",COUNTIF(H37:AX37,"SI")) -> 18 | BA37: =IF(COUNTIF(H37:AX37,"NO")=0,"",COUNTIF(H37:AX37,"NO")) | BB37: =COUNTIF(H37:AL37,"MED") -> 0 | BC37: =IF(SUM(AZ37:BB37)=0,"",SUM(AZ37:BB37)) -> 18 | BE37: =IFERROR((F37/2*BB37)+(AZ37*F37),"") -> 1980 | BF37: =_xlfn.XLOOKUP(B37,'TAREO HORAS EXTRAS'!$C$15:$C$51,'TAREO HORAS EXTRAS'!$AO$15:$AO$51,0) -> 2 | BG37: =IFERROR((F37/8*BF37),"") -> 27.5 | BQ37: =BJ37+BL37+BN37+BP37 -> 0 | BS37: =IF(CB37=$CF$9,(E37*$CG$9/2),IF(CB37=$CF$11,(E37*$CG$11/2),0)) -> 214.5 | BT37: =IF(CB37=$CF$9,(E37*$CJ$9/2),IF(CB37=$CF$11,(E37*$CJ$9/2),0)) -> 33 | BU37: =IF(CB37=$CF$9,(E37*$CG$9/2),IF(CB37=$CF$11,(E37*$CG$11/2),0)) -> 214.5 | BV37: =IF(CB37=$CF$9,(E37*$CJ$9/2),IF(CB37=$CF$11,(E37*$CJ$9/2),0)) -> 33 | BW37: =SUM(BS37:BV37) -> 495 | BY37: =BQ37+BW37 -> 495 | CA37: =IFERROR((BE37-BW37),0) -> 1485 | CB37: AFP
B38: QUISPE MAQUERA, MARCO ANTONIO | D38: =IFERROR(VLOOKUP(B38,'DATOS GRALES 1'!$B$2:$E$91,4,0),"") -> PEON | E38: =IF(D38="",0,IF(D38="PEON",3300,4200)) -> 3300 | F38: =IFERROR((E38/30),"") -> 110 | H38: SI | I38: SI | J38: SI | K38: SI | L38: SI | M38: SI | N38: NO | O38: NO | P38: NO | Q38: NO | R38: NO | S38: NO | T38: NO | U38: NO | V38: NO | W38: NO | X38: NO | Y38: NO | AZ38: =IF(COUNTIF(H38:AX38,"SI")=0,"",COUNTIF(H38:AX38,"SI")) -> 6 | BA38: =IF(COUNTIF(H38:AX38,"NO")=0,"",COUNTIF(H38:AX38,"NO")) -> 12 | BB38: =COUNTIF(H38:AL38,"MED") -> 0 | BC38: =IF(SUM(AZ38:BB38)=0,"",SUM(AZ38:BB38)) -> 18 | BE38: =IFERROR((F38/2*BB38)+(AZ38*F38),"") -> 660 | BF38: =_xlfn.XLOOKUP(B38,'TAREO HORAS EXTRAS'!$C$15:$C$51,'TAREO HORAS EXTRAS'!$AO$15:$AO$51,0) -> 0 | BG38: =IFERROR((F38/8*BF38),"") -> 0 | BQ38: =BJ38+BL38+BN38+BP38 -> 0 | BS38: =IF(CB38=$CF$9,(E38*$CG$9/2),IF(CB38=$CF$11,(E38*$CG$11/2),0)) -> 214.5 | BT38: =IF(CB38=$CF$9,(E38*$CJ$9/2),IF(CB38=$CF$11,(E38*$CJ$9/2),0)) -> 33 | BU38: =IF(CB38=$CF$9,(E38*$CG$9/2),IF(CB38=$CF$11,(E38*$CG$11/2),0)) -> 214.5 | BV38: =IF(CB38=$CF$9,(E38*$CJ$9/2),IF(CB38=$CF$11,(E38*$CJ$9/2),0)) -> 33 | BW38: =SUM(BS38:BV38) -> 495 | BY38: =BQ38+BW38 -> 495 | CA38: =IFERROR((BE38-BW38),0) -> 165 | CB38: AFP
B39: PUMAYALLI LICONA, ENOCH | D39: =IFERROR(VLOOKUP(B39,'DATOS GRALES 1'!$B$2:$E$91,4,0),"") -> PEON | E39: =IF(D39="",0,IF(D39="PEON",3300,4200)) -> 3300 | F39: =IFERROR((E39/30),"") -> 110 | H39: SI | I39: SI | J39: SI | K39: SI | L39: SI | M39: SI | N39: SI | O39: SI | P39: SI | Q39: SI | R39: SI | S39: SI | T39: SI | U39: SI | V39: SI | W39: SI | X39: SI | Y39: SI | AZ39: =IF(COUNTIF(H39:AX39,"SI")=0,"",COUNTIF(H39:AX39,"SI")) -> 18 | BA39: =IF(COUNTIF(H39:AX39,"NO")=0,"",COUNTIF(H39:AX39,"NO")) | BB39: =COUNTIF(H39:AL39,"MED") -> 0 | BC39: =IF(SUM(AZ39:BB39)=0,"",SUM(AZ39:BB39)) -> 18 | BE39: =IFERROR((F39/2*BB39)+(AZ39*F39),"") -> 1980 | BF39: =_xlfn.XLOOKUP(B39,'TAREO HORAS EXTRAS'!$C$15:$C$51,'TAREO HORAS EXTRAS'!$AO$15:$AO$51,0) -> 3 | BG39: =IFERROR((F39/8*BF39),"") -> 41.25 | BQ39: =BJ39+BL39+BN39+BP39 -> 0 | BS39: =IF(CB39=$CF$9,(E39*$CG$9/2),IF(CB39=$CF$11,(E39*$CG$11/2),0)) -> 214.5 | BT39: =IF(CB39=$CF$9,(E39*$CJ$9/2),IF(CB39=$CF$11,(E39*$CJ$9/2),0)) -> 33 | BU39: =IF(CB39=$CF$9,(E39*$CG$9/2),IF(CB39=$CF$11,(E39*$CG$11/2),0)) -> 214.5 | BV39: =IF(CB39=$CF$9,(E39*$CJ$9/2),IF(CB39=$CF$11,(E39*$CJ$9/2),0)) -> 33 | BW39: =SUM(BS39:BV39) -> 495 | BY39: =BQ39+BW39 -> 495 | CA39: =IFERROR((BE39-BW39),0) -> 1485 | CB39: AFP
B40: CURMAYARI MANUYAMA, VICTOR RAUL | D40: =IFERROR(VLOOKUP(B40,'DATOS GRALES 1'!$B$2:$E$91,4,0),"") -> OPERARIO | E40: =IF(D40="",0,IF(D40="PEON",3300,4200)) -> 4200 | F40: =IFERROR((E40/30),"") -> 140 | H40: SI | I40: SI | J40: SI | K40: SI | L40: SI | M40: SI | N40: SI | O40: SI | P40: SI | Q40: SI | R40: SI | S40: SI | T40: SI | U40: SI | V40: SI | W40: SI | X40: SI | Y40: SI | AZ40: =IF(COUNTIF(H40:AX40,"SI")=0,"",COUNTIF(H40:AX40,"SI")) -> 18 | BA40: =IF(COUNTIF(H40:AX40,"NO")=0,"",COUNTIF(H40:AX40,"NO")) | BB40: =COUNTIF(H40:AL40,"MED") -> 0 | BC40: =IF(SUM(AZ40:BB40)=0,"",SUM(AZ40:BB40)) -> 18 | BE40: =IFERROR((F40/2*BB40)+(AZ40*F40),"") -> 2520 | BF40: =_xlfn.XLOOKUP(B40,'TAREO HORAS EXTRAS'!$C$15:$C$51,'TAREO HORAS EXTRAS'!$AO$15:$AO$51,0) -> 2 | BG40: =IFERROR((F40/8*BF40),"") -> 35 | BQ40: =BJ40+BL40+BN40+BP40 -> 0 | BS40: =IF(CB40=$CF$9,(E40*$CG$9/2),IF(CB40=$CF$11,(E40*$CG$11/2),0)) -> 273 | BT40: =IF(CB40=$CF$9,(E40*$CJ$9/2),IF(CB40=$CF$11,(E40*$CJ$9/2),0)) -> 42 | BU40: =IF(CB40=$CF$9,(E40*$CG$9/2),IF(CB40=$CF$11,(E40*$CG$11/2),0)) -> 273 | BV40: =IF(CB40=$CF$9,(E40*$CJ$9/2),IF(CB40=$CF$11,(E40*$CJ$9/2),0)) -> 42 | BW40: =SUM(BS40:BV40) -> 630 | BY40: =BQ40+BW40 -> 630 | CA40: =IFERROR((BE40-BW40),0) -> 1890 | CB40: AFP
B41: CURMAYARI GUZMAN, JOFFRE | D41: =IFERROR(VLOOKUP(B41,'DATOS GRALES 1'!$B$2:$E$91,4,0),"") -> OPERARIO | E41: =IF(D41="",0,IF(D41="PEON",3300,4200)) -> 4200 | F41: =IFERROR((E41/30),"") -> 140 | H41: SI | I41: SI | J41: NO | K41: NO | L41: SI | M41: NO | N41: SI | O41: SI | P41: SI | Q41: SI | R41: SI | S41: SI | T41: SI | U41: SI | V41: SI | W41: SI | X41: SI | Y41: SI | AZ41: =IF(COUNTIF(H41:AX41,"SI")=0,"",COUNTIF(H41:AX41,"SI")) -> 15 | BA41: =IF(COUNTIF(H41:AX41,"NO")=0,"",COUNTIF(H41:AX41,"NO")) -> 3 | BB41: =COUNTIF(H41:AL41,"MED") -> 0 | BC41: =IF(SUM(AZ41:BB41)=0,"",SUM(AZ41:BB41)) -> 18 | BE41: =IFERROR((F41/2*BB41)+(AZ41*F41),"") -> 2100 | BF41: =_xlfn.XLOOKUP(B41,'TAREO HORAS EXTRAS'!$C$15:$C$51,'TAREO HORAS EXTRAS'!$AO$15:$AO$51,0) -> 4 | BG41: =IFERROR((F41/8*BF41),"") -> 70 | BQ41: =BJ41+BL41+BN41+BP41 -> 0 | BS41: =IF(CB41=$CF$9,(E41*$CG$9/2),IF(CB41=$CF$11,(E41*$CG$11/2),0)) -> 273 | BT41: =IF(CB41=$CF$9,(E41*$CJ$9/2),IF(CB41=$CF$11,(E41*$CJ$9/2),0)) -> 42 | BU41: =IF(CB41=$CF$9,(E41*$CG$9/2),IF(CB41=$CF$11,(E41*$CG$11/2),0)) -> 273 | BV41: =IF(CB41=$CF$9,(E41*$CJ$9/2),IF(CB41=$CF$11,(E41*$CJ$9/2),0)) -> 42 | BW41: =SUM(BS41:BV41) -> 630 | BY41: =BQ41+BW41 -> 630 | CA41: =IFERROR((BE41-BW41),0) -> 1470 | CB41: AFP
B42: OLIVA TARAPA, TOMAS | D42: =IFERROR(VLOOKUP(B42,'DATOS GRALES 1'!$B$2:$E$91,4,0),"") -> PEON | E42: =IF(D42="",0,IF(D42="PEON",3300,4200)) -> 3300 | F42: =IFERROR((E42/30),"") -> 110 | H42: SI | I42: SI | J42: SI | K42: SI | L42: SI | M42: SI | N42: SI | O42: SI | P42: SI | Q42: SI | R42: SI | S42: SI | T42: SI | U42: SI | V42: SI | W42: SI | X42: SI | Y42: SI | AZ42: =IF(COUNTIF(H42:AX42,"SI")=0,"",COUNTIF(H42:AX42,"SI")) -> 18 | BA42: =IF(COUNTIF(H42:AX42,"NO")=0,"",COUNTIF(H42:AX42,"NO")) | BB42: =COUNTIF(H42:AL42,"MED") -> 0 | BC42: =IF(SUM(AZ42:BB42)=0,"",SUM(AZ42:BB42)) -> 18 | BE42: =IFERROR((F42/2*BB42)+(AZ42*F42),"") -> 1980 | BF42: =_xlfn.XLOOKUP(B42,'TAREO HORAS EXTRAS'!$C$15:$C$51,'TAREO HORAS EXTRAS'!$AO$15:$AO$51,0) -> 3 | BG42: =IFERROR((F42/8*BF42),"") -> 41.25 | BQ42: =BJ42+BL42+BN42+BP42 -> 0 | BS42: =IF(CB42=$CF$9,(E42*$CG$9/2),IF(CB42=$CF$11,(E42*$CG$11/2),0)) -> 214.5 | BT42: =IF(CB42=$CF$9,(E42*$CJ$9/2),IF(CB42=$CF$11,(E42*$CJ$9/2),0)) -> 33 | BU42: =IF(CB42=$CF$9,(E42*$CG$9/2),IF(CB42=$CF$11,(E42*$CG$11/2),0)) -> 214.5 | BV42: =IF(CB42=$CF$9,(E42*$CJ$9/2),IF(CB42=$CF$11,(E42*$CJ$9/2),0)) -> 33 | BW42: =SUM(BS42:BV42) -> 495 | BY42: =BQ42+BW42 -> 495 | CA42: =IFERROR((BE42-BW42),0) -> 1485 | CB42: AFP
B43: MACHUCA NAVARRO, OMAR JIAN FRANCO | D43: =IFERROR(VLOOKUP(B43,'DATOS GRALES 1'!$B$2:$E$91,4,0),"") -> PEON | E43: =IF(D43="",0,IF(D43="PEON",3300,4200)) -> 3300 | F43: =IFERROR((E43/30),"") -> 110 | H43: SI | I43: SI | J43: SI | K43: SI | L43: SI | M43: SI | N43: SI | O43: SI | P43: SI | Q43: SI | R43: SI | S43: SI | T43: SI | U43: NO | V43: NO | W43: SI | X43: SI | Y43: SI | AA43: NO | AN43: SI | AZ43: =IF(COUNTIF(H43:AX43,"SI")=0,"",COUNTIF(H43:AX43,"SI")) -> 17 | BA43: =IF(COUNTIF(H43:AX43,"NO")=0,"",COUNTIF(H43:AX43,"NO")) -> 3 | BB43: =COUNTIF(H43:AL43,"MED") -> 0 | BC43: =IF(SUM(AZ43:BB43)=0,"",SUM(AZ43:BB43)) -> 20 | BE43: =IFERROR((F43/2*BB43)+(AZ43*F43),"") -> 1870 | BF43: =_xlfn.XLOOKUP(B43,'TAREO HORAS EXTRAS'!$C$15:$C$51,'TAREO HORAS EXTRAS'!$AO$15:$AO$51,0) -> 3 | BG43: =IFERROR((F43/8*BF43),"") -> 41.25 | BQ43: =BJ43+BL43+BN43+BP43 -> 0 | BS43: =IF(CB43=$CF$9,(E43*$CG$9/2),IF(CB43=$CF$11,(E43*$CG$11/2),0)) -> 214.5 | BT43: =IF(CB43=$CF$9,(E43*$CJ$9/2),IF(CB43=$CF$11,(E43*$CJ$9/2),0)) -> 33 | BU43: =IF(CB43=$CF$9,(E43*$CG$9/2),IF(CB43=$CF$11,(E43*$CG$11/2),0)) -> 214.5 | BV43: =IF(CB43=$CF$9,(E43*$CJ$9/2),IF(CB43=$CF$11,(E43*$CJ$9/2),0)) -> 33 | BW43: =SUM(BS43:BV43) -> 495 | BY43: =BQ43+BW43 -> 495 | CA43: =IFERROR((BE43-BW43),0) -> 1375 | CB43: AFP
B44: ESCOBAR ARBILDO, GOLBER | D44: =IFERROR(VLOOKUP(B44,'DATOS GRALES 1'!$B$2:$E$91,4,0),"") -> PEON | E44: =IF(D44="",0,IF(D44="PEON",3300,4200)) -> 3300 | F44: =IFERROR((E44/30),"") -> 110 | H44: SI | I44: SI | J44: SI | K44: SI | L44: SI | M44: SI | N44: SI | O44: SI | P44: SI | Q44: SI | R44: SI | S44: SI | T44: SI | U44: SI | V44: SI | W44: SI | X44: SI | Y44: SI | AZ44: =IF(COUNTIF(H44:AX44,"SI")=0,"",COUNTIF(H44:AX44,"SI")) -> 18 | BA44: =IF(COUNTIF(H44:AX44,"NO")=0,"",COUNTIF(H44:AX44,"NO")) | BB44: =COUNTIF(H44:AL44,"MED") -> 0 | BC44: =IF(SUM(AZ44:BB44)=0,"",SUM(AZ44:BB44)) -> 18 | BE44: =IFERROR((F44/2*BB44)+(AZ44*F44),"") -> 1980 | BF44: =_xlfn.XLOOKUP(B44,'TAREO HORAS EXTRAS'!$C$15:$C$51,'TAREO HORAS EXTRAS'!$AO$15:$AO$51,0) -> 3 | BG44: =IFERROR((F44/8*BF44),"") -> 41.25 | BQ44: =BJ44+BL44+BN44+BP44 -> 0 | BS44: =IF(CB44=$CF$9,(E44*$CG$9/2),IF(CB44=$CF$11,(E44*$CG$11/2),0)) -> 214.5 | BT44: =IF(CB44=$CF$9,(E44*$CJ$9/2),IF(CB44=$CF$11,(E44*$CJ$9/2),0)) -> 33 | BU44: =IF(CB44=$CF$9,(E44*$CG$9/2),IF(CB44=$CF$11,(E44*$CG$11/2),0)) -> 214.5 | BV44: =IF(CB44=$CF$9,(E44*$CJ$9/2),IF(CB44=$CF$11,(E44*$CJ$9/2),0)) -> 33 | BW44: =SUM(BS44:BV44) -> 495 | BY44: =BQ44+BW44 -> 495 | CA44: =IFERROR((BE44-BW44),0) -> 1485 | CB44: AFP
B45: ESCOBAR ARBILDO, RUSBER | D45: =IFERROR(VLOOKUP(B45,'DATOS GRALES 1'!$B$2:$E$91,4,0),"") -> PEON | E45: =IF(D45="",0,IF(D45="PEON",3300,4200)) -> 3300 | F45: =IFERROR((E45/30),"") -> 110 | H45: SI | I45: SI | J45: SI | K45: SI | L45: SI | M45: SI | N45: SI | O45: SI | P45: SI | Q45: SI | R45: SI | S45: SI | T45: SI | U45: SI | V45: SI | W45: SI | X45: SI | Y45: SI | AZ45: =IF(COUNTIF(H45:AX45,"SI")=0,"",COUNTIF(H45:AX45,"SI")) -> 18 | BA45: =IF(COUNTIF(H45:AX45,"NO")=0,"",COUNTIF(H45:AX45,"NO")) | BB45: =COUNTIF(H45:AL45,"MED") -> 0 | BC45: =IF(SUM(AZ45:BB45)=0,"",SUM(AZ45:BB45)) -> 18 | BE45: =IFERROR((F45/2*BB45)+(AZ45*F45),"") -> 1980 | BF45: =_xlfn.XLOOKUP(B45,'TAREO HORAS EXTRAS'!$C$15:$C$51,'TAREO HORAS EXTRAS'!$AO$15:$AO$51,0) -> 3 | BG45: =IFERROR((F45/8*BF45),"") -> 41.25 | BQ45: =BJ45+BL45+BN45+BP45 -> 0 | BS45: =IF(CB45=$CF$9,(E45*$CG$9/2),IF(CB45=$CF$11,(E45*$CG$11/2),0)) -> 214.5 | BT45: =IF(CB45=$CF$9,(E45*$CJ$9/2),IF(CB45=$CF$11,(E45*$CJ$9/2),0)) -> 33 | BU45: =IF(CB45=$CF$9,(E45*$CG$9/2),IF(CB45=$CF$11,(E45*$CG$11/2),0)) -> 214.5 | BV45: =IF(CB45=$CF$9,(E45*$CJ$9/2),IF(CB45=$CF$11,(E45*$CJ$9/2),0)) -> 33 | BW45: =SUM(BS45:BV45) -> 495 | BY45: =BQ45+BW45 -> 495 | CA45: =IFERROR((BE45-BW45),0) -> 1485 | CB45: AFP
B46: CHAVEZ MONTALICO, ISAAC | D46: =IFERROR(VLOOKUP(B46,'DATOS GRALES 1'!$B$2:$E$91,4,0),"") -> OPERARIO | E46: =IF(D46="",0,IF(D46="PEON",3300,4200)) -> 4200 | F46: =IFERROR((E46/30),"") -> 140 | H46: SI | I46: SI | J46: SI | K46: SI | L46: SI | M46: SI | N46: SI | O46: SI | P46: SI | Q46: SI | R46: SI | S46: SI | T46: SI | U46: SI | V46: SI | W46: SI | X46: SI | Y46: SI | AZ46: =IF(COUNTIF(H46:AX46,"SI")=0,"",COUNTIF(H46:AX46,"SI")) -> 18 | BA46: =IF(COUNTIF(H46:AX46,"NO")=0,"",COUNTIF(H46:AX46,"NO")) | BB46: =COUNTIF(H46:AL46,"MED") -> 0 | BC46: =IF(SUM(AZ46:BB46)=0,"",SUM(AZ46:BB46)) -> 18 | BE46: =IFERROR((F46/2*BB46)+(AZ46*F46),"") -> 2520 | BF46: =_xlfn.XLOOKUP(B46,'TAREO HORAS EXTRAS'!$C$15:$C$51,'TAREO HORAS EXTRAS'!$AO$15:$AO$51,0) -> 3 | BG46: =IFERROR((F46/8*BF46),"") -> 52.5 | BQ46: =BJ46+BL46+BN46+BP46 -> 0 | BS46: =IF(CB46=$CF$9,(E46*$CG$9/2),IF(CB46=$CF$11,(E46*$CG$11/2),0)) -> 273 | BT46: =IF(CB46=$CF$9,(E46*$CJ$9/2),IF(CB46=$CF$11,(E46*$CJ$9/2),0)) -> 42 | BU46: =IF(CB46=$CF$9,(E46*$CG$9/2),IF(CB46=$CF$11,(E46*$CG$11/2),0)) -> 273 | BV46: =IF(CB46=$CF$9,(E46*$CJ$9/2),IF(CB46=$CF$11,(E46*$CJ$9/2),0)) -> 42 | BW46: =SUM(BS46:BV46) -> 630 | BY46: =BQ46+BW46 -> 630 | CA46: =IFERROR((BE46-BW46),0) -> 1890 | CB46: AFP
B47: NAVARRO LOZANO, MARCO MANUEL | D47: =IFERROR(VLOOKUP(B47,'DATOS GRALES 1'!$B$2:$E$91,4,0),"") -> OPERARIO | E47: =IF(D47="",0,IF(D47="PEON",3300,4200)) -> 4200 | F47: =IFERROR((E47/30),"") -> 140 | H47: SI | I47: SI | J47: SI | K47: SI | L47: SI | M47: SI | N47: SI | O47: SI | P47: SI | Q47: SI | R47: SI | S47: SI | T47: SI | U47: SI | V47: SI | W47: SI | X47: SI | Y47: SI | AZ47: =IF(COUNTIF(H47:AX47,"SI")=0,"",COUNTIF(H47:AX47,"SI")) -> 18 | BA47: =IF(COUNTIF(H47:AX47,"NO")=0,"",COUNTIF(H47:AX47,"NO")) | BB47: =COUNTIF(H47:AL47,"MED") -> 0 | BC47: =IF(SUM(AZ47:BB47)=0,"",SUM(AZ47:BB47)) -> 18 | BE47: =IFERROR((F47/2*BB47)+(AZ47*F47),"") -> 2520 | BF47: =_xlfn.XLOOKUP(B47,'TAREO HORAS EXTRAS'!$C$15:$C$51,'TAREO HORAS EXTRAS'!$AO$15:$AO$51,0) -> 0 | BG47: =IFERROR((F47/8*BF47),"") -> 0 | BQ47: =BJ47+BL47+BN47+BP47 -> 0 | BS47: =IF(CB47=$CF$9,(E47*$CG$9/2),IF(CB47=$CF$11,(E47*$CG$11/2),0)) -> 273 | BT47: =IF(CB47=$CF$9,(E47*$CJ$9/2),IF(CB47=$CF$11,(E47*$CJ$9/2),0)) -> 42 | BU47: =IF(CB47=$CF$9,(E47*$CG$9/2),IF(CB47=$CF$11,(E47*$CG$11/2),0)) -> 273 | BV47: =IF(CB47=$CF$9,(E47*$CJ$9/2),IF(CB47=$CF$11,(E47*$CJ$9/2),0)) -> 42 | BW47: =SUM(BS47:BV47) -> 630 | BY47: =BQ47+BW47 -> 630 | CA47: =IFERROR((BE47-BW47),0) -> 1890 | CB47: AFP
B48: ARAPA PARQUE, ENOC | D48: =IFERROR(VLOOKUP(B48,'DATOS GRALES 1'!$B$2:$E$91,4,0),"") -> OPERARIO | E48: =IF(D48="",0,IF(D48="PEON",3300,4200)) -> 4200 | F48: =IFERROR((E48/30),"") -> 140 | N48: SI | O48: SI | P48: SI | Q48: SI | R48: SI | S48: SI | T48: SI | U48: SI | V48: SI | W48: SI | X48: SI | AZ48: =IF(COUNTIF(H48:AX48,"SI")=0,"",COUNTIF(H48:AX48,"SI")) -> 11 | BA48: =IF(COUNTIF(H48:AX48,"NO")=0,"",COUNTIF(H48:AX48,"NO")) | BB48: =COUNTIF(H48:AL48,"MED") -> 0 | BC48: =IF(SUM(AZ48:BB48)=0,"",SUM(AZ48:BB48)) -> 11 | BE48: =IFERROR((F48/2*BB48)+(AZ48*F48),"") -> 1540 | BF48: =_xlfn.XLOOKUP(B48,'TAREO HORAS EXTRAS'!$C$15:$C$51,'TAREO HORAS EXTRAS'!$AO$15:$AO$51,0) -> 2 | BG48: =IFERROR((F48/8*BF48),"") -> 35 | BQ48: =BJ48+BL48+BN48+BP48 -> 0 | BS48: =IF(CB48=$CF$9,(E48*$CG$9/2),IF(CB48=$CF$11,(E48*$CG$11/2),0)) -> 273 | BT48: =IF(CB48=$CF$9,(E48*$CJ$9/2),IF(CB48=$CF$11,(E48*$CJ$9/2),0)) -> 42 | BU48: =IF(CB48=$CF$9,(E48*$CG$9/2),IF(CB48=$CF$11,(E48*$CG$11/2),0)) -> 273 | BV48: =IF(CB48=$CF$9,(E48*$CJ$9/2),IF(CB48=$CF$11,(E48*$CJ$9/2),0)) -> 42 | BW48: =SUM(BS48:BV48) -> 630 | BY48: =BQ48+BW48 -> 630 | CA48: =IFERROR((BE48-BW48),0) -> 910 | CB48: AFP
B49: LAQUIHUANACO PACA, BARTOLOME | D49: =IFERROR(VLOOKUP(B49,'DATOS GRALES 1'!$B$2:$E$91,4,0),"") -> OPERARIO | E49: =IF(D49="",0,IF(D49="PEON",3300,4200)) -> 4200 | F49: =IFERROR((E49/30),"") -> 140 | V49: SI | W49: SI | X49: SI | AZ49: =IF(COUNTIF(H49:AX49,"SI")=0,"",COUNTIF(H49:AX49,"SI")) -> 3 | BA49: =IF(COUNTIF(H49:AX49,"NO")=0,"",COUNTIF(H49:AX49,"NO")) | BB49: =COUNTIF(H49:AL49,"MED") -> 0 | BC49: =IF(SUM(AZ49:BB49)=0,"",SUM(AZ49:BB49)) -> 3 | BE49: =IFERROR((F49/2*BB49)+(AZ49*F49),"") -> 420 | BF49: =_xlfn.XLOOKUP(B49,'TAREO HORAS EXTRAS'!$C$15:$C$51,'TAREO HORAS EXTRAS'!$AO$15:$AO$51,0) -> 0 | BG49: =IFERROR((F49/8*BF49),"") -> 0 | BQ49: =BJ49+BL49+BN49+BP49 -> 0 | BS49: =IF(CB49=$CF$9,(E49*$CG$9/2),IF(CB49=$CF$11,(E49*$CG$11/2),0)) -> 273 | BT49: =IF(CB49=$CF$9,(E49*$CJ$9/2),IF(CB49=$CF$11,(E49*$CJ$9/2),0)) -> 42 | BU49: =IF(CB49=$CF$9,(E49*$CG$9/2),IF(CB49=$CF$11,(E49*$CG$11/2),0)) -> 273 | BV49: =IF(CB49=$CF$9,(E49*$CJ$9/2),IF(CB49=$CF$11,(E49*$CJ$9/2),0)) -> 42 | BW49: =SUM(BS49:BV49) -> 630 | BY49: =BQ49+BW49 -> 630 | CA49: =IFERROR((BE49-BW49),0) -> -210 | CB49: AFP
